[
  {
    "timestamp": 866.00243,
    "can_id": "0x176",
    "raw_data": [
      0,
      0,
      1,
      0,
      0,
      0,
      327,
      20
    ],
    "id": "36096bb9-723f-40f5-a912-f634b6e02d02"
  },
  {
    "timestamp": 866.0055,
    "can_id": "0x176",
    "raw_data": [
      0,
      0,
      0,
      0,
      0,
      0,
      376,
      20
    ],
    "id": "8aba5ae6-6735-49eb-9bad-dd3704e351bf"
  },
  {
    "timestamp": 866.00849,
    "can_id": "0x176",
    "raw_data": [
      0,
      0,
      0,
      0,
      0,
      0,
      521,
      20
    ],
    "id": "ff9e2a34-5780-4026-b126-12da8a5956c4"
  },
  {
    "timestamp": 866.01147,
    "can_id": "0x176",
    "raw_data": [
      0,
      0,
      1,
      0,
      0,
      0,
      580,
      20
    ],
    "id": "1ed59868-b67f-4bd9-9546-a161a1724d66"
  },
  {
    "timestamp": 866.01463,
    "can_id": "0x176",
    "raw_data": [
      0,
      0,
      0,
      0,
      0,
      0,
      20,
      21
    ],
    "id": "55b27d78-1b2e-4bd6-95b5-24863a43d68b"
  },
  {
    "timestamp": 866.01745,
    "can_id": "0x176",
    "raw_data": [
      0,
      0,
      0,
      0,
      0,
      0,
      69,
      21
    ],
    "id": "b223deb0-7263-44d5-9fec-bf8ebd06f562"
  },
  {
    "timestamp": 866.02043,
    "can_id": "0x176",
    "raw_data": [
      0,
      0,
      2,
      0,
      0,
      0,
      101,
      21
    ],
    "id": "9d40eb99-b8a5-46f3-bfbc-f12bf95da435"
  },
  {
    "timestamp": 866.0235,
    "can_id": "0x176",
    "raw_data": [
      0,
      0,
      2,
      0,
      0,
      0,
      258,
      21
    ],
    "id": "d8a5c6e1-b625-48ee-a8ca-beec1e6c46e9"
  },
  {
    "timestamp": 866.02376,
    "can_id": "0x192",
    "raw_data": [
      0,
      0,
      0,
      0,
      1,
      0,
      0,
      0
    ],
    "id": "65ff2cf4-193b-4757-b987-e1193757aacb"
  },
  {
    "timestamp": 866.02402,
    "can_id": "0x1",
    "raw_data": [
      0,
      0,
      0,
      0,
      120,
      5,
      0,
      0
    ],
    "id": "f2f367a3-38e6-4176-b6c0-c3131f0f56ff"
  },
  {
    "timestamp": 866.02658,
    "can_id": "0x176",
    "raw_data": [
      0,
      0,
      1,
      0,
      0,
      0,
      295,
      21
    ],
    "id": "2956fc32-c35f-454d-8a4c-bc962282a6c2"
  },
  {
    "timestamp": 866.02956,
    "can_id": "0x176",
    "raw_data": [
      0,
      0,
      0,
      0,
      0,
      0,
      326,
      21
    ],
    "id": "7043d8b9-f3f4-4e49-b9b0-8bde746283d0"
  },
  {
    "timestamp": 866.03255,
    "can_id": "0x176",
    "raw_data": [
      0,
      0,
      2,
      0,
      0,
      0,
      371,
      21
    ],
    "id": "aaf47d53-d033-438e-a99f-535a4e80048b"
  },
  {
    "timestamp": 866.03554,
    "can_id": "0x176",
    "raw_data": [
      0,
      0,
      2,
      0,
      0,
      0,
      533,
      21
    ],
    "id": "a8ae35d5-adbd-4ae7-8b82-92d674c80ba8"
  },
  {
    "timestamp": 866.03852,
    "can_id": "0x176",
    "raw_data": [
      0,
      0,
      0,
      0,
      0,
      0,
      552,
      21
    ],
    "id": "508bf60a-a04f-4f62-9405-93b2931d6e73"
  },
  {
    "timestamp": 866.04151,
    "can_id": "0x176",
    "raw_data": [
      0,
      0,
      0,
      0,
      0,
      0,
      579,
      21
    ],
    "id": "df89ab9a-fee3-45b9-91f8-f619fb9a8e8a"
  },
  {
    "timestamp": 866.0445,
    "can_id": "0x176",
    "raw_data": [
      0,
      0,
      0,
      0,
      0,
      0,
      17,
      22
    ],
    "id": "c7c0ca39-ade8-4045-b5a9-e3e3c9f98844"
  },
  {
    "timestamp": 866.04748,
    "can_id": "0x176",
    "raw_data": [
      0,
      0,
      1,
      0,
      0,
      0,
      56,
      22
    ],
    "id": "63ece2b8-d387-47fc-864e-b39da46d4983"
  },
  {
    "timestamp": 866.05047,
    "can_id": "0x176",
    "raw_data": [
      0,
      0,
      1,
      0,
      0,
      0,
      96,
      22
    ],
    "id": "998b0fad-6f0e-427c-8926-1fcee5846eb6"
  },
  {
    "timestamp": 866.05346,
    "can_id": "0x176",
    "raw_data": [
      0,
      0,
      0,
      0,
      0,
      0,
      121,
      22
    ],
    "id": "ed381ccb-c13b-4095-849f-868e38b2fe37"
  },
  {
    "timestamp": 866.05644,
    "can_id": "0x176",
    "raw_data": [
      0,
      0,
      1,
      0,
      0,
      0,
      260,
      22
    ],
    "id": "c4a50851-9b46-4cf7-8378-bf61ab014551"
  },
  {
    "timestamp": 866.05943,
    "can_id": "0x176",
    "raw_data": [
      0,
      0,
      0,
      0,
      0,
      0,
      296,
      22
    ],
    "id": "68d94b89-070c-430e-9fb4-08c466c8afd4"
  },
  {
    "timestamp": 866.0625,
    "can_id": "0x176",
    "raw_data": [
      0,
      0,
      0,
      0,
      0,
      0,
      338,
      22
    ],
    "id": "b7901d08-a6d0-4c2b-ab56-956e0ce3629f"
  },
  {
    "timestamp": 866.06549,
    "can_id": "0x176",
    "raw_data": [
      0,
      0,
      0,
      0,
      0,
      0,
      372,
      22
    ],
    "id": "7df0349a-0305-481c-9cf4-d5bd9ac1188f"
  },
  {
    "timestamp": 866.06847,
    "can_id": "0x176",
    "raw_data": [
      0,
      0,
      0,
      0,
      0,
      0,
      512,
      22
    ],
    "id": "1d14ee07-eca8-40d3-a063-0b4203ac0484"
  },
  {
    "timestamp": 866.07146,
    "can_id": "0x176",
    "raw_data": [
      0,
      0,
      2,
      0,
      0,
      0,
      519,
      22
    ],
    "id": "77acbe97-7a9b-4579-bc38-09c443ee05d3"
  },
  {
    "timestamp": 866.07172,
    "can_id": "0x172",
    "raw_data": [
      0,
      0,
      0,
      0,
      89,
      2,
      1,
      0
    ],
    "id": "685c92f5-7315-4970-932d-14ac2078795a"
  },
  {
    "timestamp": 866.07197,
    "can_id": "0x171",
    "raw_data": [
      0,
      0,
      0,
      0,
      0,
      0,
      0,
      0
    ],
    "id": "fb4063f3-f12b-472e-a56b-3fa25f47efc5"
  },
  {
    "timestamp": 866.07223,
    "can_id": "0x170",
    "raw_data": [
      4,
      0,
      9,
      0,
      0,
      0,
      0,
      1
    ],
    "id": "b999ef5e-34a6-4f36-beef-a16d86e288d7"
  },
  {
    "timestamp": 866.07249,
    "can_id": "0x168",
    "raw_data": [
      52,
      0,
      311,
      593,
      593,
      597,
      1,
      0
    ],
    "id": "b9829532-2ec8-48a5-af40-894883bccc3d"
  },
  {
    "timestamp": 866.07274,
    "can_id": "0x167",
    "raw_data": [
      534,
      22,
      0,
      0,
      39,
      0,
      32,
      0
    ],
    "id": "5849f293-90b6-4aef-8f09-2c80dced8090"
  },
  {
    "timestamp": 866.07308,
    "can_id": "0x166",
    "raw_data": [
      2,
      0,
      1,
      0,
      5,
      0,
      0,
      0
    ],
    "id": "a276e97a-3ba7-4917-9aac-2bf33645be6a"
  },
  {
    "timestamp": 866.07334,
    "can_id": "0x165",
    "raw_data": [
      272,
      19,
      0,
      0,
      0,
      0,
      354,
      0
    ],
    "id": "50c055f7-3db8-4a96-a713-a33fc8006c20"
  },
  {
    "timestamp": 866.07359,
    "can_id": "0x192",
    "raw_data": [
      0,
      0,
      0,
      0,
      1,
      0,
      0,
      0
    ],
    "id": "199864e5-2c88-4cb9-b12c-9c33b6895695"
  },
  {
    "timestamp": 866.07394,
    "can_id": "0x1",
    "raw_data": [
      0,
      0,
      0,
      0,
      119,
      5,
      0,
      0
    ],
    "id": "de360ac1-2308-4458-91a2-752218ac72cb"
  },
  {
    "timestamp": 866.07436,
    "can_id": "0x176",
    "raw_data": [
      0,
      0,
      0,
      0,
      0,
      0,
      551,
      22
    ],
    "id": "c84d5ad7-b4f9-4b4a-acd5-6ff23364d57e"
  },
  {
    "timestamp": 866.07752,
    "can_id": "0x176",
    "raw_data": [
      0,
      0,
      0,
      0,
      0,
      0,
      580,
      22
    ],
    "id": "9d190362-f31a-4898-8dd7-5c4807c46e4f"
  },
  {
    "timestamp": 866.08042,
    "can_id": "0x176",
    "raw_data": [
      0,
      0,
      597,
      597,
      0,
      0,
      4,
      23
    ],
    "id": "5c00a368-e9ca-4069-882a-9244182db12e"
  },
  {
    "timestamp": 866.08349,
    "can_id": "0x176",
    "raw_data": [
      0,
      0,
      2,
      0,
      0,
      0,
      48,
      23
    ],
    "id": "0f7f6652-86e7-48de-83fb-0c93895d29c4"
  },
  {
    "timestamp": 866.08657,
    "can_id": "0x176",
    "raw_data": [
      0,
      0,
      0,
      0,
      0,
      0,
      80,
      23
    ],
    "id": "704d9437-f858-43ac-a622-de100de12d4b"
  },
  {
    "timestamp": 866.08947,
    "can_id": "0x176",
    "raw_data": [
      0,
      0,
      1,
      0,
      0,
      0,
      103,
      23
    ],
    "id": "3f6b7cde-f993-4f91-80f7-48640c11c580"
  },
  {
    "timestamp": 866.09245,
    "can_id": "0x176",
    "raw_data": [
      0,
      0,
      0,
      0,
      0,
      0,
      129,
      23
    ],
    "id": "55b52121-c12b-4830-9a5a-2b7ba7637803"
  },
  {
    "timestamp": 866.09544,
    "can_id": "0x176",
    "raw_data": [
      0,
      0,
      0,
      0,
      0,
      0,
      137,
      23
    ],
    "id": "0532d658-cfd2-4093-87e4-44b4790b93e1"
  },
  {
    "timestamp": 866.09843,
    "can_id": "0x176",
    "raw_data": [
      0,
      0,
      0,
      0,
      0,
      0,
      288,
      23
    ],
    "id": "856ad274-a1bb-46b3-ac30-2fdceb55bbec"
  },
  {
    "timestamp": 866.10141,
    "can_id": "0x176",
    "raw_data": [
      0,
      0,
      1,
      0,
      0,
      0,
      297,
      23
    ],
    "id": "a059f26e-ef7c-41f6-9089-bcedd3458ca9"
  },
  {
    "timestamp": 866.1044,
    "can_id": "0x176",
    "raw_data": [
      0,
      0,
      0,
      0,
      0,
      0,
      341,
      23
    ],
    "id": "5bc18760-99bf-49cb-b1e6-fb80d52de4cc"
  },
  {
    "timestamp": 866.10747,
    "can_id": "0x176",
    "raw_data": [
      0,
      0,
      0,
      0,
      0,
      0,
      356,
      23
    ],
    "id": "f09210d2-060c-4c86-9a68-5b8323529a3f"
  },
  {
    "timestamp": 866.11037,
    "can_id": "0x176",
    "raw_data": [
      0,
      0,
      1,
      0,
      0,
      0,
      384,
      23
    ],
    "id": "9ba73b2a-cf8f-424d-be59-e40accab4796"
  },
  {
    "timestamp": 866.11345,
    "can_id": "0x176",
    "raw_data": [
      0,
      0,
      1,
      0,
      0,
      0,
      407,
      23
    ],
    "id": "924ad4c7-c86a-46b3-bd8e-506cb52440d6"
  },
  {
    "timestamp": 866.11643,
    "can_id": "0x176",
    "raw_data": [
      0,
      0,
      0,
      0,
      0,
      0,
      533,
      23
    ],
    "id": "3d7d6603-d604-49db-af2e-59ddd5a5cd26"
  },
  {
    "timestamp": 866.11942,
    "can_id": "0x176",
    "raw_data": [
      0,
      0,
      0,
      0,
      0,
      0,
      545,
      23
    ],
    "id": "5044927f-0a14-45c0-974e-97d099d975aa"
  },
  {
    "timestamp": 866.12241,
    "can_id": "0x176",
    "raw_data": [
      0,
      0,
      2,
      0,
      0,
      0,
      564,
      23
    ],
    "id": "3293686d-f6af-4534-81e0-72dc582afb79"
  },
  {
    "timestamp": 866.12343,
    "can_id": "0x192",
    "raw_data": [
      0,
      0,
      0,
      0,
      1,
      0,
      0,
      0
    ],
    "id": "ec8fe794-199c-4aab-ac88-8c781a45f603"
  },
  {
    "timestamp": 866.12377,
    "can_id": "0x1",
    "raw_data": [
      0,
      0,
      0,
      0,
      117,
      5,
      0,
      0
    ],
    "id": "0e7189c1-1899-46f2-98fe-053f49995c99"
  },
  {
    "timestamp": 866.12548,
    "can_id": "0x176",
    "raw_data": [
      0,
      0,
      2,
      0,
      0,
      0,
      592,
      23
    ],
    "id": "f04b7ba5-6dbd-46b8-baa1-1c00aca9633d"
  },
  {
    "timestamp": 866.12838,
    "can_id": "0x176",
    "raw_data": [
      0,
      0,
      0,
      0,
      0,
      0,
      3,
      24
    ],
    "id": "d41d459b-d209-4ce4-8533-ac21b9559110"
  },
  {
    "timestamp": 866.13742,
    "can_id": "0x176",
    "raw_data": [
      0,
      0,
      1,
      0,
      0,
      0,
      37,
      24
    ],
    "id": "2c449b22-2f71-4bb2-96cc-1b1972872fb2"
  },
  {
    "timestamp": 866.14058,
    "can_id": "0x176",
    "raw_data": [
      0,
      0,
      597,
      597,
      0,
      0,
      96,
      24
    ],
    "id": "28914a02-f23d-4800-8f95-9946204c67a7"
  },
  {
    "timestamp": 866.14348,
    "can_id": "0x176",
    "raw_data": [
      0,
      0,
      3,
      0,
      0,
      0,
      120,
      24
    ],
    "id": "329b5d3f-bdba-4e5e-b88e-06b7e4f53506"
  },
  {
    "timestamp": 866.14638,
    "can_id": "0x176",
    "raw_data": [
      0,
      0,
      1,
      0,
      0,
      0,
      136,
      24
    ],
    "id": "d7cba412-4d9a-4202-92b1-5a4e36a0437a"
  },
  {
    "timestamp": 866.14946,
    "can_id": "0x176",
    "raw_data": [
      0,
      0,
      1,
      0,
      0,
      0,
      147,
      24
    ],
    "id": "10ece9ae-9069-4e16-9439-b34fba7769fb"
  },
  {
    "timestamp": 866.15244,
    "can_id": "0x176",
    "raw_data": [
      0,
      0,
      0,
      0,
      0,
      0,
      272,
      24
    ],
    "id": "00e6823e-712a-42f3-a585-c8edb0fbe513"
  },
  {
    "timestamp": 866.15543,
    "can_id": "0x176",
    "raw_data": [
      0,
      0,
      1,
      0,
      0,
      0,
      281,
      24
    ],
    "id": "d86cdd80-75bb-4b52-b656-7ca3ff1e63ca"
  },
  {
    "timestamp": 866.15842,
    "can_id": "0x176",
    "raw_data": [
      0,
      0,
      0,
      0,
      0,
      0,
      304,
      24
    ],
    "id": "f1f7d93f-e63c-4c18-8b90-8c96aa17de37"
  },
  {
    "timestamp": 866.16149,
    "can_id": "0x176",
    "raw_data": [
      0,
      0,
      0,
      0,
      0,
      0,
      328,
      24
    ],
    "id": "6f5d13ef-9dd9-402f-be47-9006970ca04d"
  },
  {
    "timestamp": 866.16447,
    "can_id": "0x176",
    "raw_data": [
      0,
      0,
      597,
      597,
      0,
      0,
      340,
      24
    ],
    "id": "f4d137a5-de9b-4aa5-9d72-93fc70f9757c"
  },
  {
    "timestamp": 866.16746,
    "can_id": "0x176",
    "raw_data": [
      0,
      0,
      0,
      0,
      0,
      0,
      357,
      24
    ],
    "id": "5affd5b0-1298-4dd1-8bbc-9268eaa037f8"
  },
  {
    "timestamp": 866.17045,
    "can_id": "0x176",
    "raw_data": [
      0,
      0,
      1,
      0,
      0,
      0,
      372,
      24
    ],
    "id": "cab7549c-c7b4-4b46-9e77-2c38dfa9cd13"
  },
  {
    "timestamp": 866.17343,
    "can_id": "0x176",
    "raw_data": [
      0,
      0,
      0,
      0,
      0,
      0,
      393,
      24
    ],
    "id": "4fa00ae2-024c-4d99-9b0a-07ce67ae18f8"
  },
  {
    "timestamp": 866.17369,
    "can_id": "0x192",
    "raw_data": [
      0,
      0,
      0,
      0,
      1,
      0,
      0,
      0
    ],
    "id": "2906a209-b7d5-4699-b619-1f698c05ab2b"
  },
  {
    "timestamp": 866.17395,
    "can_id": "0x172",
    "raw_data": [
      0,
      0,
      0,
      0,
      147,
      2,
      1,
      0
    ],
    "id": "c301adef-f8d0-4272-b538-33cd1b0aa490"
  },
  {
    "timestamp": 866.1742,
    "can_id": "0x1",
    "raw_data": [
      0,
      0,
      0,
      0,
      119,
      5,
      0,
      0
    ],
    "id": "becf6ec5-f906-4eba-b131-16be2bef24a7"
  },
  {
    "timestamp": 866.17446,
    "can_id": "0x171",
    "raw_data": [
      0,
      0,
      0,
      0,
      0,
      0,
      0,
      0
    ],
    "id": "8eb0a640-fbc7-4e45-bb71-c28b061637ac"
  },
  {
    "timestamp": 866.17471,
    "can_id": "0x170",
    "raw_data": [
      4,
      0,
      9,
      0,
      0,
      0,
      0,
      1
    ],
    "id": "30bdc0e7-90c9-4d63-9114-00d188ec7d33"
  },
  {
    "timestamp": 866.17489,
    "can_id": "0x168",
    "raw_data": [
      52,
      0,
      311,
      593,
      579,
      597,
      0,
      0
    ],
    "id": "4d1242bb-35ec-4367-adaa-2a22b840e7e0"
  },
  {
    "timestamp": 866.17514,
    "can_id": "0x167",
    "raw_data": [
      393,
      24,
      0,
      0,
      39,
      0,
      17,
      0
    ],
    "id": "7cecbd37-130e-48ae-af4d-7d4bcf3ffebc"
  },
  {
    "timestamp": 866.1754,
    "can_id": "0x166",
    "raw_data": [
      2,
      0,
      1,
      0,
      0,
      0,
      0,
      0
    ],
    "id": "ed3d4e9e-a168-4eac-b12b-0e70c2bdcc8f"
  },
  {
    "timestamp": 866.17565,
    "can_id": "0x165",
    "raw_data": [
      273,
      19,
      0,
      0,
      0,
      0,
      353,
      0
    ],
    "id": "012f1066-3b1f-4f6c-8fb7-0e71795c886a"
  },
  {
    "timestamp": 866.17642,
    "can_id": "0x176",
    "raw_data": [
      0,
      0,
      597,
      597,
      0,
      0,
      391,
      24
    ],
    "id": "55f251cb-a3e1-4452-85ae-6c837c096e1a"
  },
  {
    "timestamp": 866.17941,
    "can_id": "0x176",
    "raw_data": [
      0,
      0,
      0,
      0,
      0,
      0,
      519,
      24
    ],
    "id": "9452ba8a-a9f5-4090-8d03-8e5c0d882448"
  },
  {
    "timestamp": 866.18239,
    "can_id": "0x176",
    "raw_data": [
      0,
      0,
      0,
      0,
      0,
      0,
      544,
      24
    ],
    "id": "b4c94092-530f-4a98-b98c-7bedfb46fecc"
  },
  {
    "timestamp": 866.18547,
    "can_id": "0x176",
    "raw_data": [
      0,
      0,
      0,
      0,
      0,
      0,
      551,
      24
    ],
    "id": "1c8a8b8c-c4ab-4acd-9c3e-ec23b14b5185"
  },
  {
    "timestamp": 866.18837,
    "can_id": "0x176",
    "raw_data": [
      0,
      0,
      0,
      0,
      0,
      0,
      551,
      24
    ],
    "id": "4ce27776-c36b-4d2b-b680-b433f01459a0"
  },
  {
    "timestamp": 866.19153,
    "can_id": "0x176",
    "raw_data": [
      0,
      0,
      1,
      0,
      0,
      0,
      585,
      24
    ],
    "id": "71dac721-5ee0-49e8-83f5-43859ca0046e"
  },
  {
    "timestamp": 866.19443,
    "can_id": "0x176",
    "raw_data": [
      0,
      0,
      2,
      0,
      0,
      0,
      585,
      24
    ],
    "id": "61a288ec-3c8c-431e-aaa6-51c62455e4a7"
  },
  {
    "timestamp": 866.19741,
    "can_id": "0x176",
    "raw_data": [
      0,
      0,
      1,
      0,
      0,
      0,
      4,
      25
    ],
    "id": "d6e7e615-e103-45f8-aafe-8bf7f794cbb5"
  },
  {
    "timestamp": 866.2004,
    "can_id": "0x176",
    "raw_data": [
      0,
      0,
      0,
      0,
      0,
      0,
      8,
      25
    ],
    "id": "d6a8ea46-ae65-4329-927f-f7b0138cd54e"
  },
  {
    "timestamp": 866.20356,
    "can_id": "0x176",
    "raw_data": [
      0,
      0,
      0,
      0,
      0,
      0,
      36,
      25
    ],
    "id": "65721a6e-1120-4d9f-b2d7-34b674a11735"
  },
  {
    "timestamp": 866.20646,
    "can_id": "0x176",
    "raw_data": [
      0,
      0,
      3,
      0,
      0,
      0,
      36,
      25
    ],
    "id": "8c5ad85f-8142-4d4d-b793-7601f775b4b6"
  },
  {
    "timestamp": 866.20945,
    "can_id": "0x176",
    "raw_data": [
      0,
      0,
      0,
      0,
      0,
      0,
      80,
      25
    ],
    "id": "c8bd941f-7047-4c2a-9601-bf84b4872c6f"
  },
  {
    "timestamp": 866.21243,
    "can_id": "0x176",
    "raw_data": [
      0,
      0,
      597,
      597,
      0,
      0,
      68,
      25
    ],
    "id": "13ebb835-a12f-4f41-abe5-d64dbfc30e90"
  },
  {
    "timestamp": 866.21542,
    "can_id": "0x176",
    "raw_data": [
      0,
      0,
      1,
      0,
      0,
      0,
      82,
      25
    ],
    "id": "ae025760-675d-4af9-a0c8-06783e7a653a"
  },
  {
    "timestamp": 866.21841,
    "can_id": "0x176",
    "raw_data": [
      0,
      0,
      1,
      0,
      0,
      0,
      99,
      25
    ],
    "id": "1b7cc031-c9f2-4c67-af73-ce61f94f35e5"
  },
  {
    "timestamp": 866.22148,
    "can_id": "0x176",
    "raw_data": [
      0,
      0,
      2,
      0,
      0,
      0,
      116,
      25
    ],
    "id": "2539bd68-a100-40af-8b9f-26bd27a77e15"
  },
  {
    "timestamp": 866.22344,
    "can_id": "0x192",
    "raw_data": [
      0,
      0,
      0,
      0,
      1,
      0,
      0,
      0
    ],
    "id": "164ca158-b1aa-4851-9939-ed67b40e83d2"
  },
  {
    "timestamp": 866.22438,
    "can_id": "0x176",
    "raw_data": [
      0,
      0,
      597,
      597,
      0,
      0,
      112,
      25
    ],
    "id": "ed3627eb-e8e3-40d3-a168-dab3d6744ed3"
  },
  {
    "timestamp": 866.22463,
    "can_id": "0x1",
    "raw_data": [
      0,
      0,
      0,
      0,
      129,
      5,
      0,
      0
    ],
    "id": "d426c74e-9404-4ac1-8502-9266385cfa43"
  },
  {
    "timestamp": 866.22745,
    "can_id": "0x176",
    "raw_data": [
      0,
      0,
      1,
      0,
      0,
      0,
      133,
      25
    ],
    "id": "f8d593f8-164b-47d4-b91c-ef1927e50b56"
  },
  {
    "timestamp": 866.23044,
    "can_id": "0x176",
    "raw_data": [
      0,
      0,
      0,
      0,
      0,
      0,
      144,
      25
    ],
    "id": "9d54b84d-65cb-4c1d-8388-6ba87e20fc48"
  },
  {
    "timestamp": 866.23342,
    "can_id": "0x176",
    "raw_data": [
      0,
      0,
      2,
      0,
      0,
      0,
      261,
      25
    ],
    "id": "59459197-0bbd-4bb4-b7d3-ed46b4e4c600"
  },
  {
    "timestamp": 866.23641,
    "can_id": "0x176",
    "raw_data": [
      0,
      0,
      0,
      0,
      0,
      0,
      261,
      25
    ],
    "id": "84e4ba55-d9a8-4b6b-8524-cf924c846c01"
  },
  {
    "timestamp": 866.2394,
    "can_id": "0x176",
    "raw_data": [
      0,
      0,
      1,
      0,
      0,
      0,
      261,
      25
    ],
    "id": "8a9418df-9c0a-44b9-a35b-3301a43661d6"
  },
  {
    "timestamp": 866.24238,
    "can_id": "0x176",
    "raw_data": [
      0,
      0,
      1,
      0,
      0,
      0,
      276,
      25
    ],
    "id": "280d80f9-606b-4f86-b3be-17256d496bfd"
  },
  {
    "timestamp": 866.24546,
    "can_id": "0x176",
    "raw_data": [
      0,
      0,
      0,
      0,
      0,
      0,
      295,
      25
    ],
    "id": "9596e4f1-4014-4f30-ba77-4ed447228034"
  },
  {
    "timestamp": 866.24844,
    "can_id": "0x176",
    "raw_data": [
      0,
      0,
      1,
      0,
      0,
      0,
      297,
      25
    ],
    "id": "4f2de56d-ef0f-45c8-b78f-b320623049f6"
  },
  {
    "timestamp": 866.25143,
    "can_id": "0x176",
    "raw_data": [
      0,
      0,
      2,
      0,
      0,
      0,
      310,
      25
    ],
    "id": "b73c0cb7-c1d0-4598-9eaa-664da6a807b0"
  },
  {
    "timestamp": 866.25442,
    "can_id": "0x176",
    "raw_data": [
      0,
      0,
      1,
      0,
      0,
      0,
      310,
      25
    ],
    "id": "ab824af7-d117-4929-826a-850de270f30c"
  },
  {
    "timestamp": 866.2574,
    "can_id": "0x176",
    "raw_data": [
      0,
      0,
      0,
      0,
      0,
      0,
      344,
      25
    ],
    "id": "c0fcd590-afbb-4cb6-9716-46402734ec95"
  },
  {
    "timestamp": 866.26039,
    "can_id": "0x176",
    "raw_data": [
      0,
      0,
      0,
      0,
      0,
      0,
      329,
      25
    ],
    "id": "919bcd6f-7564-4caf-aa80-ff0409024ab2"
  },
  {
    "timestamp": 866.26346,
    "can_id": "0x176",
    "raw_data": [
      0,
      0,
      0,
      0,
      0,
      0,
      361,
      25
    ],
    "id": "0676624c-8a9a-4b1a-aef5-0ff65fc3dc2c"
  },
  {
    "timestamp": 866.26662,
    "can_id": "0x176",
    "raw_data": [
      0,
      0,
      0,
      0,
      0,
      0,
      356,
      25
    ],
    "id": "095b084a-69b2-4389-b0a8-a62b76892f8c"
  },
  {
    "timestamp": 866.26943,
    "can_id": "0x176",
    "raw_data": [
      0,
      0,
      0,
      0,
      0,
      0,
      375,
      25
    ],
    "id": "ac9c1aa0-2ba0-4016-bdc2-23a2376af074"
  },
  {
    "timestamp": 866.27242,
    "can_id": "0x176",
    "raw_data": [
      0,
      0,
      0,
      0,
      0,
      0,
      375,
      25
    ],
    "id": "fa4883ca-acae-47fa-afc9-dabd5e3213c3"
  },
  {
    "timestamp": 866.27353,
    "can_id": "0x192",
    "raw_data": [
      0,
      0,
      0,
      0,
      1,
      0,
      0,
      0
    ],
    "id": "b19c8319-4f6f-4934-8512-1bd4ada7d040"
  },
  {
    "timestamp": 866.27387,
    "can_id": "0x1",
    "raw_data": [
      0,
      0,
      0,
      0,
      120,
      5,
      0,
      0
    ],
    "id": "c769a2b8-f043-4db8-ae55-0bee111f68a5"
  },
  {
    "timestamp": 866.27541,
    "can_id": "0x176",
    "raw_data": [
      0,
      0,
      1,
      0,
      0,
      0,
      388,
      25
    ],
    "id": "df72e9bf-796a-441d-9a40-ecd65e969c03"
  },
  {
    "timestamp": 866.27566,
    "can_id": "0x172",
    "raw_data": [
      0,
      0,
      0,
      0,
      295,
      2,
      1,
      0
    ],
    "id": "49469a34-15e2-4c58-bed6-890ff25e1fa4"
  },
  {
    "timestamp": 866.27601,
    "can_id": "0x171",
    "raw_data": [
      0,
      0,
      0,
      0,
      0,
      0,
      0,
      0
    ],
    "id": "1c7a9d9c-39ab-4386-b038-30885faf1890"
  },
  {
    "timestamp": 866.27626,
    "can_id": "0x170",
    "raw_data": [
      4,
      0,
      9,
      0,
      0,
      0,
      0,
      1
    ],
    "id": "281467ea-f603-4b17-8eb8-9a475f475ba8"
  },
  {
    "timestamp": 866.27652,
    "can_id": "0x168",
    "raw_data": [
      52,
      0,
      311,
      593,
      579,
      597,
      1,
      0
    ],
    "id": "78761c37-9b65-4357-8f88-bb9d7e0fd03d"
  },
  {
    "timestamp": 866.27677,
    "can_id": "0x167",
    "raw_data": [
      390,
      25,
      0,
      0,
      34,
      0,
      37,
      0
    ],
    "id": "b05d68cf-1366-4f41-bd1e-0f20d730815a"
  },
  {
    "timestamp": 866.27703,
    "can_id": "0x166",
    "raw_data": [
      4,
      0,
      7,
      0,
      5,
      0,
      0,
      0
    ],
    "id": "2f21abe5-f785-43ef-9071-313e9c7d1e7e"
  },
  {
    "timestamp": 866.27729,
    "can_id": "0x165",
    "raw_data": [
      272,
      19,
      0,
      0,
      0,
      0,
      353,
      0
    ],
    "id": "43184c1d-2483-4af9-aeb9-8e48bff0d502"
  },
  {
    "timestamp": 866.27848,
    "can_id": "0x176",
    "raw_data": [
      0,
      0,
      0,
      0,
      0,
      0,
      388,
      25
    ],
    "id": "1160a034-90ea-44e7-8b72-8d4d9ef859e0"
  },
  {
    "timestamp": 866.28147,
    "can_id": "0x176",
    "raw_data": [
      0,
      0,
      0,
      0,
      0,
      0,
      401,
      25
    ],
    "id": "c81e22b5-8251-404b-a56b-966bfc2e52c6"
  },
  {
    "timestamp": 866.28454,
    "can_id": "0x176",
    "raw_data": [
      0,
      0,
      597,
      597,
      0,
      0,
      409,
      25
    ],
    "id": "f10ba3af-1fce-4126-abdf-26c50c04bed6"
  },
  {
    "timestamp": 866.28744,
    "can_id": "0x176",
    "raw_data": [
      0,
      0,
      0,
      0,
      0,
      0,
      520,
      25
    ],
    "id": "a2c378cb-3d9e-4d11-a71d-ade66200151c"
  },
  {
    "timestamp": 866.29043,
    "can_id": "0x176",
    "raw_data": [
      0,
      0,
      1,
      0,
      0,
      0,
      520,
      25
    ],
    "id": "49735221-2cc5-4c60-920f-2788e7787b89"
  },
  {
    "timestamp": 866.29341,
    "can_id": "0x176",
    "raw_data": [
      0,
      0,
      1,
      0,
      0,
      0,
      520,
      25
    ],
    "id": "09f85a1a-c3b9-4160-b4cc-0ba2b8ceefbe"
  },
  {
    "timestamp": 866.2964,
    "can_id": "0x176",
    "raw_data": [
      0,
      0,
      1,
      0,
      0,
      0,
      520,
      25
    ],
    "id": "6ecf5fa7-f80d-430d-a69e-ed8ec5a9069b"
  },
  {
    "timestamp": 866.29939,
    "can_id": "0x176",
    "raw_data": [
      0,
      0,
      1,
      0,
      0,
      0,
      533,
      25
    ],
    "id": "28aff64c-0ec5-4d80-9ec3-83d29ca7dc98"
  },
  {
    "timestamp": 866.30237,
    "can_id": "0x176",
    "raw_data": [
      0,
      0,
      3,
      0,
      0,
      0,
      567,
      25
    ],
    "id": "c80e44f5-d516-4480-9d32-51df3b23c37a"
  },
  {
    "timestamp": 866.30545,
    "can_id": "0x176",
    "raw_data": [
      0,
      0,
      597,
      597,
      0,
      0,
      569,
      25
    ],
    "id": "1116609b-3515-4e31-a923-629e8aea1a68"
  },
  {
    "timestamp": 866.30843,
    "can_id": "0x176",
    "raw_data": [
      0,
      0,
      2,
      0,
      0,
      0,
      552,
      25
    ],
    "id": "58ebd329-d83d-401a-a4ca-bf0f4d94fc07"
  },
  {
    "timestamp": 866.31142,
    "can_id": "0x176",
    "raw_data": [
      0,
      0,
      0,
      0,
      0,
      0,
      569,
      25
    ],
    "id": "6f90959e-3442-4b97-a5de-b91c0d297d23"
  },
  {
    "timestamp": 866.31441,
    "can_id": "0x176",
    "raw_data": [
      0,
      0,
      1,
      0,
      0,
      0,
      594,
      25
    ],
    "id": "4a99ebf1-7161-4204-93f5-c7dfb6eab0f7"
  },
  {
    "timestamp": 866.31739,
    "can_id": "0x176",
    "raw_data": [
      0,
      0,
      0,
      0,
      0,
      0,
      584,
      25
    ],
    "id": "43717c0e-b09e-45ee-80df-570fef8b62b9"
  },
  {
    "timestamp": 866.32038,
    "can_id": "0x176",
    "raw_data": [
      0,
      0,
      1,
      0,
      0,
      0,
      579,
      25
    ],
    "id": "42a44ba3-b9b8-460a-86cd-0519e3a29d1f"
  },
  {
    "timestamp": 866.32345,
    "can_id": "0x176",
    "raw_data": [
      0,
      0,
      0,
      0,
      0,
      0,
      1,
      32
    ],
    "id": "71da939c-baaf-465b-8406-c4b1bf619a6c"
  },
  {
    "timestamp": 866.32371,
    "can_id": "0x192",
    "raw_data": [
      0,
      0,
      0,
      0,
      1,
      0,
      0,
      0
    ],
    "id": "66de75ca-0c3a-41e1-b6e4-839631b5700d"
  },
  {
    "timestamp": 866.32405,
    "can_id": "0x1",
    "raw_data": [
      0,
      0,
      0,
      0,
      118,
      5,
      0,
      0
    ],
    "id": "e48a97b2-5d36-4570-84aa-c318c0035ebd"
  },
  {
    "timestamp": 866.32652,
    "can_id": "0x176",
    "raw_data": [
      0,
      0,
      1,
      0,
      0,
      0,
      5,
      32
    ],
    "id": "0c8f0f8c-e81d-4d8b-b973-76e75c69d963"
  },
  {
    "timestamp": 866.32968,
    "can_id": "0x176",
    "raw_data": [
      0,
      0,
      0,
      0,
      0,
      0,
      9,
      32
    ],
    "id": "251f45f9-e54a-41fa-986c-64978764bc35"
  },
  {
    "timestamp": 866.3325,
    "can_id": "0x176",
    "raw_data": [
      0,
      0,
      2,
      0,
      0,
      0,
      33,
      32
    ],
    "id": "f49b515f-cb45-4e7e-b060-4672c2434988"
  },
  {
    "timestamp": 866.33548,
    "can_id": "0x176",
    "raw_data": [
      0,
      0,
      0,
      0,
      0,
      0,
      33,
      32
    ],
    "id": "1303bc76-0d2c-4a51-9d59-227366acb9fe"
  },
  {
    "timestamp": 866.33847,
    "can_id": "0x176",
    "raw_data": [
      0,
      0,
      1,
      0,
      0,
      0,
      22,
      32
    ],
    "id": "ef6ec2b3-52ad-4739-bc14-f3ab00bd48f4"
  },
  {
    "timestamp": 866.34146,
    "can_id": "0x176",
    "raw_data": [
      0,
      0,
      1,
      0,
      0,
      0,
      35,
      32
    ],
    "id": "0d59484f-4052-4139-abae-df27ea2916be"
  },
  {
    "timestamp": 866.34444,
    "can_id": "0x176",
    "raw_data": [
      0,
      0,
      0,
      0,
      0,
      0,
      37,
      32
    ],
    "id": "f13403c4-d7a2-4144-a565-0a57f982ce57"
  },
  {
    "timestamp": 866.34743,
    "can_id": "0x176",
    "raw_data": [
      0,
      0,
      597,
      597,
      0,
      0,
      37,
      32
    ],
    "id": "2570c7fe-314a-4379-ba0c-af8a35dab4ab"
  },
  {
    "timestamp": 866.35042,
    "can_id": "0x176",
    "raw_data": [
      0,
      0,
      0,
      0,
      0,
      0,
      39,
      32
    ],
    "id": "14f0549a-8e85-4362-b210-42a7f4a76030"
  },
  {
    "timestamp": 866.3534,
    "can_id": "0x176",
    "raw_data": [
      0,
      0,
      0,
      0,
      0,
      0,
      56,
      32
    ],
    "id": "3aeff828-4a10-4a3d-a544-daccab753281"
  },
  {
    "timestamp": 866.35639,
    "can_id": "0x176",
    "raw_data": [
      0,
      0,
      0,
      0,
      0,
      0,
      54,
      32
    ],
    "id": "ad7a86e1-b85e-4708-bd43-1a2954ca5174"
  },
  {
    "timestamp": 866.35946,
    "can_id": "0x176",
    "raw_data": [
      0,
      0,
      0,
      0,
      0,
      0,
      56,
      32
    ],
    "id": "26e025db-d705-4c30-ac0d-0aa5b7896d7b"
  },
  {
    "timestamp": 866.36245,
    "can_id": "0x176",
    "raw_data": [
      0,
      0,
      0,
      0,
      0,
      0,
      67,
      32
    ],
    "id": "5421ffc5-73c4-4fd9-9017-46d9e826ab96"
  },
  {
    "timestamp": 866.36543,
    "can_id": "0x176",
    "raw_data": [
      0,
      0,
      0,
      0,
      0,
      0,
      67,
      32
    ],
    "id": "1954b089-ecf0-41a9-8bee-d697a449d583"
  },
  {
    "timestamp": 866.36842,
    "can_id": "0x176",
    "raw_data": [
      0,
      0,
      0,
      0,
      0,
      0,
      71,
      32
    ],
    "id": "0cc41238-8846-43b6-b232-24acfbfac4ef"
  },
  {
    "timestamp": 866.37141,
    "can_id": "0x176",
    "raw_data": [
      0,
      0,
      2,
      0,
      0,
      0,
      69,
      32
    ],
    "id": "a5a395cf-0128-4d59-89b8-394f2ac90aa2"
  },
  {
    "timestamp": 866.37354,
    "can_id": "0x192",
    "raw_data": [
      0,
      0,
      0,
      0,
      1,
      0,
      0,
      0
    ],
    "id": "13bcde75-46a8-49f2-ba61-7ce130519fe1"
  },
  {
    "timestamp": 866.37439,
    "can_id": "0x176",
    "raw_data": [
      0,
      0,
      1,
      0,
      0,
      0,
      86,
      32
    ],
    "id": "a0eaa9f6-693e-4506-aaf6-7a15f4476aca"
  },
  {
    "timestamp": 866.37465,
    "can_id": "0x1",
    "raw_data": [
      0,
      0,
      0,
      0,
      120,
      5,
      0,
      0
    ],
    "id": "4b5b9a2b-555d-4230-b890-457cd44fa7b3"
  },
  {
    "timestamp": 866.37747,
    "can_id": "0x176",
    "raw_data": [
      0,
      0,
      1,
      0,
      0,
      0,
      88,
      32
    ],
    "id": "0c05a549-3530-4237-98ec-8f1014d2b393"
  },
  {
    "timestamp": 866.37772,
    "can_id": "0x172",
    "raw_data": [
      0,
      0,
      0,
      0,
      353,
      2,
      1,
      0
    ],
    "id": "6c1a2cf5-3741-49ed-9608-a0e42785be1f"
  },
  {
    "timestamp": 866.37798,
    "can_id": "0x171",
    "raw_data": [
      0,
      0,
      0,
      0,
      0,
      0,
      0,
      0
    ],
    "id": "281d2fbf-dfee-40ba-940e-54d7556eb611"
  },
  {
    "timestamp": 866.37832,
    "can_id": "0x170",
    "raw_data": [
      4,
      0,
      9,
      0,
      0,
      0,
      0,
      1
    ],
    "id": "5c45a9fb-484c-4394-8c0b-e2925e1a1be9"
  },
  {
    "timestamp": 866.37849,
    "can_id": "0x168",
    "raw_data": [
      52,
      0,
      311,
      593,
      582,
      597,
      1,
      0
    ],
    "id": "25112890-7ff0-4b68-b7aa-2d23e69c1ae5"
  },
  {
    "timestamp": 866.37883,
    "can_id": "0x167",
    "raw_data": [
      88,
      32,
      0,
      0,
      24,
      0,
      22,
      0
    ],
    "id": "3160df17-addc-469b-ae29-5d6ace8c379c"
  },
  {
    "timestamp": 866.37909,
    "can_id": "0x166",
    "raw_data": [
      4,
      0,
      5,
      0,
      7,
      0,
      0,
      0
    ],
    "id": "2c5b08b4-9c21-4fb0-9322-74392cec76ca"
  },
  {
    "timestamp": 866.37934,
    "can_id": "0x165",
    "raw_data": [
      265,
      19,
      0,
      0,
      0,
      0,
      354,
      0
    ],
    "id": "65763ac3-107c-4d4e-838f-616026750f70"
  },
  {
    "timestamp": 866.38045,
    "can_id": "0x176",
    "raw_data": [
      0,
      0,
      0,
      0,
      0,
      0,
      86,
      32
    ],
    "id": "a5c2fd47-20a4-4548-9b14-7247cf2323f9"
  },
  {
    "timestamp": 866.38353,
    "can_id": "0x176",
    "raw_data": [
      0,
      0,
      0,
      0,
      0,
      0,
      105,
      32
    ],
    "id": "991487db-a686-4250-8f04-382110db6056"
  },
  {
    "timestamp": 866.38643,
    "can_id": "0x176",
    "raw_data": [
      0,
      0,
      0,
      0,
      0,
      0,
      105,
      32
    ],
    "id": "bec4f315-7d55-4c2b-97cd-feb73f56a831"
  },
  {
    "timestamp": 866.38958,
    "can_id": "0x176",
    "raw_data": [
      0,
      0,
      0,
      0,
      0,
      0,
      113,
      32
    ],
    "id": "657af9c3-4641-489d-9000-a25fd6d5f2db"
  },
  {
    "timestamp": 866.39257,
    "can_id": "0x176",
    "raw_data": [
      0,
      0,
      1,
      0,
      0,
      0,
      105,
      32
    ],
    "id": "b32a4f2e-7364-4a4d-a35d-cafb793f5b1f"
  },
  {
    "timestamp": 866.39556,
    "can_id": "0x176",
    "raw_data": [
      0,
      0,
      0,
      0,
      0,
      0,
      120,
      32
    ],
    "id": "721b0e5c-e2d0-4eda-b8dc-ae1297dac750"
  },
  {
    "timestamp": 866.39837,
    "can_id": "0x176",
    "raw_data": [
      0,
      0,
      0,
      0,
      0,
      0,
      115,
      32
    ],
    "id": "3f6290ec-d1c0-4b25-9f95-39a534b29d55"
  },
  {
    "timestamp": 866.40153,
    "can_id": "0x176",
    "raw_data": [
      0,
      0,
      0,
      0,
      0,
      0,
      130,
      32
    ],
    "id": "9edaecf1-18c1-456e-bad4-ae8f47cf5147"
  },
  {
    "timestamp": 866.40443,
    "can_id": "0x176",
    "raw_data": [
      0,
      0,
      0,
      0,
      0,
      0,
      115,
      32
    ],
    "id": "dd652b6f-6ea0-4a32-88be-e22693eb4a6d"
  },
  {
    "timestamp": 866.40759,
    "can_id": "0x176",
    "raw_data": [
      0,
      0,
      1,
      0,
      0,
      0,
      132,
      32
    ],
    "id": "54149bdb-3b68-4dfb-be6b-3ee0f0cf328d"
  },
  {
    "timestamp": 866.41041,
    "can_id": "0x176",
    "raw_data": [
      0,
      0,
      0,
      0,
      0,
      0,
      130,
      32
    ],
    "id": "c0ebfd7f-77cc-407a-b349-23e842f86fee"
  },
  {
    "timestamp": 866.41356,
    "can_id": "0x176",
    "raw_data": [
      0,
      0,
      0,
      0,
      0,
      0,
      130,
      32
    ],
    "id": "86cc18ba-81ca-4c6e-a686-a23f45ced16c"
  },
  {
    "timestamp": 866.41638,
    "can_id": "0x176",
    "raw_data": [
      0,
      0,
      597,
      597,
      0,
      0,
      132,
      32
    ],
    "id": "535247e8-05f2-4087-80f7-d29bf762c939"
  },
  {
    "timestamp": 866.41954,
    "can_id": "0x176",
    "raw_data": [
      0,
      0,
      1,
      0,
      0,
      0,
      130,
      32
    ],
    "id": "b64b4229-51d9-4ebd-90f0-e1a13fbb33b9"
  },
  {
    "timestamp": 866.42244,
    "can_id": "0x176",
    "raw_data": [
      0,
      0,
      0,
      0,
      0,
      0,
      145,
      32
    ],
    "id": "795af67a-46e2-481f-9eaf-18559b7db112"
  },
  {
    "timestamp": 866.42346,
    "can_id": "0x192",
    "raw_data": [
      0,
      0,
      0,
      0,
      1,
      0,
      0,
      0
    ],
    "id": "9ee4d865-ae6f-49b8-bd9d-269f54367b86"
  },
  {
    "timestamp": 866.4238,
    "can_id": "0x1",
    "raw_data": [
      0,
      0,
      0,
      0,
      121,
      5,
      0,
      0
    ],
    "id": "beedd4e7-353e-4251-b7d3-30d30bbeffee"
  },
  {
    "timestamp": 866.42551,
    "can_id": "0x176",
    "raw_data": [
      0,
      0,
      0,
      0,
      0,
      0,
      149,
      32
    ],
    "id": "83eed0e3-1fd6-4f12-b322-ac17047d9938"
  },
  {
    "timestamp": 866.4285,
    "can_id": "0x176",
    "raw_data": [
      0,
      0,
      0,
      0,
      0,
      0,
      147,
      32
    ],
    "id": "e8255198-be0a-44cb-8d43-80917011eb1d"
  },
  {
    "timestamp": 866.43148,
    "can_id": "0x176",
    "raw_data": [
      0,
      0,
      0,
      0,
      0,
      0,
      258,
      32
    ],
    "id": "016ae376-97fa-4992-a3ea-46e47cfd933b"
  },
  {
    "timestamp": 866.43447,
    "can_id": "0x176",
    "raw_data": [
      0,
      0,
      0,
      0,
      0,
      0,
      258,
      32
    ],
    "id": "f92b46b5-0071-4c60-9037-8964fc68507f"
  },
  {
    "timestamp": 866.43746,
    "can_id": "0x176",
    "raw_data": [
      0,
      0,
      0,
      0,
      0,
      0,
      256,
      32
    ],
    "id": "2662ac7c-dda4-4b4b-970c-436ce950cdaa"
  },
  {
    "timestamp": 866.44044,
    "can_id": "0x176",
    "raw_data": [
      0,
      0,
      0,
      0,
      0,
      0,
      260,
      32
    ],
    "id": "34c1e7d0-739c-446c-addb-62ac4f0114f3"
  },
  {
    "timestamp": 866.44351,
    "can_id": "0x176",
    "raw_data": [
      0,
      0,
      597,
      597,
      0,
      0,
      260,
      32
    ],
    "id": "f395344b-4868-4284-8ecb-d016d96cc641"
  },
  {
    "timestamp": 866.4465,
    "can_id": "0x176",
    "raw_data": [
      0,
      0,
      0,
      0,
      0,
      0,
      275,
      32
    ],
    "id": "2ce9e606-4efd-49f6-83ed-2179161c4c63"
  },
  {
    "timestamp": 866.44949,
    "can_id": "0x176",
    "raw_data": [
      0,
      0,
      597,
      597,
      0,
      0,
      277,
      32
    ],
    "id": "74da16d4-d0bd-43d8-83c2-4d09812300be"
  },
  {
    "timestamp": 866.45247,
    "can_id": "0x176",
    "raw_data": [
      0,
      0,
      0,
      0,
      0,
      0,
      260,
      32
    ],
    "id": "07c151f8-d280-4fa8-b9cd-d7167c39cd4a"
  },
  {
    "timestamp": 866.45563,
    "can_id": "0x176",
    "raw_data": [
      0,
      0,
      1,
      0,
      0,
      0,
      275,
      32
    ],
    "id": "5b758ead-7b3b-43bc-8679-f63a4fb4ff9c"
  },
  {
    "timestamp": 866.45845,
    "can_id": "0x176",
    "raw_data": [
      0,
      0,
      2,
      0,
      0,
      0,
      290,
      32
    ],
    "id": "cecdf912-f600-42d9-91a1-4c98cdadb39f"
  },
  {
    "timestamp": 866.46143,
    "can_id": "0x176",
    "raw_data": [
      0,
      0,
      0,
      0,
      0,
      0,
      290,
      32
    ],
    "id": "6de4d9ca-94dd-480c-8585-97ae84ed1c5a"
  },
  {
    "timestamp": 866.46442,
    "can_id": "0x176",
    "raw_data": [
      0,
      0,
      0,
      0,
      0,
      0,
      272,
      32
    ],
    "id": "175f8da2-cafb-4589-ba2e-a493e01f15a9"
  },
  {
    "timestamp": 866.46749,
    "can_id": "0x176",
    "raw_data": [
      0,
      0,
      0,
      0,
      0,
      0,
      277,
      32
    ],
    "id": "67c3cb30-016d-4d98-b3cb-6074f62ca7a4"
  },
  {
    "timestamp": 866.47048,
    "can_id": "0x176",
    "raw_data": [
      0,
      0,
      0,
      0,
      0,
      0,
      281,
      32
    ],
    "id": "61a5997f-2bc8-4e8b-8f55-33ac4aceb485"
  },
  {
    "timestamp": 866.47347,
    "can_id": "0x192",
    "raw_data": [
      0,
      0,
      0,
      0,
      1,
      0,
      0,
      0
    ],
    "id": "e209e6f6-aae0-4214-9e8f-01f34083376a"
  },
  {
    "timestamp": 866.47372,
    "can_id": "0x176",
    "raw_data": [
      0,
      0,
      1,
      0,
      0,
      0,
      290,
      32
    ],
    "id": "6052f373-10c1-4ee8-99d3-091fa1f28384"
  },
  {
    "timestamp": 866.47398,
    "can_id": "0x1",
    "raw_data": [
      0,
      0,
      0,
      0,
      118,
      5,
      0,
      0
    ],
    "id": "31483c67-0b58-42e3-b20d-4f018acd2361"
  },
  {
    "timestamp": 866.47654,
    "can_id": "0x176",
    "raw_data": [
      0,
      0,
      0,
      0,
      0,
      0,
      306,
      32
    ],
    "id": "76b23bd4-3ab7-4a7e-9668-e7b61b0a42b8"
  },
  {
    "timestamp": 866.47953,
    "can_id": "0x176",
    "raw_data": [
      0,
      0,
      0,
      0,
      0,
      0,
      292,
      32
    ],
    "id": "56a9b1bb-1891-464b-84b7-6afecb309b33"
  },
  {
    "timestamp": 866.47978,
    "can_id": "0x172",
    "raw_data": [
      0,
      0,
      0,
      0,
      405,
      2,
      1,
      0
    ],
    "id": "e293a597-6cb4-48d7-a4be-81e6defc20c7"
  },
  {
    "timestamp": 866.48004,
    "can_id": "0x171",
    "raw_data": [
      0,
      0,
      0,
      0,
      0,
      0,
      0,
      0
    ],
    "id": "b8042501-685e-4f30-a46c-aa94fa1e400f"
  },
  {
    "timestamp": 866.48029,
    "can_id": "0x170",
    "raw_data": [
      4,
      0,
      9,
      0,
      0,
      0,
      0,
      1
    ],
    "id": "6862a248-ff5e-4f52-a76a-4afdfec6a0fa"
  },
  {
    "timestamp": 866.48063,
    "can_id": "0x168",
    "raw_data": [
      52,
      0,
      311,
      593,
      593,
      597,
      1,
      0
    ],
    "id": "7c53dc06-f759-40a0-9584-3dec4e2ecd02"
  },
  {
    "timestamp": 866.48089,
    "can_id": "0x167",
    "raw_data": [
      294,
      32,
      0,
      0,
      49,
      0,
      32,
      0
    ],
    "id": "060933d3-ab79-40c0-a3a9-ff80ae8bf2e2"
  },
  {
    "timestamp": 866.48115,
    "can_id": "0x166",
    "raw_data": [
      0,
      0,
      1,
      0,
      0,
      0,
      0,
      0
    ],
    "id": "e02a57b9-d0dd-483b-802e-c25ef4c41fe9"
  },
  {
    "timestamp": 866.4814,
    "can_id": "0x165",
    "raw_data": [
      272,
      19,
      0,
      0,
      0,
      0,
      354,
      0
    ],
    "id": "4befed41-c467-4e63-b7cf-164129db085f"
  },
  {
    "timestamp": 866.48243,
    "can_id": "0x176",
    "raw_data": [
      0,
      0,
      1,
      0,
      0,
      0,
      294,
      32
    ],
    "id": "dd01d82a-aa82-453e-9079-7ba052ae3ab6"
  },
  {
    "timestamp": 866.48558,
    "can_id": "0x176",
    "raw_data": [
      0,
      0,
      0,
      0,
      0,
      0,
      306,
      32
    ],
    "id": "8eb30e68-cf1c-408f-aa75-a5f116be2198"
  },
  {
    "timestamp": 866.48857,
    "can_id": "0x176",
    "raw_data": [
      0,
      0,
      1,
      0,
      0,
      0,
      296,
      32
    ],
    "id": "140d7375-e687-4fa3-9d52-b85cf56bf633"
  },
  {
    "timestamp": 866.49156,
    "can_id": "0x176",
    "raw_data": [
      0,
      0,
      1,
      0,
      0,
      0,
      292,
      32
    ],
    "id": "4584ca2a-3685-4e5d-b732-90b482048e39"
  },
  {
    "timestamp": 866.49437,
    "can_id": "0x176",
    "raw_data": [
      0,
      0,
      1,
      0,
      0,
      0,
      309,
      32
    ],
    "id": "050c3a4e-7649-42ad-9bc8-cebab8df51e0"
  },
  {
    "timestamp": 866.49753,
    "can_id": "0x176",
    "raw_data": [
      0,
      0,
      0,
      0,
      0,
      0,
      296,
      32
    ],
    "id": "70b745cf-f15e-4c19-b801-75d1eb3c8c6a"
  },
  {
    "timestamp": 866.50043,
    "can_id": "0x176",
    "raw_data": [
      0,
      0,
      0,
      0,
      0,
      0,
      309,
      32
    ],
    "id": "404daf4a-f372-4980-9bdf-b957a7f7d379"
  },
  {
    "timestamp": 866.5035,
    "can_id": "0x176",
    "raw_data": [
      0,
      0,
      0,
      0,
      0,
      0,
      292,
      32
    ],
    "id": "5359604f-f284-4471-a38c-375860d5e628"
  },
  {
    "timestamp": 866.50641,
    "can_id": "0x176",
    "raw_data": [
      0,
      0,
      0,
      0,
      0,
      0,
      304,
      32
    ],
    "id": "b0deb052-33b3-40f1-8f2c-529df250ca78"
  },
  {
    "timestamp": 866.50956,
    "can_id": "0x176",
    "raw_data": [
      0,
      0,
      597,
      597,
      0,
      0,
      309,
      32
    ],
    "id": "1a71460e-e755-4bdd-af10-8879368a8e96"
  },
  {
    "timestamp": 866.51255,
    "can_id": "0x176",
    "raw_data": [
      0,
      0,
      0,
      0,
      0,
      0,
      324,
      32
    ],
    "id": "b7c3e636-9758-4550-89f0-d6f72d4e021b"
  },
  {
    "timestamp": 866.51554,
    "can_id": "0x176",
    "raw_data": [
      0,
      0,
      1,
      0,
      0,
      0,
      321,
      32
    ],
    "id": "1a89aedb-b21c-46aa-80cd-5c42ed8f5edc"
  },
  {
    "timestamp": 866.51852,
    "can_id": "0x176",
    "raw_data": [
      0,
      0,
      0,
      0,
      0,
      0,
      324,
      32
    ],
    "id": "1efb084e-450a-4eec-b94b-5c85481b3a80"
  },
  {
    "timestamp": 866.52151,
    "can_id": "0x176",
    "raw_data": [
      0,
      0,
      1,
      0,
      0,
      0,
      321,
      32
    ],
    "id": "5e78a9c3-1a2a-4e44-baa1-4bd60a20a0a6"
  },
  {
    "timestamp": 866.52356,
    "can_id": "0x192",
    "raw_data": [
      0,
      0,
      0,
      0,
      1,
      0,
      0,
      0
    ],
    "id": "26dfd82b-2d8b-493d-a9af-c2327f2bcc68"
  },
  {
    "timestamp": 866.5245,
    "can_id": "0x176",
    "raw_data": [
      0,
      0,
      0,
      0,
      0,
      0,
      311,
      32
    ],
    "id": "fa1feaba-c488-483c-8f28-bd5f158e177c"
  },
  {
    "timestamp": 866.52475,
    "can_id": "0x1",
    "raw_data": [
      0,
      0,
      0,
      0,
      128,
      5,
      0,
      0
    ],
    "id": "a515c71f-6e52-4718-a37f-655a44489f5b"
  },
  {
    "timestamp": 866.52748,
    "can_id": "0x176",
    "raw_data": [
      0,
      0,
      1,
      0,
      0,
      0,
      336,
      32
    ],
    "id": "f0936d9f-ef42-4ab0-9d79-99498fad46b2"
  },
  {
    "timestamp": 866.53047,
    "can_id": "0x176",
    "raw_data": [
      0,
      0,
      0,
      0,
      0,
      0,
      336,
      32
    ],
    "id": "a6513b04-e3b8-4d53-9426-0cd0ed86c3ba"
  },
  {
    "timestamp": 866.53346,
    "can_id": "0x176",
    "raw_data": [
      0,
      0,
      0,
      0,
      0,
      0,
      321,
      32
    ],
    "id": "90a2ee92-0ccd-4ddc-b3fe-f875fe50b8d3"
  },
  {
    "timestamp": 866.53644,
    "can_id": "0x176",
    "raw_data": [
      0,
      0,
      1,
      0,
      0,
      0,
      328,
      32
    ],
    "id": "12059786-369d-45a1-9acd-053938144570"
  },
  {
    "timestamp": 866.53943,
    "can_id": "0x176",
    "raw_data": [
      0,
      0,
      0,
      0,
      0,
      0,
      336,
      32
    ],
    "id": "6fa63a2b-35a2-4f46-a2d9-9dc98faf18b3"
  },
  {
    "timestamp": 866.5425,
    "can_id": "0x176",
    "raw_data": [
      0,
      0,
      1,
      0,
      0,
      0,
      328,
      32
    ],
    "id": "efc12c07-ebfd-4765-aba7-37d38e09985a"
  },
  {
    "timestamp": 866.54549,
    "can_id": "0x176",
    "raw_data": [
      0,
      0,
      1,
      0,
      0,
      0,
      343,
      32
    ],
    "id": "7111105b-4ca8-43dc-bf05-e8a7971d5cb4"
  },
  {
    "timestamp": 866.54847,
    "can_id": "0x176",
    "raw_data": [
      0,
      0,
      0,
      0,
      0,
      0,
      326,
      32
    ],
    "id": "299b7813-e3df-4a5c-be0b-a4c7a6743398"
  },
  {
    "timestamp": 866.55146,
    "can_id": "0x176",
    "raw_data": [
      0,
      0,
      0,
      0,
      0,
      0,
      340,
      32
    ],
    "id": "36f1d7fb-1179-44ee-b3d3-30545f36bb1e"
  },
  {
    "timestamp": 866.55445,
    "can_id": "0x176",
    "raw_data": [
      0,
      0,
      597,
      597,
      0,
      0,
      338,
      32
    ],
    "id": "424fb848-fccb-4b5d-8d54-5cb0973eeb9c"
  },
  {
    "timestamp": 866.55743,
    "can_id": "0x176",
    "raw_data": [
      0,
      0,
      1,
      0,
      0,
      0,
      336,
      32
    ],
    "id": "40337d4d-c37b-43e5-b91c-46fb21d65779"
  },
  {
    "timestamp": 866.56042,
    "can_id": "0x176",
    "raw_data": [
      0,
      0,
      0,
      0,
      0,
      0,
      336,
      32
    ],
    "id": "a85b327b-d09f-455d-9226-26f61d34e40f"
  },
  {
    "timestamp": 866.56349,
    "can_id": "0x176",
    "raw_data": [
      0,
      0,
      0,
      0,
      0,
      0,
      338,
      32
    ],
    "id": "6de64d56-7514-4bbd-8cc2-c2d739f1c0bb"
  },
  {
    "timestamp": 866.56648,
    "can_id": "0x176",
    "raw_data": [
      0,
      0,
      0,
      0,
      0,
      0,
      343,
      32
    ],
    "id": "7c0ec4c3-c1bc-40ef-81cf-518ad4ec28f7"
  },
  {
    "timestamp": 866.56947,
    "can_id": "0x176",
    "raw_data": [
      0,
      0,
      2,
      0,
      0,
      0,
      345,
      32
    ],
    "id": "3cc8e22d-ce56-4605-ab90-b6c23a2d50cc"
  },
  {
    "timestamp": 866.57245,
    "can_id": "0x176",
    "raw_data": [
      0,
      0,
      1,
      0,
      0,
      0,
      343,
      32
    ],
    "id": "0ba89b86-d8be-4fa2-aa8b-b266167c92bb"
  },
  {
    "timestamp": 866.57348,
    "can_id": "0x192",
    "raw_data": [
      0,
      0,
      0,
      0,
      1,
      0,
      0,
      0
    ],
    "id": "6b5e836a-d187-4ba4-babd-1eca5c462843"
  },
  {
    "timestamp": 866.57382,
    "can_id": "0x1",
    "raw_data": [
      0,
      0,
      0,
      0,
      118,
      5,
      0,
      0
    ],
    "id": "a97cccc1-f6fd-4b87-aea4-662fcda438f0"
  },
  {
    "timestamp": 866.57553,
    "can_id": "0x176",
    "raw_data": [
      0,
      0,
      0,
      0,
      0,
      0,
      340,
      32
    ],
    "id": "ad41ed2d-f6c4-4f51-9860-19ed540f90d0"
  },
  {
    "timestamp": 866.57843,
    "can_id": "0x176",
    "raw_data": [
      0,
      0,
      3,
      0,
      0,
      0,
      345,
      32
    ],
    "id": "db335d4a-5694-49ad-b800-1f44738a5c99"
  },
  {
    "timestamp": 866.58158,
    "can_id": "0x176",
    "raw_data": [
      0,
      0,
      1,
      0,
      0,
      0,
      345,
      32
    ],
    "id": "0d330582-108b-4aa1-8601-6b871b83aac0"
  },
  {
    "timestamp": 866.58184,
    "can_id": "0x172",
    "raw_data": [
      0,
      0,
      0,
      0,
      553,
      2,
      1,
      0
    ],
    "id": "c5e4f23e-0950-4cee-966d-dcc8f6d32680"
  },
  {
    "timestamp": 866.5821,
    "can_id": "0x171",
    "raw_data": [
      0,
      0,
      0,
      0,
      0,
      0,
      0,
      0
    ],
    "id": "5fa6b4c1-4272-48b6-9939-11de49cc5e4a"
  },
  {
    "timestamp": 866.58235,
    "can_id": "0x170",
    "raw_data": [
      4,
      0,
      9,
      0,
      0,
      0,
      0,
      1
    ],
    "id": "e42a9b3e-6f9b-4ec8-bc75-fb1467a5d5b6"
  },
  {
    "timestamp": 866.58261,
    "can_id": "0x168",
    "raw_data": [
      52,
      0,
      311,
      593,
      593,
      597,
      1,
      0
    ],
    "id": "1dbc5917-b7b6-4128-b3d4-fdf13b15c887"
  },
  {
    "timestamp": 866.58286,
    "can_id": "0x167",
    "raw_data": [
      355,
      32,
      0,
      0,
      49,
      0,
      22,
      0
    ],
    "id": "969a31cb-28b4-45fa-b3ab-f1c19836c046"
  },
  {
    "timestamp": 866.58321,
    "can_id": "0x166",
    "raw_data": [
      2,
      0,
      1,
      0,
      3,
      0,
      0,
      0
    ],
    "id": "530b8f7d-ff03-4dd0-babd-3cd2d77865cf"
  },
  {
    "timestamp": 866.58346,
    "can_id": "0x165",
    "raw_data": [
      265,
      19,
      0,
      0,
      0,
      0,
      354,
      0
    ],
    "id": "026f9008-e26f-4ed9-a78e-9455253a05e7"
  },
  {
    "timestamp": 866.58449,
    "can_id": "0x176",
    "raw_data": [
      0,
      0,
      0,
      0,
      0,
      0,
      340,
      32
    ],
    "id": "65614020-978b-4b95-af50-43eb5e8b032a"
  },
  {
    "timestamp": 866.58747,
    "can_id": "0x176",
    "raw_data": [
      0,
      0,
      0,
      0,
      0,
      0,
      345,
      32
    ],
    "id": "6b3ec7c3-c1c3-4d1e-a877-730ea26792af"
  },
  {
    "timestamp": 866.59046,
    "can_id": "0x176",
    "raw_data": [
      0,
      0,
      0,
      0,
      0,
      0,
      343,
      32
    ],
    "id": "246693d0-df70-4dd4-ae5f-c6fc1196cb4e"
  },
  {
    "timestamp": 866.59345,
    "can_id": "0x176",
    "raw_data": [
      0,
      0,
      597,
      597,
      0,
      0,
      360,
      32
    ],
    "id": "8eb0d099-4359-44b8-a78c-78193f344344"
  },
  {
    "timestamp": 866.59643,
    "can_id": "0x176",
    "raw_data": [
      0,
      0,
      1,
      0,
      0,
      0,
      353,
      32
    ],
    "id": "ebe2876c-48d1-418e-9d71-0958b4ce2e1e"
  },
  {
    "timestamp": 866.5995,
    "can_id": "0x176",
    "raw_data": [
      0,
      0,
      0,
      0,
      0,
      0,
      368,
      32
    ],
    "id": "1b3fd9fb-37a8-42f3-8559-79d8cd90cf82"
  },
  {
    "timestamp": 866.60249,
    "can_id": "0x176",
    "raw_data": [
      0,
      0,
      2,
      0,
      0,
      0,
      360,
      32
    ],
    "id": "ac9afa0d-71f8-4f38-9204-79741ee0fa9d"
  },
  {
    "timestamp": 866.60548,
    "can_id": "0x176",
    "raw_data": [
      0,
      0,
      597,
      597,
      0,
      0,
      372,
      32
    ],
    "id": "58028df2-d417-472b-80b7-c736d9532691"
  },
  {
    "timestamp": 866.60846,
    "can_id": "0x176",
    "raw_data": [
      0,
      0,
      0,
      0,
      0,
      0,
      358,
      32
    ],
    "id": "7a56b789-183f-4d56-84f4-bb350aca2685"
  },
  {
    "timestamp": 866.61145,
    "can_id": "0x176",
    "raw_data": [
      0,
      0,
      2,
      0,
      0,
      0,
      368,
      32
    ],
    "id": "2cec8305-eb86-4002-b541-bcaa86d3261a"
  },
  {
    "timestamp": 866.61444,
    "can_id": "0x176",
    "raw_data": [
      0,
      0,
      0,
      0,
      0,
      0,
      355,
      32
    ],
    "id": "5db3b181-b94b-40ed-bfb2-11c9d7cef6c1"
  },
  {
    "timestamp": 866.61742,
    "can_id": "0x176",
    "raw_data": [
      0,
      0,
      0,
      0,
      0,
      0,
      360,
      32
    ],
    "id": "ad5e8c89-48a6-4c61-8785-e9846021d394"
  },
  {
    "timestamp": 866.62041,
    "can_id": "0x176",
    "raw_data": [
      0,
      0,
      2,
      0,
      0,
      0,
      374,
      32
    ],
    "id": "d4443542-4915-439d-84db-cac94c6b72e2"
  },
  {
    "timestamp": 866.62348,
    "can_id": "0x176",
    "raw_data": [
      0,
      0,
      0,
      0,
      0,
      0,
      360,
      32
    ],
    "id": "b3b847df-714e-4e82-af03-b25e4c4cbb19"
  },
  {
    "timestamp": 866.62374,
    "can_id": "0x192",
    "raw_data": [
      0,
      0,
      0,
      0,
      1,
      0,
      0,
      0
    ],
    "id": "9c369c47-872c-416f-9eeb-13349de462be"
  },
  {
    "timestamp": 866.62399,
    "can_id": "0x1",
    "raw_data": [
      0,
      0,
      0,
      0,
      120,
      5,
      0,
      0
    ],
    "id": "d914c8c7-f77a-4d49-9ca1-191438fbe84a"
  },
  {
    "timestamp": 866.62638,
    "can_id": "0x176",
    "raw_data": [
      0,
      0,
      0,
      0,
      0,
      0,
      355,
      32
    ],
    "id": "98147dac-671e-4572-9091-c0ca94b7938b"
  },
  {
    "timestamp": 866.62954,
    "can_id": "0x176",
    "raw_data": [
      0,
      0,
      2,
      0,
      0,
      0,
      368,
      32
    ],
    "id": "6077bbc5-34b5-4bb9-ba01-7f235c9946d2"
  },
  {
    "timestamp": 866.63253,
    "can_id": "0x176",
    "raw_data": [
      0,
      0,
      0,
      0,
      0,
      0,
      372,
      32
    ],
    "id": "06f7d85a-df2c-4982-92ed-ff37119343cf"
  },
  {
    "timestamp": 866.63551,
    "can_id": "0x176",
    "raw_data": [
      0,
      0,
      0,
      0,
      0,
      0,
      360,
      32
    ],
    "id": "d5162cb7-9326-4c00-9f48-dcb61f9d3432"
  },
  {
    "timestamp": 866.6385,
    "can_id": "0x176",
    "raw_data": [
      0,
      0,
      1,
      0,
      0,
      0,
      372,
      32
    ],
    "id": "6ef561bb-a86b-4cbc-a14e-f069215ee1d0"
  },
  {
    "timestamp": 866.64149,
    "can_id": "0x176",
    "raw_data": [
      0,
      0,
      0,
      0,
      0,
      0,
      370,
      32
    ],
    "id": "b956f123-1eab-4a3b-a14e-7a185688eb56"
  },
  {
    "timestamp": 866.64465,
    "can_id": "0x176",
    "raw_data": [
      0,
      0,
      2,
      0,
      0,
      0,
      374,
      32
    ],
    "id": "e36e94cb-9dc8-4d5c-bbf6-4d417aca08b4"
  },
  {
    "timestamp": 866.64746,
    "can_id": "0x176",
    "raw_data": [
      0,
      0,
      0,
      0,
      0,
      0,
      372,
      32
    ],
    "id": "82f162db-3fc7-4f56-9547-03022387d32c"
  },
  {
    "timestamp": 866.65045,
    "can_id": "0x176",
    "raw_data": [
      0,
      0,
      0,
      0,
      0,
      0,
      360,
      32
    ],
    "id": "c6911595-d41b-4c24-821f-a7eecd557e98"
  },
  {
    "timestamp": 866.65343,
    "can_id": "0x176",
    "raw_data": [
      0,
      0,
      2,
      0,
      0,
      0,
      372,
      32
    ],
    "id": "c9a6a2f4-bbf2-44af-a9a3-609ec6b2deaa"
  },
  {
    "timestamp": 866.65642,
    "can_id": "0x176",
    "raw_data": [
      0,
      0,
      597,
      597,
      0,
      0,
      377,
      32
    ],
    "id": "8419e3dd-8d1e-42d7-9a80-be00b2b9a15e"
  },
  {
    "timestamp": 866.65941,
    "can_id": "0x176",
    "raw_data": [
      0,
      0,
      0,
      0,
      0,
      0,
      385,
      32
    ],
    "id": "22c7c57f-ef68-4d0d-9a25-67ebcba01a48"
  },
  {
    "timestamp": 866.66248,
    "can_id": "0x176",
    "raw_data": [
      0,
      0,
      2,
      0,
      0,
      0,
      372,
      32
    ],
    "id": "b603f38f-6a59-45f0-bd40-04c3eea46151"
  },
  {
    "timestamp": 866.66547,
    "can_id": "0x176",
    "raw_data": [
      0,
      0,
      0,
      0,
      0,
      0,
      360,
      32
    ],
    "id": "f1f7b74b-f4ef-418a-a8fb-f10f96a6b168"
  },
  {
    "timestamp": 866.66845,
    "can_id": "0x176",
    "raw_data": [
      0,
      0,
      0,
      0,
      0,
      0,
      372,
      32
    ],
    "id": "cd6ca677-d3a8-49dc-9777-98d429d12d2d"
  },
  {
    "timestamp": 866.67144,
    "can_id": "0x176",
    "raw_data": [
      0,
      0,
      0,
      0,
      0,
      0,
      370,
      32
    ],
    "id": "eaae8de0-8180-4bae-b0a3-f89a4cf31e68"
  },
  {
    "timestamp": 866.67349,
    "can_id": "0x192",
    "raw_data": [
      0,
      0,
      0,
      0,
      1,
      0,
      0,
      0
    ],
    "id": "5f1ce766-9dbf-461e-b2f7-295de90d047c"
  },
  {
    "timestamp": 866.67443,
    "can_id": "0x176",
    "raw_data": [
      0,
      0,
      0,
      0,
      0,
      0,
      370,
      32
    ],
    "id": "c8ef0acc-7e74-41ee-aadf-f1c483b55cd9"
  },
  {
    "timestamp": 866.67468,
    "can_id": "0x1",
    "raw_data": [
      0,
      0,
      0,
      0,
      119,
      5,
      0,
      0
    ],
    "id": "5e781658-292a-498d-bf66-89b5af0b68f7"
  },
  {
    "timestamp": 866.6775,
    "can_id": "0x176",
    "raw_data": [
      0,
      0,
      0,
      0,
      0,
      0,
      392,
      32
    ],
    "id": "b6829aa4-7818-46aa-bb1c-1ee468146bb7"
  },
  {
    "timestamp": 866.68049,
    "can_id": "0x176",
    "raw_data": [
      0,
      0,
      0,
      0,
      0,
      0,
      370,
      32
    ],
    "id": "3c38305c-f699-49e4-9468-2e07c558cf31"
  },
  {
    "timestamp": 866.68347,
    "can_id": "0x176",
    "raw_data": [
      0,
      0,
      597,
      597,
      0,
      0,
      370,
      32
    ],
    "id": "92d82e96-370b-47fe-95d2-20aca2faf7ba"
  },
  {
    "timestamp": 866.68373,
    "can_id": "0x172",
    "raw_data": [
      0,
      0,
      0,
      0,
      7,
      3,
      1,
      0
    ],
    "id": "5caa2074-af15-4d66-ac98-e11599b4bf7b"
  },
  {
    "timestamp": 866.68398,
    "can_id": "0x171",
    "raw_data": [
      0,
      0,
      0,
      0,
      0,
      0,
      0,
      0
    ],
    "id": "e03ff46c-5932-439a-9aac-1e8712283ba6"
  },
  {
    "timestamp": 866.68424,
    "can_id": "0x170",
    "raw_data": [
      4,
      0,
      9,
      0,
      0,
      0,
      0,
      1
    ],
    "id": "96280790-590a-43be-8bd6-6cf4c1986d80"
  },
  {
    "timestamp": 866.6845,
    "can_id": "0x168",
    "raw_data": [
      52,
      0,
      311,
      593,
      593,
      597,
      1,
      0
    ],
    "id": "726d960e-00a2-4069-98f8-6f947f006b26"
  },
  {
    "timestamp": 866.68475,
    "can_id": "0x167",
    "raw_data": [
      372,
      32,
      0,
      0,
      49,
      0,
      17,
      0
    ],
    "id": "5be7a871-1b07-45ff-809d-9a624cf27daf"
  },
  {
    "timestamp": 866.68501,
    "can_id": "0x166",
    "raw_data": [
      596,
      597,
      0,
      0,
      1,
      0,
      0,
      0
    ],
    "id": "96292ec4-44bc-4a22-8b65-f6ea727b544a"
  },
  {
    "timestamp": 866.68535,
    "can_id": "0x165",
    "raw_data": [
      273,
      19,
      0,
      0,
      0,
      0,
      354,
      0
    ],
    "id": "4a39b6f2-b0be-454f-bee8-d2b74a78344f"
  },
  {
    "timestamp": 866.68646,
    "can_id": "0x176",
    "raw_data": [
      0,
      0,
      0,
      0,
      0,
      0,
      377,
      32
    ],
    "id": "ec3b1275-7a5c-4286-b98d-d0e16054b556"
  },
  {
    "timestamp": 866.68953,
    "can_id": "0x176",
    "raw_data": [
      0,
      0,
      0,
      0,
      0,
      0,
      385,
      32
    ],
    "id": "d7bb749f-01f4-4685-96ac-f64fe68c9c9f"
  },
  {
    "timestamp": 866.69235,
    "can_id": "0x176",
    "raw_data": [
      0,
      0,
      0,
      0,
      0,
      0,
      374,
      32
    ],
    "id": "20e1fc86-94f0-4b68-897b-223aa8a2e855"
  },
  {
    "timestamp": 866.6955,
    "can_id": "0x176",
    "raw_data": [
      0,
      0,
      0,
      0,
      0,
      0,
      374,
      32
    ],
    "id": "68edf6a8-275f-4d4f-9dac-1af5c71a0ece"
  },
  {
    "timestamp": 866.69849,
    "can_id": "0x176",
    "raw_data": [
      0,
      0,
      0,
      0,
      0,
      0,
      374,
      32
    ],
    "id": "554f82cd-3780-42bf-b6fd-4faae0ec975d"
  },
  {
    "timestamp": 866.70148,
    "can_id": "0x176",
    "raw_data": [
      0,
      0,
      1,
      0,
      0,
      0,
      392,
      32
    ],
    "id": "4e6a39e7-6cd8-4cd8-9a1c-c793cfb0af95"
  },
  {
    "timestamp": 866.70438,
    "can_id": "0x176",
    "raw_data": [
      0,
      0,
      1,
      0,
      0,
      0,
      372,
      32
    ],
    "id": "cf70c478-6d89-4ca7-b6bd-2fbf01a6161f"
  },
  {
    "timestamp": 866.70754,
    "can_id": "0x176",
    "raw_data": [
      0,
      0,
      0,
      0,
      0,
      0,
      392,
      32
    ],
    "id": "84181fce-24fb-4d36-a018-e28c4e4840d5"
  },
  {
    "timestamp": 866.71044,
    "can_id": "0x176",
    "raw_data": [
      0,
      0,
      1,
      0,
      0,
      0,
      392,
      32
    ],
    "id": "623f9961-ba53-4f90-8fd6-950bd4a1ec89"
  },
  {
    "timestamp": 866.71342,
    "can_id": "0x176",
    "raw_data": [
      0,
      0,
      0,
      0,
      0,
      0,
      387,
      32
    ],
    "id": "49eaef12-d634-4318-bb5b-26b79263b4b1"
  },
  {
    "timestamp": 866.71641,
    "can_id": "0x176",
    "raw_data": [
      0,
      0,
      1,
      0,
      0,
      0,
      377,
      32
    ],
    "id": "86ed27a7-413f-4f8d-89ef-0a242b6dd9b1"
  },
  {
    "timestamp": 866.7194,
    "can_id": "0x176",
    "raw_data": [
      0,
      0,
      0,
      0,
      0,
      0,
      387,
      32
    ],
    "id": "945ce778-7b32-4b53-991e-67ef655a1842"
  },
  {
    "timestamp": 866.72247,
    "can_id": "0x176",
    "raw_data": [
      0,
      0,
      0,
      0,
      0,
      0,
      392,
      32
    ],
    "id": "1657cb08-c464-4c65-968b-e1870f648d1e"
  },
  {
    "timestamp": 866.72349,
    "can_id": "0x192",
    "raw_data": [
      0,
      0,
      0,
      0,
      1,
      0,
      0,
      0
    ],
    "id": "3b89c2da-e4cd-411d-bb57-e810ac73a48f"
  },
  {
    "timestamp": 866.72375,
    "can_id": "0x1",
    "raw_data": [
      0,
      0,
      0,
      0,
      118,
      5,
      0,
      0
    ],
    "id": "a65f8368-fc00-40ae-8790-9f6a14eba985"
  },
  {
    "timestamp": 866.72546,
    "can_id": "0x176",
    "raw_data": [
      0,
      0,
      2,
      0,
      0,
      0,
      392,
      32
    ],
    "id": "5a7d2bd8-81e8-4045-b6e8-3df6771ce4c7"
  },
  {
    "timestamp": 866.72844,
    "can_id": "0x176",
    "raw_data": [
      0,
      0,
      1,
      0,
      0,
      0,
      374,
      32
    ],
    "id": "3ef35131-8f09-4342-89d1-4ffd215c6626"
  },
  {
    "timestamp": 866.73143,
    "can_id": "0x176",
    "raw_data": [
      0,
      0,
      1,
      0,
      0,
      0,
      385,
      32
    ],
    "id": "cf248511-0d41-424e-88d2-1ad83a224977"
  },
  {
    "timestamp": 866.73442,
    "can_id": "0x176",
    "raw_data": [
      0,
      0,
      1,
      0,
      0,
      0,
      374,
      32
    ],
    "id": "89fc8ab4-085c-47d6-8619-cfcf52deda19"
  },
  {
    "timestamp": 866.7374,
    "can_id": "0x176",
    "raw_data": [
      0,
      0,
      1,
      0,
      0,
      0,
      389,
      32
    ],
    "id": "2d16bb5f-7e76-4b8b-9d91-d099a88d1492"
  },
  {
    "timestamp": 866.74039,
    "can_id": "0x176",
    "raw_data": [
      0,
      0,
      2,
      0,
      0,
      0,
      387,
      32
    ],
    "id": "05002c9e-e04e-48c3-9763-e6027660823d"
  },
  {
    "timestamp": 866.74346,
    "can_id": "0x176",
    "raw_data": [
      0,
      0,
      0,
      0,
      0,
      0,
      377,
      32
    ],
    "id": "ddefda36-54ef-411f-8fe1-9ec453d87c2d"
  },
  {
    "timestamp": 866.74645,
    "can_id": "0x176",
    "raw_data": [
      0,
      0,
      0,
      0,
      0,
      0,
      389,
      32
    ],
    "id": "343578b1-31df-4447-8983-08bccfc7dcfc"
  },
  {
    "timestamp": 866.74943,
    "can_id": "0x176",
    "raw_data": [
      0,
      0,
      0,
      0,
      0,
      0,
      392,
      32
    ],
    "id": "324080f4-d509-4517-ba5b-01ae6ad37b78"
  },
  {
    "timestamp": 866.75242,
    "can_id": "0x176",
    "raw_data": [
      0,
      0,
      0,
      0,
      0,
      0,
      387,
      32
    ],
    "id": "da9455cb-66a7-4b8b-8b24-d72493653288"
  },
  {
    "timestamp": 866.75541,
    "can_id": "0x176",
    "raw_data": [
      0,
      0,
      1,
      0,
      0,
      0,
      387,
      32
    ],
    "id": "1095a85e-21e7-40b2-a96a-ba7d99e4057f"
  },
  {
    "timestamp": 866.75839,
    "can_id": "0x176",
    "raw_data": [
      0,
      0,
      1,
      0,
      0,
      0,
      387,
      32
    ],
    "id": "b410cde6-249b-4d47-8e5d-80e75ded7b3a"
  },
  {
    "timestamp": 866.76147,
    "can_id": "0x176",
    "raw_data": [
      0,
      0,
      597,
      597,
      0,
      0,
      389,
      32
    ],
    "id": "d442a660-3086-4782-b44c-623f1fad7023"
  },
  {
    "timestamp": 866.76437,
    "can_id": "0x176",
    "raw_data": [
      0,
      0,
      1,
      0,
      0,
      0,
      387,
      32
    ],
    "id": "e4954eee-bfe1-4b67-a4c7-0f930433ff9d"
  },
  {
    "timestamp": 866.76744,
    "can_id": "0x176",
    "raw_data": [
      0,
      0,
      2,
      0,
      0,
      0,
      392,
      32
    ],
    "id": "79a0bead-9197-45f3-b73e-0fe5d1148ce9"
  },
  {
    "timestamp": 866.7706,
    "can_id": "0x176",
    "raw_data": [
      0,
      0,
      0,
      0,
      0,
      0,
      389,
      32
    ],
    "id": "86245400-87d6-43ff-bcc4-8cbff5a88422"
  },
  {
    "timestamp": 866.77341,
    "can_id": "0x176",
    "raw_data": [
      0,
      0,
      0,
      0,
      0,
      0,
      404,
      32
    ],
    "id": "2d38331b-19b9-4ea6-895d-7ff9e8d55ae8"
  },
  {
    "timestamp": 866.77367,
    "can_id": "0x192",
    "raw_data": [
      0,
      0,
      0,
      0,
      1,
      0,
      0,
      0
    ],
    "id": "56fc598b-a50c-4264-be2d-2d0c3a128400"
  },
  {
    "timestamp": 866.77401,
    "can_id": "0x1",
    "raw_data": [
      0,
      0,
      0,
      0,
      119,
      5,
      0,
      0
    ],
    "id": "e59cc2a6-b1c0-487f-ac52-d1e8a765460a"
  },
  {
    "timestamp": 866.77631,
    "can_id": "0x176",
    "raw_data": [
      0,
      0,
      1,
      0,
      0,
      0,
      372,
      32
    ],
    "id": "c04cf257-8037-44e1-a2fd-bc0ef31f812f"
  },
  {
    "timestamp": 866.77947,
    "can_id": "0x176",
    "raw_data": [
      0,
      0,
      597,
      597,
      0,
      0,
      392,
      32
    ],
    "id": "85fa718c-d24c-45b2-ac81-05f3593a69c3"
  },
  {
    "timestamp": 866.78246,
    "can_id": "0x176",
    "raw_data": [
      0,
      0,
      0,
      0,
      0,
      0,
      400,
      32
    ],
    "id": "f7885fce-aec2-4add-995e-4cd2fab26a0c"
  },
  {
    "timestamp": 866.78545,
    "can_id": "0x176",
    "raw_data": [
      0,
      0,
      2,
      0,
      0,
      0,
      389,
      32
    ],
    "id": "6f4a4812-4b89-41f4-9864-5430867b7fb8"
  },
  {
    "timestamp": 866.7857,
    "can_id": "0x172",
    "raw_data": [
      0,
      0,
      1,
      0,
      65,
      3,
      1,
      0
    ],
    "id": "5bb11f83-a3b6-4226-8cf0-a48f055c0e39"
  },
  {
    "timestamp": 866.78596,
    "can_id": "0x171",
    "raw_data": [
      0,
      0,
      0,
      0,
      0,
      0,
      0,
      0
    ],
    "id": "26b28d1c-be6c-42f0-bf26-98568c459703"
  },
  {
    "timestamp": 866.78621,
    "can_id": "0x170",
    "raw_data": [
      4,
      0,
      9,
      0,
      0,
      0,
      0,
      1
    ],
    "id": "a9a1a36d-df24-4597-93f2-c2206db0de58"
  },
  {
    "timestamp": 866.78647,
    "can_id": "0x168",
    "raw_data": [
      52,
      0,
      311,
      593,
      580,
      597,
      2,
      0
    ],
    "id": "90f2aa15-2709-4032-9507-3bb484df88ad"
  },
  {
    "timestamp": 866.78673,
    "can_id": "0x167",
    "raw_data": [
      389,
      32,
      0,
      0,
      19,
      0,
      32,
      0
    ],
    "id": "2addabb0-1aa2-44b7-a76e-c32648dace0b"
  },
  {
    "timestamp": 866.78698,
    "can_id": "0x166",
    "raw_data": [
      6,
      0,
      1,
      0,
      0,
      0,
      0,
      0
    ],
    "id": "6a41656b-70e6-49fb-b2f9-e9fc61978a87"
  },
  {
    "timestamp": 866.78724,
    "can_id": "0x165",
    "raw_data": [
      272,
      19,
      0,
      0,
      0,
      0,
      354,
      0
    ],
    "id": "ff7a10d0-7f7f-4438-be2f-c8c676ed8781"
  },
  {
    "timestamp": 866.78835,
    "can_id": "0x176",
    "raw_data": [
      0,
      0,
      0,
      0,
      0,
      0,
      389,
      32
    ],
    "id": "bdaaf250-16c2-4783-917b-51698ff986c5"
  },
  {
    "timestamp": 866.79142,
    "can_id": "0x176",
    "raw_data": [
      0,
      0,
      0,
      0,
      0,
      0,
      402,
      32
    ],
    "id": "d42219e9-fca7-4dbc-92d8-9089701432ce"
  },
  {
    "timestamp": 866.79441,
    "can_id": "0x176",
    "raw_data": [
      0,
      0,
      1,
      0,
      0,
      0,
      392,
      32
    ],
    "id": "d5300bea-0e11-4d81-a976-bb9fbebd1151"
  },
  {
    "timestamp": 866.79748,
    "can_id": "0x176",
    "raw_data": [
      0,
      0,
      0,
      0,
      0,
      0,
      400,
      32
    ],
    "id": "aaa75fc8-5a22-4b19-9a80-a9fc1ca02260"
  },
  {
    "timestamp": 866.80038,
    "can_id": "0x176",
    "raw_data": [
      0,
      0,
      1,
      0,
      0,
      0,
      389,
      32
    ],
    "id": "b9ce3438-c6a6-4d97-9146-fd080cf8d337"
  },
  {
    "timestamp": 866.80345,
    "can_id": "0x176",
    "raw_data": [
      0,
      0,
      0,
      0,
      0,
      0,
      387,
      32
    ],
    "id": "83e46b3d-7638-4f2b-bc3a-048140fa47a9"
  },
  {
    "timestamp": 866.80644,
    "can_id": "0x176",
    "raw_data": [
      0,
      0,
      1,
      0,
      0,
      0,
      392,
      32
    ],
    "id": "adaa1afc-c211-41d8-8085-38f1b290142e"
  },
  {
    "timestamp": 866.80951,
    "can_id": "0x176",
    "raw_data": [
      0,
      0,
      1,
      0,
      0,
      0,
      400,
      32
    ],
    "id": "1bb44837-8d3d-49c6-98f8-0e70e8fab0af"
  },
  {
    "timestamp": 866.81241,
    "can_id": "0x176",
    "raw_data": [
      0,
      0,
      1,
      0,
      0,
      0,
      402,
      32
    ],
    "id": "64267042-476f-4066-ad45-b5e6746c567e"
  },
  {
    "timestamp": 866.8154,
    "can_id": "0x176",
    "raw_data": [
      0,
      0,
      0,
      0,
      0,
      0,
      402,
      32
    ],
    "id": "aa82ee0d-252c-4303-b668-051c31fc9584"
  },
  {
    "timestamp": 866.81838,
    "can_id": "0x176",
    "raw_data": [
      0,
      0,
      1,
      0,
      0,
      0,
      387,
      32
    ],
    "id": "85a485dd-0822-4fab-a09c-95020ba28d92"
  },
  {
    "timestamp": 866.82146,
    "can_id": "0x176",
    "raw_data": [
      0,
      0,
      0,
      0,
      0,
      0,
      385,
      32
    ],
    "id": "858186f2-b849-401d-9df0-a4204b7ec082"
  },
  {
    "timestamp": 866.8235,
    "can_id": "0x192",
    "raw_data": [
      0,
      0,
      0,
      0,
      1,
      0,
      0,
      0
    ],
    "id": "99385591-f6da-442a-a828-67d1eaa48999"
  },
  {
    "timestamp": 866.82444,
    "can_id": "0x176",
    "raw_data": [
      0,
      0,
      0,
      0,
      0,
      0,
      406,
      32
    ],
    "id": "3d7b551e-8389-4a76-ae7c-e73d4dc86d27"
  },
  {
    "timestamp": 866.8247,
    "can_id": "0x1",
    "raw_data": [
      0,
      0,
      0,
      0,
      118,
      5,
      0,
      0
    ],
    "id": "6813da5f-9d38-4517-a931-64d0c4f12534"
  },
  {
    "timestamp": 866.82751,
    "can_id": "0x176",
    "raw_data": [
      0,
      0,
      1,
      0,
      0,
      0,
      404,
      32
    ],
    "id": "0cf38d61-3cc2-44f5-be0d-1165eda81c5d"
  },
  {
    "timestamp": 866.8305,
    "can_id": "0x176",
    "raw_data": [
      0,
      0,
      0,
      0,
      0,
      0,
      389,
      32
    ],
    "id": "9ae4b76e-a032-4411-a4a0-d6b7d11c8e21"
  },
  {
    "timestamp": 866.83357,
    "can_id": "0x176",
    "raw_data": [
      0,
      0,
      0,
      0,
      0,
      0,
      387,
      32
    ],
    "id": "daa2208d-14d6-47f6-a6c0-0058a49afee3"
  },
  {
    "timestamp": 866.83639,
    "can_id": "0x176",
    "raw_data": [
      0,
      0,
      1,
      0,
      0,
      0,
      387,
      32
    ],
    "id": "997da365-ed25-4175-91ee-e6f6181786d9"
  },
  {
    "timestamp": 866.83938,
    "can_id": "0x176",
    "raw_data": [
      0,
      0,
      1,
      0,
      0,
      0,
      387,
      32
    ],
    "id": "44b6f965-13e4-45b5-b069-fe8c59e58d33"
  },
  {
    "timestamp": 866.84245,
    "can_id": "0x176",
    "raw_data": [
      0,
      0,
      2,
      0,
      0,
      0,
      400,
      32
    ],
    "id": "f4231bbc-d1cc-4cab-bd55-143ed20e6b18"
  },
  {
    "timestamp": 866.84543,
    "can_id": "0x176",
    "raw_data": [
      0,
      0,
      597,
      597,
      0,
      0,
      402,
      32
    ],
    "id": "34ca079f-f2f9-4dc3-9071-26c70f5774c7"
  },
  {
    "timestamp": 866.84842,
    "can_id": "0x176",
    "raw_data": [
      0,
      0,
      1,
      0,
      0,
      0,
      406,
      32
    ],
    "id": "6168cb57-91cd-40cb-a1b5-893cc955a959"
  },
  {
    "timestamp": 866.85141,
    "can_id": "0x176",
    "raw_data": [
      0,
      0,
      2,
      0,
      0,
      0,
      387,
      32
    ],
    "id": "07fafb8b-2dcb-43be-9c7f-6dc724934685"
  },
  {
    "timestamp": 866.85439,
    "can_id": "0x176",
    "raw_data": [
      0,
      0,
      0,
      0,
      0,
      0,
      402,
      32
    ],
    "id": "a84755e4-433e-4910-8698-6f397b359044"
  },
  {
    "timestamp": 866.85738,
    "can_id": "0x176",
    "raw_data": [
      0,
      0,
      0,
      0,
      0,
      0,
      392,
      32
    ],
    "id": "d72a5773-12d7-40ec-8ef2-e6674fc42b4a"
  },
  {
    "timestamp": 866.86037,
    "can_id": "0x176",
    "raw_data": [
      0,
      0,
      0,
      0,
      0,
      0,
      389,
      32
    ],
    "id": "d49fe681-d3b4-4f53-b0c2-ed4a828172e6"
  },
  {
    "timestamp": 866.86344,
    "can_id": "0x176",
    "raw_data": [
      0,
      0,
      0,
      0,
      0,
      0,
      389,
      32
    ],
    "id": "e23c2de9-f645-4d52-93e4-f66b731f465d"
  },
  {
    "timestamp": 866.86643,
    "can_id": "0x176",
    "raw_data": [
      0,
      0,
      0,
      0,
      0,
      0,
      387,
      32
    ],
    "id": "c7dbba48-fcb0-4d3d-a975-200861e2a282"
  },
  {
    "timestamp": 866.86941,
    "can_id": "0x176",
    "raw_data": [
      0,
      0,
      0,
      0,
      0,
      0,
      392,
      32
    ],
    "id": "343d62f7-62f6-4a2c-b374-db13b899395a"
  },
  {
    "timestamp": 866.8724,
    "can_id": "0x176",
    "raw_data": [
      0,
      0,
      2,
      0,
      0,
      0,
      392,
      32
    ],
    "id": "5b300d37-4e8f-4504-ab4b-492fdfe46e3b"
  },
  {
    "timestamp": 866.87342,
    "can_id": "0x192",
    "raw_data": [
      0,
      0,
      0,
      0,
      1,
      0,
      0,
      0
    ],
    "id": "5b199e9e-f0bf-4fe1-ab40-12dd5d2dae94"
  },
  {
    "timestamp": 866.87377,
    "can_id": "0x1",
    "raw_data": [
      0,
      0,
      0,
      0,
      119,
      5,
      0,
      0
    ],
    "id": "790afc09-8244-43ad-b937-cb534ef7f9f7"
  },
  {
    "timestamp": 866.87547,
    "can_id": "0x176",
    "raw_data": [
      0,
      0,
      0,
      0,
      0,
      0,
      392,
      32
    ],
    "id": "4b09a732-fe5b-447f-ab49-9a9d7ab82c1c"
  },
  {
    "timestamp": 866.87846,
    "can_id": "0x176",
    "raw_data": [
      0,
      0,
      2,
      0,
      0,
      0,
      389,
      32
    ],
    "id": "92edded7-51a2-402c-bbe3-e78b09ef72ea"
  },
  {
    "timestamp": 866.88145,
    "can_id": "0x176",
    "raw_data": [
      0,
      0,
      1,
      0,
      0,
      0,
      402,
      32
    ],
    "id": "c0b740ca-4577-4ea0-b998-6790a2af11f7"
  },
  {
    "timestamp": 866.88443,
    "can_id": "0x176",
    "raw_data": [
      0,
      0,
      0,
      0,
      0,
      0,
      406,
      32
    ],
    "id": "6d44749e-a418-4c5b-8557-0f67c2dfbc86"
  },
  {
    "timestamp": 866.8875,
    "can_id": "0x176",
    "raw_data": [
      0,
      0,
      2,
      0,
      0,
      0,
      402,
      32
    ],
    "id": "a5acecd4-b433-4310-8f20-41d75bc217e5"
  },
  {
    "timestamp": 866.88776,
    "can_id": "0x172",
    "raw_data": [
      0,
      0,
      0,
      0,
      117,
      3,
      1,
      0
    ],
    "id": "e0fa38d7-e067-437d-960b-979143c80e72"
  },
  {
    "timestamp": 866.88802,
    "can_id": "0x171",
    "raw_data": [
      0,
      0,
      0,
      0,
      0,
      0,
      0,
      0
    ],
    "id": "0b855e44-aa8b-4e6f-b972-0d536eb8f819"
  },
  {
    "timestamp": 866.88827,
    "can_id": "0x170",
    "raw_data": [
      4,
      0,
      9,
      0,
      0,
      0,
      0,
      1
    ],
    "id": "801a064a-5077-45e5-b689-7bba767f6d74"
  },
  {
    "timestamp": 866.88853,
    "can_id": "0x168",
    "raw_data": [
      52,
      0,
      311,
      593,
      593,
      597,
      0,
      0
    ],
    "id": "95355df0-4214-4ec2-b689-487ffab9b4cf"
  },
  {
    "timestamp": 866.88878,
    "can_id": "0x167",
    "raw_data": [
      402,
      32,
      0,
      0,
      54,
      0,
      17,
      0
    ],
    "id": "cabf5b37-8243-4486-ae1e-1a1ede4e30d1"
  },
  {
    "timestamp": 866.88904,
    "can_id": "0x166",
    "raw_data": [
      0,
      0,
      2,
      0,
      0,
      0,
      0,
      0
    ],
    "id": "efc33eb8-e8a0-49fe-ac72-e671af08f42b"
  },
  {
    "timestamp": 866.8893,
    "can_id": "0x165",
    "raw_data": [
      273,
      19,
      0,
      0,
      0,
      0,
      353,
      0
    ],
    "id": "1604f376-c729-4afe-a979-082fcdee82a6"
  },
  {
    "timestamp": 866.89049,
    "can_id": "0x176",
    "raw_data": [
      0,
      0,
      0,
      0,
      0,
      0,
      387,
      32
    ],
    "id": "bd385a87-bebb-4cb6-a240-d16f9f822196"
  },
  {
    "timestamp": 866.89348,
    "can_id": "0x176",
    "raw_data": [
      0,
      0,
      0,
      0,
      0,
      0,
      404,
      32
    ],
    "id": "68576eb0-a7c1-47f7-8e1c-5f5377f88d33"
  },
  {
    "timestamp": 866.89646,
    "can_id": "0x176",
    "raw_data": [
      0,
      0,
      1,
      0,
      0,
      0,
      408,
      32
    ],
    "id": "247ea158-5b17-4b63-86f9-279467e71108"
  },
  {
    "timestamp": 866.89945,
    "can_id": "0x176",
    "raw_data": [
      0,
      0,
      1,
      0,
      0,
      0,
      392,
      32
    ],
    "id": "17c85289-e261-42bf-bcb7-bb5bb9db0dd1"
  },
  {
    "timestamp": 866.90244,
    "can_id": "0x176",
    "raw_data": [
      0,
      0,
      1,
      0,
      0,
      0,
      404,
      32
    ],
    "id": "a02caa42-ad93-4719-8271-603a916409dd"
  },
  {
    "timestamp": 866.90551,
    "can_id": "0x176",
    "raw_data": [
      0,
      0,
      597,
      597,
      0,
      0,
      392,
      32
    ],
    "id": "5523d466-3022-4cbf-866b-c9b02c28fc23"
  },
  {
    "timestamp": 866.9085,
    "can_id": "0x176",
    "raw_data": [
      0,
      0,
      0,
      0,
      0,
      0,
      392,
      32
    ],
    "id": "f33a9414-1c14-44a2-8a54-e5d9ae46aa67"
  },
  {
    "timestamp": 866.91148,
    "can_id": "0x176",
    "raw_data": [
      0,
      0,
      0,
      0,
      0,
      0,
      406,
      32
    ],
    "id": "5bf3cffe-295b-4985-8be3-738205c5a81f"
  },
  {
    "timestamp": 866.91447,
    "can_id": "0x176",
    "raw_data": [
      0,
      0,
      0,
      0,
      0,
      0,
      392,
      32
    ],
    "id": "eec70721-fb11-4d21-8e94-eb3325ac056b"
  },
  {
    "timestamp": 866.91746,
    "can_id": "0x176",
    "raw_data": [
      0,
      0,
      2,
      0,
      0,
      0,
      400,
      32
    ],
    "id": "5dbc1a59-e849-48ee-9011-8f810b3e0416"
  },
  {
    "timestamp": 866.92044,
    "can_id": "0x176",
    "raw_data": [
      0,
      0,
      0,
      0,
      0,
      0,
      402,
      32
    ],
    "id": "1e675f7e-e49b-47b9-9622-b5f7fe25cdfc"
  },
  {
    "timestamp": 866.92343,
    "can_id": "0x192",
    "raw_data": [
      0,
      0,
      0,
      0,
      1,
      0,
      0,
      0
    ],
    "id": "d61ff2d6-527f-4677-9797-9bb2a37b0b0d"
  },
  {
    "timestamp": 866.92369,
    "can_id": "0x176",
    "raw_data": [
      0,
      0,
      1,
      0,
      0,
      0,
      402,
      32
    ],
    "id": "3b06be72-99cc-4578-a797-2c5980fd6666"
  },
  {
    "timestamp": 866.92394,
    "can_id": "0x1",
    "raw_data": [
      0,
      0,
      0,
      0,
      119,
      5,
      0,
      0
    ],
    "id": "bbf26332-5f26-461c-873e-223cda3a9a4c"
  },
  {
    "timestamp": 866.92642,
    "can_id": "0x176",
    "raw_data": [
      0,
      0,
      0,
      0,
      0,
      0,
      404,
      32
    ],
    "id": "b7ff96dc-2806-42c1-89a0-01faa1362564"
  },
  {
    "timestamp": 866.92957,
    "can_id": "0x176",
    "raw_data": [
      0,
      0,
      0,
      0,
      0,
      0,
      406,
      32
    ],
    "id": "670260b0-5fdf-4a04-ba3c-1de274835049"
  },
  {
    "timestamp": 866.93239,
    "can_id": "0x176",
    "raw_data": [
      0,
      0,
      0,
      0,
      0,
      0,
      389,
      32
    ],
    "id": "46be1fdb-eb8e-4eb8-b665-413c0e670f41"
  },
  {
    "timestamp": 866.93555,
    "can_id": "0x176",
    "raw_data": [
      0,
      0,
      0,
      0,
      0,
      0,
      404,
      32
    ],
    "id": "f4a3d6e7-63cb-4182-afce-c529978a84f0"
  },
  {
    "timestamp": 866.93845,
    "can_id": "0x176",
    "raw_data": [
      0,
      0,
      0,
      0,
      0,
      0,
      402,
      32
    ],
    "id": "3450e55b-8620-4a05-afdc-369a3f705498"
  },
  {
    "timestamp": 866.94152,
    "can_id": "0x176",
    "raw_data": [
      0,
      0,
      1,
      0,
      0,
      0,
      408,
      32
    ],
    "id": "b955ddbb-d7f2-483d-b9ab-f5aa5be28c25"
  },
  {
    "timestamp": 866.94451,
    "can_id": "0x176",
    "raw_data": [
      0,
      0,
      597,
      597,
      0,
      0,
      404,
      32
    ],
    "id": "c3c888ec-0db3-4c7e-962d-7fb775320c20"
  },
  {
    "timestamp": 866.94749,
    "can_id": "0x176",
    "raw_data": [
      0,
      0,
      0,
      0,
      0,
      0,
      392,
      32
    ],
    "id": "4812b61c-1f06-45a1-98cb-4f3b42132b6b"
  },
  {
    "timestamp": 866.95048,
    "can_id": "0x176",
    "raw_data": [
      0,
      0,
      0,
      0,
      0,
      0,
      400,
      32
    ],
    "id": "64057054-9ee6-4ea6-9557-dd07f08c5b25"
  },
  {
    "timestamp": 866.95355,
    "can_id": "0x176",
    "raw_data": [
      0,
      0,
      1,
      0,
      0,
      0,
      406,
      32
    ],
    "id": "82725e0c-cccf-4ec2-bd55-3e552e7a50b7"
  },
  {
    "timestamp": 866.95645,
    "can_id": "0x176",
    "raw_data": [
      0,
      0,
      3,
      0,
      0,
      0,
      406,
      32
    ],
    "id": "19c7ce89-7c37-40c5-b570-71d53f8fa51d"
  },
  {
    "timestamp": 866.95961,
    "can_id": "0x176",
    "raw_data": [
      0,
      0,
      0,
      0,
      0,
      0,
      400,
      32
    ],
    "id": "6f7e7d5f-b0b5-4bcb-8d0a-9618bc5f5943"
  },
  {
    "timestamp": 866.96243,
    "can_id": "0x176",
    "raw_data": [
      0,
      0,
      0,
      0,
      0,
      0,
      404,
      32
    ],
    "id": "8e919a5a-1664-496a-8902-3446174f8d6b"
  },
  {
    "timestamp": 866.96558,
    "can_id": "0x176",
    "raw_data": [
      0,
      0,
      0,
      0,
      0,
      0,
      400,
      32
    ],
    "id": "e95f1554-2ef7-4041-b28c-2b8b3da0079d"
  },
  {
    "timestamp": 866.96849,
    "can_id": "0x176",
    "raw_data": [
      0,
      0,
      1,
      0,
      0,
      0,
      402,
      32
    ],
    "id": "3fa88c0f-359a-4cb6-90c8-563b0a120f6e"
  },
  {
    "timestamp": 866.97147,
    "can_id": "0x176",
    "raw_data": [
      0,
      0,
      0,
      0,
      0,
      0,
      404,
      32
    ],
    "id": "5a828337-55b1-4aa1-baaf-448cfd7a95a9"
  },
  {
    "timestamp": 866.97352,
    "can_id": "0x192",
    "raw_data": [
      0,
      0,
      0,
      0,
      1,
      0,
      0,
      0
    ],
    "id": "9a61b02c-c60e-45bd-a933-8ef915d8b567"
  },
  {
    "timestamp": 866.97437,
    "can_id": "0x176",
    "raw_data": [
      0,
      0,
      597,
      597,
      0,
      0,
      387,
      32
    ],
    "id": "03200c0b-c3bc-4f53-a915-795a0692177a"
  },
  {
    "timestamp": 866.97463,
    "can_id": "0x1",
    "raw_data": [
      0,
      0,
      0,
      0,
      119,
      5,
      0,
      0
    ],
    "id": "5c6686dc-81f8-472b-98e5-6d9230605ea6"
  },
  {
    "timestamp": 866.97745,
    "can_id": "0x176",
    "raw_data": [
      0,
      0,
      0,
      0,
      0,
      0,
      402,
      32
    ],
    "id": "844db6c2-e2da-4a75-86a5-e96f28dcaa3f"
  },
  {
    "timestamp": 866.98043,
    "can_id": "0x176",
    "raw_data": [
      0,
      0,
      0,
      0,
      0,
      0,
      404,
      32
    ],
    "id": "705df11c-ff7f-4bf7-8941-80e68912f583"
  },
  {
    "timestamp": 866.9835,
    "can_id": "0x176",
    "raw_data": [
      0,
      0,
      1,
      0,
      0,
      0,
      406,
      32
    ],
    "id": "894758d9-f8ee-4dba-9289-d11789a6c794"
  },
  {
    "timestamp": 866.98649,
    "can_id": "0x176",
    "raw_data": [
      0,
      0,
      0,
      0,
      0,
      0,
      402,
      32
    ],
    "id": "843e2f59-1c23-4c6d-aafa-de4bb9c552b4"
  },
  {
    "timestamp": 866.98948,
    "can_id": "0x176",
    "raw_data": [
      0,
      0,
      0,
      0,
      0,
      0,
      404,
      32
    ],
    "id": "6e5d606e-b512-4ec5-9291-aa48d5f9529d"
  },
  {
    "timestamp": 866.98982,
    "can_id": "0x172",
    "raw_data": [
      0,
      0,
      1,
      0,
      265,
      3,
      1,
      0
    ],
    "id": "cd4948ba-2fa5-45be-aa65-0f88f88fc888"
  },
  {
    "timestamp": 866.99007,
    "can_id": "0x171",
    "raw_data": [
      0,
      0,
      0,
      0,
      0,
      0,
      0,
      0
    ],
    "id": "82a01ccd-c075-44cd-93a6-e5f307f1dae7"
  },
  {
    "timestamp": 866.99033,
    "can_id": "0x170",
    "raw_data": [
      4,
      0,
      9,
      0,
      0,
      0,
      0,
      1
    ],
    "id": "eb5a68a2-02e6-4dd9-b05a-8e9d1d5cc7e6"
  },
  {
    "timestamp": 866.99059,
    "can_id": "0x168",
    "raw_data": [
      52,
      0,
      311,
      593,
      579,
      597,
      2,
      0
    ],
    "id": "5720a6b8-5569-4a53-9cc1-32835d71a053"
  },
  {
    "timestamp": 866.99084,
    "can_id": "0x167",
    "raw_data": [
      404,
      32,
      0,
      0,
      34,
      0,
      17,
      0
    ],
    "id": "f72eb0e3-a872-4cf5-a3bb-1e6382f748b0"
  },
  {
    "timestamp": 866.9911,
    "can_id": "0x166",
    "raw_data": [
      4,
      0,
      5,
      0,
      2,
      0,
      0,
      0
    ],
    "id": "ff94d35d-4752-41c6-bf97-afd5c58e01a3"
  },
  {
    "timestamp": 866.99135,
    "can_id": "0x165",
    "raw_data": [
      272,
      19,
      0,
      0,
      0,
      0,
      353,
      0
    ],
    "id": "b55416b0-cb47-4bc1-a37c-ae79bfc31a79"
  },
  {
    "timestamp": 866.99246,
    "can_id": "0x176",
    "raw_data": [
      0,
      0,
      0,
      0,
      0,
      0,
      402,
      32
    ],
    "id": "2abb2a52-9362-446e-bc9a-ff71c5e1aa5e"
  },
  {
    "timestamp": 866.99545,
    "can_id": "0x176",
    "raw_data": [
      0,
      0,
      1,
      0,
      0,
      0,
      402,
      32
    ],
    "id": "c067aa1e-7d82-42a0-afa1-4d6a18d89010"
  },
  {
    "timestamp": 866.99844,
    "can_id": "0x176",
    "raw_data": [
      0,
      0,
      0,
      0,
      0,
      0,
      392,
      32
    ],
    "id": "3d670e5b-3943-4d85-83bf-108a403c0ac7"
  }
]