[
  {
    "timestamp": 858.00149,
    "can_id": "0x176",
    "raw_data": [
      0,
      0,
      1,
      0,
      0,
      0,
      8,
      0
    ],
    "id": "c804531a-5612-481e-ab15-aeb14b91ed7c"
  },
  {
    "timestamp": 858.00447,
    "can_id": "0x176",
    "raw_data": [
      0,
      0,
      1,
      0,
      0,
      0,
      18,
      0
    ],
    "id": "7c30fec6-25eb-406f-bfa1-5616a7108a2d"
  },
  {
    "timestamp": 858.00746,
    "can_id": "0x176",
    "raw_data": [
      0,
      0,
      0,
      0,
      0,
      0,
      3,
      0
    ],
    "id": "244d165b-5b84-4d27-a506-1798ddbb214f"
  },
  {
    "timestamp": 858.01045,
    "can_id": "0x176",
    "raw_data": [
      0,
      0,
      0,
      0,
      0,
      0,
      5,
      0
    ],
    "id": "6a3d2cca-36a5-4c8d-8e98-20c74105b89c"
  },
  {
    "timestamp": 858.01361,
    "can_id": "0x176",
    "raw_data": [
      0,
      0,
      0,
      0,
      0,
      0,
      16,
      0
    ],
    "id": "76ede60a-209f-4ba1-b3e5-a41b89759e74"
  },
  {
    "timestamp": 858.01386,
    "can_id": "0x172",
    "raw_data": [
      0,
      0,
      0,
      0,
      393,
      583,
      0,
      0
    ],
    "id": "a70a4974-0020-4d79-8b8c-03eb72fb46e7"
  },
  {
    "timestamp": 858.0142,
    "can_id": "0x171",
    "raw_data": [
      0,
      0,
      0,
      0,
      0,
      0,
      0,
      0
    ],
    "id": "5771146a-f9c5-47a5-a8ab-719954bbb5e1"
  },
  {
    "timestamp": 858.01446,
    "can_id": "0x170",
    "raw_data": [
      4,
      0,
      9,
      0,
      0,
      0,
      0,
      1
    ],
    "id": "1625eaf2-ef5b-4338-a544-3245bd7e9e9c"
  },
  {
    "timestamp": 858.01471,
    "can_id": "0x168",
    "raw_data": [
      52,
      0,
      311,
      593,
      596,
      597,
      0,
      0
    ],
    "id": "f82e36c4-b0f4-4789-8b51-403e3bca7c9d"
  },
  {
    "timestamp": 858.01497,
    "can_id": "0x167",
    "raw_data": [
      18,
      0,
      0,
      0,
      34,
      0,
      17,
      0
    ],
    "id": "3da2d257-dfd9-4f86-866b-aeb036e972bc"
  },
  {
    "timestamp": 858.01523,
    "can_id": "0x166",
    "raw_data": [
      0,
      0,
      1,
      0,
      2,
      0,
      0,
      0
    ],
    "id": "ab8617d4-68af-480d-b415-508e150fbbce"
  },
  {
    "timestamp": 858.01548,
    "can_id": "0x165",
    "raw_data": [
      272,
      19,
      0,
      0,
      0,
      0,
      354,
      0
    ],
    "id": "4e2d424d-a86c-4493-8137-1a3348830986"
  },
  {
    "timestamp": 858.01642,
    "can_id": "0x176",
    "raw_data": [
      0,
      0,
      0,
      0,
      0,
      0,
      16,
      0
    ],
    "id": "817d58ae-d3ee-43b1-98c2-8c23158def5d"
  },
  {
    "timestamp": 858.01949,
    "can_id": "0x176",
    "raw_data": [
      0,
      0,
      0,
      0,
      0,
      0,
      8,
      0
    ],
    "id": "e53384a5-3842-484b-ad27-d9f0d0b9df6f"
  },
  {
    "timestamp": 858.02248,
    "can_id": "0x176",
    "raw_data": [
      0,
      0,
      1,
      0,
      0,
      0,
      8,
      0
    ],
    "id": "f26639fd-4a35-4cb4-81ff-f338da51f7fa"
  },
  {
    "timestamp": 858.02359,
    "can_id": "0x192",
    "raw_data": [
      0,
      0,
      0,
      0,
      1,
      0,
      0,
      0
    ],
    "id": "13d927da-f523-4b93-a7dd-b4b1a4bd4bb7"
  },
  {
    "timestamp": 858.02393,
    "can_id": "0x1",
    "raw_data": [
      0,
      0,
      0,
      0,
      150,
      5,
      0,
      0
    ],
    "id": "28b00cd6-94f3-40d2-a77e-b3ffe0594bd6"
  },
  {
    "timestamp": 858.02555,
    "can_id": "0x176",
    "raw_data": [
      0,
      0,
      1,
      0,
      0,
      0,
      20,
      0
    ],
    "id": "1293c41f-fbed-4a2a-a85e-64e9d6253b8c"
  },
  {
    "timestamp": 858.02837,
    "can_id": "0x176",
    "raw_data": [
      0,
      0,
      0,
      0,
      0,
      0,
      3,
      0
    ],
    "id": "dd75d7d1-1df7-4e96-8d88-6aa87e8d217c"
  },
  {
    "timestamp": 858.03161,
    "can_id": "0x176",
    "raw_data": [
      0,
      0,
      0,
      0,
      0,
      0,
      5,
      0
    ],
    "id": "c5c5f320-c485-4a3d-9ca0-0d02a16ae6ed"
  },
  {
    "timestamp": 858.03443,
    "can_id": "0x176",
    "raw_data": [
      0,
      0,
      0,
      0,
      0,
      0,
      5,
      0
    ],
    "id": "e8b95df2-e1af-487a-8c1c-bdf9cbdb50c0"
  },
  {
    "timestamp": 858.03758,
    "can_id": "0x176",
    "raw_data": [
      0,
      0,
      1,
      0,
      0,
      0,
      18,
      0
    ],
    "id": "414647b4-1de7-462c-8ec2-dc6abf272dd9"
  },
  {
    "timestamp": 858.0404,
    "can_id": "0x176",
    "raw_data": [
      0,
      0,
      1,
      0,
      0,
      0,
      16,
      0
    ],
    "id": "f63ee568-658b-41ea-94bb-5337b96f6056"
  },
  {
    "timestamp": 858.04356,
    "can_id": "0x176",
    "raw_data": [
      0,
      0,
      0,
      0,
      0,
      0,
      8,
      0
    ],
    "id": "b4ee6882-5ebe-4469-a0ce-55a2e1c347f1"
  },
  {
    "timestamp": 858.04654,
    "can_id": "0x176",
    "raw_data": [
      0,
      0,
      0,
      0,
      0,
      0,
      16,
      0
    ],
    "id": "28db46f8-0578-426b-8290-83ae0d3824ab"
  },
  {
    "timestamp": 858.04953,
    "can_id": "0x176",
    "raw_data": [
      0,
      0,
      0,
      0,
      0,
      0,
      8,
      0
    ],
    "id": "c90ac790-4f2f-4fcc-a444-717a12b8afb9"
  },
  {
    "timestamp": 858.0526,
    "can_id": "0x176",
    "raw_data": [
      0,
      0,
      0,
      0,
      0,
      0,
      18,
      0
    ],
    "id": "b48b2300-2aa9-449a-95ca-f7af8f48230d"
  },
  {
    "timestamp": 858.05559,
    "can_id": "0x176",
    "raw_data": [
      0,
      0,
      0,
      0,
      0,
      0,
      5,
      0
    ],
    "id": "5bf4b4ed-a6d5-417e-9170-2ca67335283e"
  },
  {
    "timestamp": 858.05841,
    "can_id": "0x176",
    "raw_data": [
      0,
      0,
      0,
      0,
      0,
      0,
      8,
      0
    ],
    "id": "498b4b95-a921-46dc-ae01-e9e99fbf75e6"
  },
  {
    "timestamp": 858.06156,
    "can_id": "0x176",
    "raw_data": [
      0,
      0,
      0,
      0,
      0,
      0,
      16,
      0
    ],
    "id": "ee929333-0337-464d-a236-6885ff613ba0"
  },
  {
    "timestamp": 858.06455,
    "can_id": "0x176",
    "raw_data": [
      0,
      0,
      1,
      0,
      0,
      0,
      8,
      0
    ],
    "id": "29b1ce83-8dbc-4bb9-8ddc-bef121602e98"
  },
  {
    "timestamp": 858.06754,
    "can_id": "0x176",
    "raw_data": [
      0,
      0,
      0,
      0,
      0,
      0,
      16,
      0
    ],
    "id": "6c2e59b0-1e96-44b7-8fc5-12bd7b637888"
  },
  {
    "timestamp": 858.07385,
    "can_id": "0x192",
    "raw_data": [
      0,
      0,
      0,
      0,
      1,
      0,
      0,
      0
    ],
    "id": "102b22d1-c342-4829-b060-61303d6bd1e8"
  },
  {
    "timestamp": 858.07411,
    "can_id": "0x176",
    "raw_data": [
      0,
      0,
      2,
      0,
      0,
      0,
      8,
      0
    ],
    "id": "5800e4d1-6e75-4094-8fff-2db23cb9b138"
  },
  {
    "timestamp": 858.07436,
    "can_id": "0x1",
    "raw_data": [
      0,
      0,
      0,
      0,
      146,
      5,
      0,
      0
    ],
    "id": "c16f9351-d94a-45cc-9c90-0edd10610a83"
  },
  {
    "timestamp": 858.07658,
    "can_id": "0x176",
    "raw_data": [
      0,
      0,
      0,
      0,
      0,
      0,
      8,
      0
    ],
    "id": "5a88e297-5f78-4156-b207-fa63fd9d92f3"
  },
  {
    "timestamp": 858.07948,
    "can_id": "0x176",
    "raw_data": [
      0,
      0,
      0,
      0,
      0,
      0,
      8,
      0
    ],
    "id": "23c7617f-7976-4efa-b664-8acaf641ab6f"
  },
  {
    "timestamp": 858.08238,
    "can_id": "0x176",
    "raw_data": [
      0,
      0,
      0,
      0,
      0,
      0,
      8,
      0
    ],
    "id": "5e109eb9-42e6-41d5-b639-412091b53700"
  },
  {
    "timestamp": 858.12369,
    "can_id": "0x192",
    "raw_data": [
      0,
      0,
      0,
      0,
      1,
      0,
      0,
      0
    ],
    "id": "30498d43-27f0-4d45-bff3-6d7c4b4d8097"
  },
  {
    "timestamp": 858.12394,
    "can_id": "0x176",
    "raw_data": [
      0,
      0,
      595,
      597,
      0,
      0,
      18,
      0
    ],
    "id": "055fead4-0d9a-4f69-aa9c-99d32a8ec1e8"
  },
  {
    "timestamp": 858.1242,
    "can_id": "0x1",
    "raw_data": [
      0,
      0,
      0,
      0,
      150,
      5,
      0,
      0
    ],
    "id": "34906c5c-0a53-4f98-8b33-0074af1ccb78"
  },
  {
    "timestamp": 858.12445,
    "can_id": "0x172",
    "raw_data": [
      0,
      0,
      1,
      0,
      547,
      583,
      0,
      0
    ],
    "id": "d3a45872-f09f-4731-8f50-3f38cbc44d5f"
  },
  {
    "timestamp": 858.12471,
    "can_id": "0x176",
    "raw_data": [
      0,
      0,
      0,
      0,
      0,
      0,
      8,
      0
    ],
    "id": "027b90f0-6a70-4b47-83c1-0f20b1055608"
  },
  {
    "timestamp": 858.12497,
    "can_id": "0x171",
    "raw_data": [
      0,
      0,
      0,
      0,
      0,
      0,
      0,
      0
    ],
    "id": "19ee0ec7-dc69-47a3-8290-3d374032d105"
  },
  {
    "timestamp": 858.12522,
    "can_id": "0x170",
    "raw_data": [
      4,
      0,
      9,
      0,
      0,
      0,
      0,
      1
    ],
    "id": "8522d011-4d33-4082-913c-640e08efff9c"
  },
  {
    "timestamp": 858.12548,
    "can_id": "0x168",
    "raw_data": [
      52,
      0,
      311,
      593,
      579,
      597,
      2,
      0
    ],
    "id": "53c7e9e3-db53-4391-90ea-3f9c6a39b518"
  },
  {
    "timestamp": 858.12573,
    "can_id": "0x167",
    "raw_data": [
      3,
      0,
      0,
      0,
      24,
      0,
      52,
      0
    ],
    "id": "099553f0-9900-4531-85f8-3de3d4290333"
  },
  {
    "timestamp": 858.12599,
    "can_id": "0x166",
    "raw_data": [
      5,
      0,
      6,
      0,
      8,
      0,
      0,
      0
    ],
    "id": "23081518-1e08-447c-bf20-0d68e39e2604"
  },
  {
    "timestamp": 858.12625,
    "can_id": "0x165",
    "raw_data": [
      265,
      19,
      0,
      0,
      0,
      0,
      354,
      0
    ],
    "id": "d0ab8832-491d-412a-8166-2c3f358c0103"
  },
  {
    "timestamp": 858.12744,
    "can_id": "0x176",
    "raw_data": [
      0,
      0,
      0,
      0,
      0,
      0,
      8,
      0
    ],
    "id": "854ce900-02be-4df7-92c9-8c334646ec18"
  },
  {
    "timestamp": 858.13051,
    "can_id": "0x176",
    "raw_data": [
      0,
      0,
      0,
      0,
      0,
      0,
      16,
      0
    ],
    "id": "142d53ba-a77e-46ad-8bc8-323d6c0aab63"
  },
  {
    "timestamp": 858.1335,
    "can_id": "0x176",
    "raw_data": [
      0,
      0,
      0,
      0,
      0,
      0,
      16,
      0
    ],
    "id": "ec984e6e-d2e3-450f-8b3c-11a24c78143d"
  },
  {
    "timestamp": 858.13649,
    "can_id": "0x176",
    "raw_data": [
      0,
      0,
      2,
      0,
      0,
      0,
      18,
      0
    ],
    "id": "625de3d3-26c4-477e-bdd2-fc472af622f3"
  },
  {
    "timestamp": 858.13964,
    "can_id": "0x176",
    "raw_data": [
      0,
      0,
      0,
      0,
      0,
      0,
      16,
      0
    ],
    "id": "be26f459-343e-42f0-9afe-901c19f104f0"
  },
  {
    "timestamp": 858.14246,
    "can_id": "0x176",
    "raw_data": [
      0,
      0,
      1,
      0,
      0,
      0,
      5,
      0
    ],
    "id": "1cab4e2b-deba-43e4-bb02-87f2a9d17ad4"
  },
  {
    "timestamp": 858.14545,
    "can_id": "0x176",
    "raw_data": [
      0,
      0,
      597,
      597,
      0,
      0,
      3,
      0
    ],
    "id": "4eacf016-451d-40da-91b0-0b6c531fc977"
  },
  {
    "timestamp": 858.14852,
    "can_id": "0x176",
    "raw_data": [
      0,
      0,
      0,
      0,
      0,
      0,
      16,
      0
    ],
    "id": "f66d100a-fe4b-43b8-a164-49c2fff16b27"
  },
  {
    "timestamp": 858.1515,
    "can_id": "0x176",
    "raw_data": [
      0,
      0,
      0,
      0,
      0,
      0,
      5,
      0
    ],
    "id": "d01e2a46-2fd4-4b95-b0c9-10033f11601d"
  },
  {
    "timestamp": 858.15449,
    "can_id": "0x176",
    "raw_data": [
      0,
      0,
      0,
      0,
      0,
      0,
      8,
      0
    ],
    "id": "b933f67e-4152-4a72-bef6-960d32a4e196"
  },
  {
    "timestamp": 858.15756,
    "can_id": "0x176",
    "raw_data": [
      0,
      0,
      597,
      597,
      0,
      0,
      18,
      0
    ],
    "id": "3b598271-9dbf-4962-a8d1-661fb1cb9244"
  },
  {
    "timestamp": 858.16055,
    "can_id": "0x176",
    "raw_data": [
      0,
      0,
      0,
      0,
      0,
      0,
      16,
      0
    ],
    "id": "29e9efcf-f49c-44f8-8c61-4d103e4ce589"
  },
  {
    "timestamp": 858.16354,
    "can_id": "0x176",
    "raw_data": [
      0,
      0,
      1,
      0,
      0,
      0,
      16,
      0
    ],
    "id": "eb55eee9-c0d8-439c-8b1d-295a19b51761"
  },
  {
    "timestamp": 858.16652,
    "can_id": "0x176",
    "raw_data": [
      0,
      0,
      1,
      0,
      0,
      0,
      18,
      0
    ],
    "id": "c82bf411-9ae3-4458-a6a0-8630d0f7c5a4"
  },
  {
    "timestamp": 858.16951,
    "can_id": "0x176",
    "raw_data": [
      0,
      0,
      0,
      0,
      0,
      0,
      16,
      0
    ],
    "id": "c2d28704-1a9d-4d6c-8382-88647c21c4e5"
  },
  {
    "timestamp": 858.1725,
    "can_id": "0x176",
    "raw_data": [
      0,
      0,
      2,
      0,
      0,
      0,
      16,
      0
    ],
    "id": "b5a4df6a-e5ca-4f6f-972a-387c5a49aa3d"
  },
  {
    "timestamp": 858.17352,
    "can_id": "0x192",
    "raw_data": [
      0,
      0,
      0,
      0,
      1,
      0,
      0,
      0
    ],
    "id": "4a28df0d-956c-41ed-9c83-e04fb0833d4b"
  },
  {
    "timestamp": 858.17386,
    "can_id": "0x1",
    "raw_data": [
      0,
      0,
      0,
      0,
      148,
      5,
      0,
      0
    ],
    "id": "fbc9b303-1e73-4a27-b224-3cb2daa266b4"
  },
  {
    "timestamp": 858.22353,
    "can_id": "0x192",
    "raw_data": [
      0,
      0,
      0,
      0,
      1,
      0,
      0,
      0
    ],
    "id": "caf55395-a7ba-4d41-ad89-1cec28d07291"
  },
  {
    "timestamp": 858.22378,
    "can_id": "0x176",
    "raw_data": [
      0,
      0,
      595,
      597,
      0,
      0,
      8,
      0
    ],
    "id": "defac65b-0c8f-4683-a856-542c98485e30"
  },
  {
    "timestamp": 858.22404,
    "can_id": "0x1",
    "raw_data": [
      0,
      0,
      0,
      0,
      146,
      5,
      0,
      0
    ],
    "id": "f078063d-96ac-42b8-a723-d18d05bb482a"
  },
  {
    "timestamp": 858.22429,
    "can_id": "0x172",
    "raw_data": [
      0,
      0,
      0,
      0,
      1,
      584,
      0,
      0
    ],
    "id": "b3a2dbcf-9315-4193-8651-e61b1d800e28"
  },
  {
    "timestamp": 858.22455,
    "can_id": "0x171",
    "raw_data": [
      0,
      0,
      0,
      0,
      0,
      0,
      0,
      0
    ],
    "id": "5b648306-bcd1-4490-aece-3a4216f5d0cb"
  },
  {
    "timestamp": 858.22481,
    "can_id": "0x170",
    "raw_data": [
      4,
      0,
      9,
      0,
      0,
      0,
      0,
      1
    ],
    "id": "5ce1f6c1-268a-41f1-9a4a-aa8a2cc79bea"
  },
  {
    "timestamp": 858.22506,
    "can_id": "0x168",
    "raw_data": [
      52,
      0,
      311,
      593,
      596,
      597,
      0,
      0
    ],
    "id": "a6f146ea-a7f1-422a-822d-a48bf18182a4"
  },
  {
    "timestamp": 858.22532,
    "can_id": "0x167",
    "raw_data": [
      8,
      0,
      0,
      0,
      54,
      0,
      41,
      0
    ],
    "id": "811d4792-64e0-4741-bb2d-1f5b3518ed52"
  },
  {
    "timestamp": 858.23197,
    "can_id": "0x176",
    "raw_data": [
      0,
      0,
      0,
      0,
      0,
      0,
      20,
      0
    ],
    "id": "fe194242-3321-4838-8832-aafb443d457f"
  },
  {
    "timestamp": 858.23266,
    "can_id": "0x176",
    "raw_data": [
      0,
      0,
      1,
      0,
      0,
      0,
      8,
      0
    ],
    "id": "46a0abef-ce20-49c7-8653-25c64833df10"
  },
  {
    "timestamp": 858.23564,
    "can_id": "0x176",
    "raw_data": [
      0,
      0,
      0,
      0,
      0,
      0,
      16,
      0
    ],
    "id": "c74b901b-f780-4691-866c-73b38a84b878"
  },
  {
    "timestamp": 858.23854,
    "can_id": "0x176",
    "raw_data": [
      0,
      0,
      0,
      0,
      0,
      0,
      8,
      0
    ],
    "id": "a01068d2-f2e7-4e83-bdbe-509a3dabe3c5"
  },
  {
    "timestamp": 858.24571,
    "can_id": "0x176",
    "raw_data": [
      0,
      0,
      0,
      0,
      0,
      0,
      3,
      0
    ],
    "id": "cd54250f-1398-4193-8423-7344cbdd327a"
  },
  {
    "timestamp": 858.24759,
    "can_id": "0x176",
    "raw_data": [
      0,
      0,
      2,
      0,
      0,
      0,
      8,
      0
    ],
    "id": "a8a1bdc5-512e-49c1-b414-ba5f03575bab"
  },
  {
    "timestamp": 858.25058,
    "can_id": "0x176",
    "raw_data": [
      0,
      0,
      0,
      0,
      0,
      0,
      16,
      0
    ],
    "id": "c9795f75-859a-48d4-9a3e-5bbcc71c04a8"
  },
  {
    "timestamp": 858.25911,
    "can_id": "0x176",
    "raw_data": [
      0,
      0,
      0,
      0,
      0,
      0,
      8,
      0
    ],
    "id": "76e2e58a-b881-422f-96ee-66bb10bd22c5"
  },
  {
    "timestamp": 858.25971,
    "can_id": "0x176",
    "raw_data": [
      0,
      0,
      597,
      597,
      0,
      0,
      18,
      0
    ],
    "id": "8cdc906b-11d4-4bf8-bb1e-94f4fc593add"
  },
  {
    "timestamp": 858.26269,
    "can_id": "0x176",
    "raw_data": [
      0,
      0,
      1,
      0,
      0,
      0,
      16,
      0
    ],
    "id": "5ce9f5b2-810f-4c21-a603-6c1d3d496291"
  },
  {
    "timestamp": 858.26295,
    "can_id": "0x166",
    "raw_data": [
      0,
      0,
      597,
      597,
      596,
      597,
      0,
      0
    ],
    "id": "d8e72396-fe10-469f-843f-1af9874871c8"
  },
  {
    "timestamp": 858.26321,
    "can_id": "0x165",
    "raw_data": [
      265,
      19,
      0,
      0,
      0,
      0,
      354,
      0
    ],
    "id": "8a2c7c8a-0305-440c-aa21-e07a288c6dca"
  },
  {
    "timestamp": 858.26559,
    "can_id": "0x176",
    "raw_data": [
      0,
      0,
      1,
      0,
      0,
      0,
      16,
      0
    ],
    "id": "c6d26a2d-5ab9-4a87-8fd4-a837c12016cb"
  },
  {
    "timestamp": 858.2685,
    "can_id": "0x176",
    "raw_data": [
      0,
      0,
      597,
      597,
      0,
      0,
      8,
      0
    ],
    "id": "a6c1378d-1de9-4ebc-abfc-9224c469935b"
  },
  {
    "timestamp": 858.27165,
    "can_id": "0x176",
    "raw_data": [
      0,
      0,
      1,
      0,
      0,
      0,
      20,
      0
    ],
    "id": "ddfbdbe2-791a-4dce-939e-edb623e07e7a"
  },
  {
    "timestamp": 858.27362,
    "can_id": "0x192",
    "raw_data": [
      0,
      0,
      0,
      0,
      1,
      0,
      0,
      0
    ],
    "id": "bd7c19de-ec76-4ab7-aba6-2515cc20c2a7"
  },
  {
    "timestamp": 858.27455,
    "can_id": "0x176",
    "raw_data": [
      0,
      0,
      0,
      0,
      0,
      0,
      18,
      0
    ],
    "id": "f05ffc0b-da24-4c8d-b283-c98c7a55c9dc"
  },
  {
    "timestamp": 858.27481,
    "can_id": "0x1",
    "raw_data": [
      0,
      0,
      0,
      0,
      147,
      5,
      0,
      0
    ],
    "id": "e6dea090-9a20-4f19-8e17-cefc6eeb3c21"
  },
  {
    "timestamp": 858.27763,
    "can_id": "0x176",
    "raw_data": [
      0,
      0,
      0,
      0,
      0,
      0,
      8,
      0
    ],
    "id": "90a3b546-d908-476b-981f-1a99e55e65c1"
  },
  {
    "timestamp": 858.28044,
    "can_id": "0x176",
    "raw_data": [
      0,
      0,
      0,
      0,
      0,
      0,
      8,
      0
    ],
    "id": "6529cede-df72-4bd7-9750-fcdc949b8845"
  },
  {
    "timestamp": 858.2836,
    "can_id": "0x176",
    "raw_data": [
      0,
      0,
      0,
      0,
      0,
      0,
      8,
      0
    ],
    "id": "568ef14f-8f6e-434a-b9f7-89a06cf15947"
  },
  {
    "timestamp": 858.28659,
    "can_id": "0x176",
    "raw_data": [
      0,
      0,
      0,
      0,
      0,
      0,
      8,
      0
    ],
    "id": "64fe6582-34a6-41f1-916e-04acc64173c3"
  },
  {
    "timestamp": 858.28957,
    "can_id": "0x176",
    "raw_data": [
      0,
      0,
      0,
      0,
      0,
      0,
      18,
      0
    ],
    "id": "b4b24bef-bf88-49a5-8f43-c59c0303ec04"
  },
  {
    "timestamp": 858.29247,
    "can_id": "0x176",
    "raw_data": [
      0,
      0,
      0,
      0,
      0,
      0,
      18,
      0
    ],
    "id": "5c83213f-2ca0-4237-b893-0368d3d99804"
  },
  {
    "timestamp": 858.29563,
    "can_id": "0x176",
    "raw_data": [
      0,
      0,
      597,
      597,
      0,
      0,
      16,
      0
    ],
    "id": "ac9186fc-22d4-46c8-b99f-013630ff715f"
  },
  {
    "timestamp": 858.29845,
    "can_id": "0x176",
    "raw_data": [
      0,
      0,
      597,
      597,
      0,
      0,
      5,
      0
    ],
    "id": "7a58e7d9-f3b3-46fe-942f-90d4bc50991b"
  },
  {
    "timestamp": 858.30152,
    "can_id": "0x176",
    "raw_data": [
      0,
      0,
      0,
      0,
      0,
      0,
      8,
      0
    ],
    "id": "69971507-8df2-4c3c-a276-dcd350d375ac"
  },
  {
    "timestamp": 858.30451,
    "can_id": "0x176",
    "raw_data": [
      0,
      0,
      0,
      0,
      0,
      0,
      16,
      0
    ],
    "id": "45ace144-88a5-4b6b-b776-953f60a77e3e"
  },
  {
    "timestamp": 858.30749,
    "can_id": "0x176",
    "raw_data": [
      0,
      0,
      596,
      597,
      0,
      0,
      8,
      0
    ],
    "id": "961c0bcc-58c2-47b1-aabc-2e66352f6cc4"
  },
  {
    "timestamp": 858.31048,
    "can_id": "0x176",
    "raw_data": [
      0,
      0,
      1,
      0,
      0,
      0,
      0,
      0
    ],
    "id": "259c93b9-4be5-47b8-ab67-b961e92a6f12"
  },
  {
    "timestamp": 858.31355,
    "can_id": "0x176",
    "raw_data": [
      0,
      0,
      0,
      0,
      0,
      0,
      5,
      0
    ],
    "id": "7b79cefd-76cd-46d3-9481-2c419edf201b"
  },
  {
    "timestamp": 858.31654,
    "can_id": "0x176",
    "raw_data": [
      0,
      0,
      597,
      597,
      0,
      0,
      8,
      0
    ],
    "id": "cec812b4-d8a2-45cf-af49-d4a6d8c656e4"
  },
  {
    "timestamp": 858.31953,
    "can_id": "0x176",
    "raw_data": [
      0,
      0,
      0,
      0,
      0,
      0,
      16,
      0
    ],
    "id": "f8dad795-c10f-496a-a633-04a15f616930"
  },
  {
    "timestamp": 858.31978,
    "can_id": "0x172",
    "raw_data": [
      0,
      0,
      0,
      0,
      53,
      584,
      0,
      0
    ],
    "id": "4cf95040-5f04-4dd2-b1e6-48408386fe84"
  },
  {
    "timestamp": 858.32004,
    "can_id": "0x171",
    "raw_data": [
      0,
      0,
      0,
      0,
      0,
      0,
      0,
      0
    ],
    "id": "1a128a8d-1cc7-45ec-b8c9-d82760acc125"
  },
  {
    "timestamp": 858.32029,
    "can_id": "0x170",
    "raw_data": [
      4,
      0,
      9,
      0,
      0,
      0,
      0,
      1
    ],
    "id": "90f4e237-755e-40e0-b0f3-d4db8c5a2617"
  },
  {
    "timestamp": 858.32081,
    "can_id": "0x168",
    "raw_data": [
      52,
      0,
      311,
      593,
      595,
      597,
      597,
      597
    ],
    "id": "e1a1a8f6-9a7f-40f8-b338-37056a5b8b25"
  },
  {
    "timestamp": 858.32106,
    "can_id": "0x167",
    "raw_data": [
      18,
      0,
      0,
      0,
      49,
      0,
      2,
      0
    ],
    "id": "4ad275cb-c119-43c8-a027-1eb427b82d89"
  },
  {
    "timestamp": 858.32132,
    "can_id": "0x166",
    "raw_data": [
      1,
      0,
      4,
      0,
      1,
      0,
      0,
      0
    ],
    "id": "a8c9e610-e692-49b8-9395-3ab2bff934e8"
  },
  {
    "timestamp": 858.32166,
    "can_id": "0x165",
    "raw_data": [
      272,
      19,
      0,
      0,
      0,
      0,
      354,
      0
    ],
    "id": "73b12876-3d41-48eb-8035-977419658c7f"
  },
  {
    "timestamp": 858.32243,
    "can_id": "0x176",
    "raw_data": [
      0,
      0,
      2,
      0,
      0,
      0,
      20,
      0
    ],
    "id": "71127a48-9bf4-4f6c-8ed5-59e427e99127"
  },
  {
    "timestamp": 858.32354,
    "can_id": "0x192",
    "raw_data": [
      0,
      0,
      0,
      0,
      1,
      0,
      0,
      0
    ],
    "id": "08ab695a-1661-4cef-8da6-600013ec6407"
  },
  {
    "timestamp": 858.32388,
    "can_id": "0x1",
    "raw_data": [
      0,
      0,
      0,
      0,
      147,
      5,
      0,
      0
    ],
    "id": "25adde57-2de6-4c1d-9b91-9913eac2e7e5"
  },
  {
    "timestamp": 858.3255,
    "can_id": "0x176",
    "raw_data": [
      0,
      0,
      0,
      0,
      0,
      0,
      20,
      0
    ],
    "id": "a9594054-59e9-4ebc-97d8-83471a8fc833"
  },
  {
    "timestamp": 858.32866,
    "can_id": "0x176",
    "raw_data": [
      0,
      0,
      0,
      0,
      0,
      0,
      5,
      0
    ],
    "id": "ffbc2e1e-6463-4e14-9eb2-2f4cc40a2855"
  },
  {
    "timestamp": 858.33156,
    "can_id": "0x176",
    "raw_data": [
      0,
      0,
      0,
      0,
      0,
      0,
      8,
      0
    ],
    "id": "896423fe-13c5-4fb1-98cd-d9ce61c72f73"
  },
  {
    "timestamp": 858.33454,
    "can_id": "0x176",
    "raw_data": [
      0,
      0,
      597,
      597,
      0,
      0,
      18,
      0
    ],
    "id": "8e0bd966-4a1b-4903-b09d-4153f23cfa1b"
  },
  {
    "timestamp": 858.33753,
    "can_id": "0x176",
    "raw_data": [
      0,
      0,
      0,
      0,
      0,
      0,
      8,
      0
    ],
    "id": "07dca244-94fe-47f5-a437-b9cd5f88506d"
  },
  {
    "timestamp": 858.34052,
    "can_id": "0x176",
    "raw_data": [
      0,
      0,
      1,
      0,
      0,
      0,
      8,
      0
    ],
    "id": "b0f643b3-2f68-4392-bd7a-5ee1a2b7624a"
  },
  {
    "timestamp": 858.3435,
    "can_id": "0x176",
    "raw_data": [
      0,
      0,
      1,
      0,
      0,
      0,
      8,
      0
    ],
    "id": "e4951492-bc85-431d-baad-e33a4353803c"
  },
  {
    "timestamp": 858.34649,
    "can_id": "0x176",
    "raw_data": [
      0,
      0,
      0,
      0,
      0,
      0,
      8,
      0
    ],
    "id": "e5add82c-c89f-4ff8-bdb4-244a5137ec3a"
  },
  {
    "timestamp": 858.34956,
    "can_id": "0x176",
    "raw_data": [
      0,
      0,
      0,
      0,
      0,
      0,
      18,
      0
    ],
    "id": "ccb8f6d6-2d7c-4332-87bf-5906c8bf784a"
  },
  {
    "timestamp": 858.35255,
    "can_id": "0x176",
    "raw_data": [
      0,
      0,
      0,
      0,
      0,
      0,
      16,
      0
    ],
    "id": "ab444395-7ce1-4c00-b0df-8a8c54dc6733"
  },
  {
    "timestamp": 858.35554,
    "can_id": "0x176",
    "raw_data": [
      0,
      0,
      0,
      0,
      0,
      0,
      8,
      0
    ],
    "id": "a1762d11-bd64-4bdb-a38f-b5b7b0405b0b"
  },
  {
    "timestamp": 858.35852,
    "can_id": "0x176",
    "raw_data": [
      0,
      0,
      3,
      0,
      0,
      0,
      16,
      0
    ],
    "id": "cbbcd599-5e39-4478-bbe6-48c6cff617f9"
  },
  {
    "timestamp": 858.36151,
    "can_id": "0x176",
    "raw_data": [
      0,
      0,
      0,
      0,
      0,
      0,
      16,
      0
    ],
    "id": "3e44a4b8-31b1-47cd-9eee-2ff607f54bbb"
  },
  {
    "timestamp": 858.3645,
    "can_id": "0x176",
    "raw_data": [
      0,
      0,
      1,
      0,
      0,
      0,
      16,
      0
    ],
    "id": "66087f29-9fa7-41b8-a488-bacff3c12e06"
  },
  {
    "timestamp": 858.36748,
    "can_id": "0x176",
    "raw_data": [
      0,
      0,
      0,
      0,
      0,
      0,
      16,
      0
    ],
    "id": "54793e2e-277a-49b8-afd7-567620615809"
  },
  {
    "timestamp": 858.37055,
    "can_id": "0x176",
    "raw_data": [
      0,
      0,
      1,
      0,
      0,
      0,
      3,
      0
    ],
    "id": "5107ee6b-f99a-44de-8088-ebfa74222b8a"
  },
  {
    "timestamp": 858.37354,
    "can_id": "0x192",
    "raw_data": [
      0,
      0,
      0,
      0,
      1,
      0,
      0,
      0
    ],
    "id": "a6f162d8-6e64-4fc6-91e0-d253add0eb18"
  },
  {
    "timestamp": 858.37371,
    "can_id": "0x176",
    "raw_data": [
      0,
      0,
      1,
      0,
      0,
      0,
      8,
      0
    ],
    "id": "a98492e2-5434-42b5-95c9-34e2ca48d9a3"
  },
  {
    "timestamp": 858.37397,
    "can_id": "0x1",
    "raw_data": [
      0,
      0,
      0,
      0,
      147,
      5,
      0,
      0
    ],
    "id": "79dac334-cf01-48b8-ba26-58e492f3401b"
  },
  {
    "timestamp": 858.37644,
    "can_id": "0x176",
    "raw_data": [
      0,
      0,
      596,
      597,
      0,
      0,
      5,
      0
    ],
    "id": "1cc9cd00-b06e-4263-9eb7-01c69f93e5b4"
  },
  {
    "timestamp": 858.3796,
    "can_id": "0x176",
    "raw_data": [
      0,
      0,
      0,
      0,
      0,
      0,
      16,
      0
    ],
    "id": "bbe28480-0f78-4f90-a9f4-8feb843ea45c"
  },
  {
    "timestamp": 858.39377,
    "can_id": "0x176",
    "raw_data": [
      0,
      0,
      2,
      0,
      0,
      0,
      8,
      0
    ],
    "id": "04dbd1ef-f963-4ab6-9323-b3bc6d6288f0"
  },
  {
    "timestamp": 858.39453,
    "can_id": "0x176",
    "raw_data": [
      0,
      0,
      0,
      0,
      0,
      0,
      25,
      0
    ],
    "id": "eec2005e-98e3-4955-a972-9e91d7e64435"
  },
  {
    "timestamp": 858.39752,
    "can_id": "0x176",
    "raw_data": [
      0,
      0,
      1,
      0,
      0,
      0,
      16,
      0
    ],
    "id": "af34fb7b-7dc4-4080-8399-a4ccc154daa1"
  },
  {
    "timestamp": 858.40042,
    "can_id": "0x176",
    "raw_data": [
      0,
      0,
      1,
      0,
      0,
      0,
      8,
      0
    ],
    "id": "488a0059-54c5-4f5d-a2d5-8ea705d91f16"
  },
  {
    "timestamp": 858.40349,
    "can_id": "0x176",
    "raw_data": [
      0,
      0,
      2,
      0,
      0,
      0,
      5,
      0
    ],
    "id": "275cac73-ddcf-423a-acc4-6d600cfbab6c"
  },
  {
    "timestamp": 858.40648,
    "can_id": "0x176",
    "raw_data": [
      0,
      0,
      0,
      0,
      0,
      0,
      16,
      0
    ],
    "id": "decf8d8c-cbad-4f0e-bc25-486e91acacc6"
  },
  {
    "timestamp": 858.40947,
    "can_id": "0x176",
    "raw_data": [
      0,
      0,
      1,
      0,
      0,
      0,
      16,
      0
    ],
    "id": "17c1b43d-4caa-4f35-8a4f-2ec22fb89077"
  },
  {
    "timestamp": 858.41254,
    "can_id": "0x176",
    "raw_data": [
      0,
      0,
      2,
      0,
      0,
      0,
      5,
      0
    ],
    "id": "2d417c09-dce9-4c64-966b-fbfbf49a2133"
  },
  {
    "timestamp": 858.42116,
    "can_id": "0x176",
    "raw_data": [
      0,
      0,
      0,
      0,
      0,
      0,
      5,
      0
    ],
    "id": "b58e7570-4980-411a-b61c-72a80fc8d898"
  },
  {
    "timestamp": 858.42158,
    "can_id": "0x176",
    "raw_data": [
      0,
      0,
      0,
      0,
      0,
      0,
      16,
      0
    ],
    "id": "5973c6f8-adb8-4705-84ec-6edb51342e5c"
  },
  {
    "timestamp": 858.42184,
    "can_id": "0x172",
    "raw_data": [
      0,
      0,
      1,
      0,
      105,
      584,
      0,
      0
    ],
    "id": "68ddd421-f0cf-43a4-9dba-765a1d5885bb"
  },
  {
    "timestamp": 858.4221,
    "can_id": "0x171",
    "raw_data": [
      0,
      0,
      0,
      0,
      0,
      0,
      0,
      0
    ],
    "id": "ee0b202c-6185-438d-9c15-8af1b48a45cb"
  },
  {
    "timestamp": 858.42235,
    "can_id": "0x170",
    "raw_data": [
      4,
      0,
      9,
      0,
      0,
      0,
      0,
      1
    ],
    "id": "e5aecb3c-144f-4bfa-9ab0-9080445d78cf"
  },
  {
    "timestamp": 858.42261,
    "can_id": "0x168",
    "raw_data": [
      52,
      0,
      311,
      593,
      585,
      597,
      1,
      0
    ],
    "id": "aae50340-58e6-416f-a0ed-ec2955b8153f"
  },
  {
    "timestamp": 858.42286,
    "can_id": "0x167",
    "raw_data": [
      3,
      0,
      0,
      0,
      24,
      0,
      22,
      0
    ],
    "id": "07010cb3-2f81-4421-a234-a979c410356e"
  },
  {
    "timestamp": 858.42372,
    "can_id": "0x192",
    "raw_data": [
      0,
      0,
      0,
      0,
      1,
      0,
      0,
      0
    ],
    "id": "436274a7-3759-4bd3-a1ac-adbc5886df6f"
  },
  {
    "timestamp": 858.42414,
    "can_id": "0x1",
    "raw_data": [
      0,
      0,
      0,
      0,
      146,
      5,
      0,
      0
    ],
    "id": "bbc623e7-2d55-4468-b223-ee0e22a8a497"
  },
  {
    "timestamp": 858.42457,
    "can_id": "0x176",
    "raw_data": [
      0,
      0,
      0,
      0,
      0,
      0,
      5,
      0
    ],
    "id": "419e8cef-1a91-4e32-af1d-31edce652cd3"
  },
  {
    "timestamp": 858.42764,
    "can_id": "0x176",
    "raw_data": [
      0,
      0,
      0,
      0,
      0,
      0,
      8,
      0
    ],
    "id": "61164302-a520-41a7-bf4c-617eea971110"
  },
  {
    "timestamp": 858.43592,
    "can_id": "0x176",
    "raw_data": [
      0,
      0,
      1,
      0,
      0,
      0,
      16,
      0
    ],
    "id": "8b10b8b7-101f-4b49-831c-38133bdd0e61"
  },
  {
    "timestamp": 858.4366,
    "can_id": "0x176",
    "raw_data": [
      0,
      0,
      0,
      0,
      0,
      0,
      16,
      0
    ],
    "id": "88b1b66f-a54d-4cd3-886a-79580d9c6daf"
  },
  {
    "timestamp": 858.43976,
    "can_id": "0x176",
    "raw_data": [
      0,
      0,
      597,
      597,
      0,
      0,
      5,
      0
    ],
    "id": "3195fcc9-693a-487f-848c-e5981c0e36a0"
  },
  {
    "timestamp": 858.44249,
    "can_id": "0x176",
    "raw_data": [
      0,
      0,
      0,
      0,
      0,
      0,
      16,
      0
    ],
    "id": "775097bc-76cd-4613-b7b5-9f8b0468ffcb"
  },
  {
    "timestamp": 858.44872,
    "can_id": "0x176",
    "raw_data": [
      0,
      0,
      1,
      0,
      0,
      0,
      16,
      0
    ],
    "id": "3ff3860b-741b-4fb1-aadb-09a3195381e0"
  },
  {
    "timestamp": 858.45162,
    "can_id": "0x176",
    "raw_data": [
      0,
      0,
      0,
      0,
      0,
      0,
      5,
      0
    ],
    "id": "e4d55a0f-bbd6-4662-a27f-d77585272801"
  },
  {
    "timestamp": 858.45486,
    "can_id": "0x176",
    "raw_data": [
      0,
      0,
      597,
      597,
      0,
      0,
      8,
      0
    ],
    "id": "2c657f90-66f2-4869-9528-a6b990c54ebe"
  },
  {
    "timestamp": 858.46135,
    "can_id": "0x176",
    "raw_data": [
      0,
      0,
      0,
      0,
      0,
      0,
      20,
      0
    ],
    "id": "c5a389ef-13be-4641-9c35-fb730921ead1"
  },
  {
    "timestamp": 858.46348,
    "can_id": "0x176",
    "raw_data": [
      0,
      0,
      596,
      597,
      0,
      0,
      8,
      0
    ],
    "id": "dd1e700f-98db-4281-b4a1-bbb97fd45bcf"
  },
  {
    "timestamp": 858.46664,
    "can_id": "0x176",
    "raw_data": [
      0,
      0,
      597,
      597,
      0,
      0,
      23,
      0
    ],
    "id": "4dfe1130-70f8-46be-9e79-b8f65a7789f8"
  },
  {
    "timestamp": 858.47364,
    "can_id": "0x192",
    "raw_data": [
      0,
      0,
      0,
      0,
      1,
      0,
      0,
      0
    ],
    "id": "1df9939e-5687-4a04-97fc-cb9a85a8b517"
  },
  {
    "timestamp": 858.47423,
    "can_id": "0x176",
    "raw_data": [
      0,
      0,
      0,
      0,
      0,
      0,
      1,
      0
    ],
    "id": "7944d700-c258-4811-9661-aa22f6c8dccf"
  },
  {
    "timestamp": 858.47449,
    "can_id": "0x1",
    "raw_data": [
      0,
      0,
      0,
      0,
      144,
      5,
      0,
      0
    ],
    "id": "a50e592d-9990-45cc-8eca-1f6b321160f9"
  },
  {
    "timestamp": 858.47569,
    "can_id": "0x176",
    "raw_data": [
      0,
      0,
      0,
      0,
      0,
      0,
      5,
      0
    ],
    "id": "976948cb-e9fe-4cf9-a6f0-30b54b563003"
  },
  {
    "timestamp": 858.47867,
    "can_id": "0x176",
    "raw_data": [
      0,
      0,
      0,
      0,
      0,
      0,
      16,
      0
    ],
    "id": "20c80467-792c-481a-92bd-8cca5b6f4901"
  },
  {
    "timestamp": 858.48695,
    "can_id": "0x176",
    "raw_data": [
      0,
      0,
      0,
      0,
      0,
      0,
      5,
      0
    ],
    "id": "4c53cf03-1182-4285-9595-75b5307c74a0"
  },
  {
    "timestamp": 858.48763,
    "can_id": "0x176",
    "raw_data": [
      0,
      0,
      1,
      0,
      0,
      0,
      16,
      0
    ],
    "id": "bb7fc58d-feb7-498f-8451-29e559ec9e48"
  },
  {
    "timestamp": 858.4907,
    "can_id": "0x176",
    "raw_data": [
      0,
      0,
      597,
      597,
      0,
      0,
      3,
      0
    ],
    "id": "62227a92-6802-4cb9-8243-fb81010396e6"
  },
  {
    "timestamp": 858.49369,
    "can_id": "0x176",
    "raw_data": [
      0,
      0,
      597,
      597,
      0,
      0,
      16,
      0
    ],
    "id": "c0588e15-0e0a-4f09-82ef-da80f2570d9a"
  },
  {
    "timestamp": 858.49983,
    "can_id": "0x176",
    "raw_data": [
      0,
      0,
      1,
      0,
      0,
      0,
      16,
      0
    ],
    "id": "cad7bda9-6a86-4851-9005-f60e0e74b273"
  },
  {
    "timestamp": 858.50274,
    "can_id": "0x176",
    "raw_data": [
      0,
      0,
      597,
      597,
      0,
      0,
      16,
      0
    ],
    "id": "51c72384-c546-402c-a9b8-c32f8a32935f"
  },
  {
    "timestamp": 858.50572,
    "can_id": "0x176",
    "raw_data": [
      0,
      0,
      0,
      0,
      0,
      0,
      16,
      0
    ],
    "id": "f8aaf147-e6c7-4db7-844f-4b82ab095329"
  },
  {
    "timestamp": 858.51246,
    "can_id": "0x176",
    "raw_data": [
      0,
      0,
      0,
      0,
      0,
      0,
      18,
      0
    ],
    "id": "4c3b8299-2b05-4232-bc99-78d67a7dc3b6"
  },
  {
    "timestamp": 858.51443,
    "can_id": "0x176",
    "raw_data": [
      0,
      0,
      596,
      597,
      0,
      0,
      8,
      0
    ],
    "id": "71b7da09-8ed3-4512-a3fe-dc7d65a2a73a"
  },
  {
    "timestamp": 858.51775,
    "can_id": "0x176",
    "raw_data": [
      0,
      0,
      597,
      597,
      0,
      0,
      8,
      0
    ],
    "id": "d8099837-cc0b-412d-b47d-6d7551811994"
  },
  {
    "timestamp": 858.52364,
    "can_id": "0x192",
    "raw_data": [
      0,
      0,
      0,
      0,
      1,
      0,
      0,
      0
    ],
    "id": "56bf910d-9160-4c80-9428-2c6c34026717"
  },
  {
    "timestamp": 858.52578,
    "can_id": "0x176",
    "raw_data": [
      0,
      0,
      0,
      0,
      0,
      0,
      18,
      0
    ],
    "id": "253e2b39-7727-4aa9-83e2-52861e5df0d9"
  },
  {
    "timestamp": 858.52603,
    "can_id": "0x1",
    "raw_data": [
      0,
      0,
      0,
      0,
      147,
      5,
      0,
      0
    ],
    "id": "57f5e2b8-8421-421b-8ece-4cf862f59bb9"
  },
  {
    "timestamp": 858.52629,
    "can_id": "0x172",
    "raw_data": [
      0,
      0,
      0,
      0,
      259,
      584,
      0,
      0
    ],
    "id": "743adeb1-5956-4f4d-afd0-28e9c77a5b13"
  },
  {
    "timestamp": 858.52654,
    "can_id": "0x176",
    "raw_data": [
      0,
      0,
      0,
      0,
      0,
      0,
      16,
      0
    ],
    "id": "857943ec-bf04-4797-af39-6195df3d6e3c"
  },
  {
    "timestamp": 858.5268,
    "can_id": "0x171",
    "raw_data": [
      0,
      0,
      0,
      0,
      0,
      0,
      0,
      0
    ],
    "id": "2c9f7fe4-2705-4bb1-bce6-2ae6f1c470b2"
  },
  {
    "timestamp": 858.52706,
    "can_id": "0x170",
    "raw_data": [
      4,
      0,
      9,
      0,
      0,
      0,
      0,
      1
    ],
    "id": "adcdb93f-e359-45f2-9179-1a1e4f0e8a8e"
  },
  {
    "timestamp": 858.52731,
    "can_id": "0x168",
    "raw_data": [
      52,
      0,
      311,
      593,
      584,
      597,
      1,
      0
    ],
    "id": "cadae3c0-1147-460d-9480-ba87225619a3"
  },
  {
    "timestamp": 858.52757,
    "can_id": "0x167",
    "raw_data": [
      18,
      0,
      0,
      0,
      39,
      0,
      32,
      0
    ],
    "id": "0e7359c2-22e0-4b90-9ef1-5322bf873353"
  },
  {
    "timestamp": 858.52953,
    "can_id": "0x176",
    "raw_data": [
      0,
      0,
      0,
      0,
      0,
      0,
      18,
      0
    ],
    "id": "227501a9-c5a1-4b82-b1ab-cc8401129e0e"
  },
  {
    "timestamp": 858.5326,
    "can_id": "0x176",
    "raw_data": [
      0,
      0,
      0,
      0,
      0,
      0,
      3,
      0
    ],
    "id": "fe70269f-cc99-46ff-9715-1475b403aba5"
  },
  {
    "timestamp": 858.54003,
    "can_id": "0x176",
    "raw_data": [
      0,
      0,
      1,
      0,
      0,
      0,
      5,
      0
    ],
    "id": "339bf8f5-af44-448a-af63-bf89a6f7689c"
  },
  {
    "timestamp": 858.54156,
    "can_id": "0x176",
    "raw_data": [
      0,
      0,
      0,
      0,
      0,
      0,
      16,
      0
    ],
    "id": "e45b31e5-a071-4a21-be10-2a710128a2c7"
  },
  {
    "timestamp": 858.54463,
    "can_id": "0x176",
    "raw_data": [
      0,
      0,
      0,
      0,
      0,
      0,
      18,
      0
    ],
    "id": "ae22aaf4-4a89-4386-b823-933c2fe4716e"
  },
  {
    "timestamp": 858.55249,
    "can_id": "0x176",
    "raw_data": [
      0,
      0,
      0,
      0,
      0,
      0,
      18,
      0
    ],
    "id": "d158c394-bb7b-4512-8fb0-0e798681fb2b"
  },
  {
    "timestamp": 858.55368,
    "can_id": "0x176",
    "raw_data": [
      0,
      0,
      1,
      0,
      0,
      0,
      16,
      0
    ],
    "id": "4456b385-dbf3-4ddb-905b-b5e8e91b80a9"
  },
  {
    "timestamp": 858.55667,
    "can_id": "0x176",
    "raw_data": [
      0,
      0,
      1,
      0,
      0,
      0,
      8,
      0
    ],
    "id": "9bacaa70-e9bf-4e55-9f06-ae617e23a4cc"
  },
  {
    "timestamp": 858.56503,
    "can_id": "0x176",
    "raw_data": [
      0,
      0,
      1,
      0,
      0,
      0,
      5,
      0
    ],
    "id": "d349f218-87f9-47d8-ab3e-57acfbb25dc4"
  },
  {
    "timestamp": 858.56563,
    "can_id": "0x176",
    "raw_data": [
      0,
      0,
      597,
      597,
      0,
      0,
      5,
      0
    ],
    "id": "9ea157ae-d6fb-42ff-863b-96ece4cc0bbc"
  },
  {
    "timestamp": 858.56853,
    "can_id": "0x176",
    "raw_data": [
      0,
      0,
      0,
      0,
      0,
      0,
      8,
      0
    ],
    "id": "68fddb3c-5cbe-416a-8b17-c8629f94fc9f"
  },
  {
    "timestamp": 858.57169,
    "can_id": "0x176",
    "raw_data": [
      0,
      0,
      0,
      0,
      0,
      0,
      5,
      0
    ],
    "id": "3731e819-7520-46c2-b913-6d53929695a7"
  },
  {
    "timestamp": 858.57365,
    "can_id": "0x192",
    "raw_data": [
      0,
      0,
      0,
      0,
      1,
      0,
      0,
      0
    ],
    "id": "5120901f-3f67-4bd7-95ed-3413c9a47086"
  },
  {
    "timestamp": 858.58022,
    "can_id": "0x176",
    "raw_data": [
      0,
      0,
      0,
      0,
      0,
      0,
      16,
      0
    ],
    "id": "6d64a9f4-d10d-4809-8b46-ea5c0579c9dc"
  },
  {
    "timestamp": 858.58047,
    "can_id": "0x1",
    "raw_data": [
      0,
      0,
      0,
      0,
      146,
      5,
      0,
      0
    ],
    "id": "d84474c3-efb8-4a41-b774-298a46ce2953"
  },
  {
    "timestamp": 858.58082,
    "can_id": "0x176",
    "raw_data": [
      0,
      0,
      0,
      0,
      0,
      0,
      8,
      0
    ],
    "id": "44cf5a58-38a4-4de2-ba4e-c0072cf74033"
  },
  {
    "timestamp": 858.58372,
    "can_id": "0x176",
    "raw_data": [
      0,
      0,
      0,
      0,
      0,
      0,
      8,
      0
    ],
    "id": "21202d0e-709c-44a6-b499-9ca3ad321135"
  },
  {
    "timestamp": 858.58645,
    "can_id": "0x176",
    "raw_data": [
      0,
      0,
      597,
      597,
      0,
      0,
      8,
      0
    ],
    "id": "2408d509-8b04-497e-b3b5-91548929c13f"
  },
  {
    "timestamp": 858.59319,
    "can_id": "0x176",
    "raw_data": [
      0,
      0,
      597,
      597,
      0,
      0,
      8,
      0
    ],
    "id": "ed2bb2c9-8c48-41cb-bfb0-17cd50496b51"
  },
  {
    "timestamp": 858.59566,
    "can_id": "0x176",
    "raw_data": [
      0,
      0,
      597,
      597,
      0,
      0,
      16,
      0
    ],
    "id": "f2da0314-f38b-4589-8f3c-3d9e746ef0d8"
  },
  {
    "timestamp": 858.59848,
    "can_id": "0x176",
    "raw_data": [
      0,
      0,
      0,
      0,
      0,
      0,
      20,
      0
    ],
    "id": "7bf74266-be8d-4d18-ba27-9b7ed44820a3"
  },
  {
    "timestamp": 858.60582,
    "can_id": "0x176",
    "raw_data": [
      0,
      0,
      0,
      0,
      0,
      0,
      8,
      0
    ],
    "id": "2430ec0d-bd50-4b29-a064-1653c3797d2f"
  },
  {
    "timestamp": 858.60761,
    "can_id": "0x176",
    "raw_data": [
      0,
      0,
      0,
      0,
      0,
      0,
      16,
      0
    ],
    "id": "94b9c1c8-1aef-4882-ab0a-b288f051e585"
  },
  {
    "timestamp": 858.6106,
    "can_id": "0x176",
    "raw_data": [
      0,
      0,
      0,
      0,
      0,
      0,
      8,
      0
    ],
    "id": "f1c30310-1b61-4ee7-b36e-94b95094845e"
  },
  {
    "timestamp": 858.61828,
    "can_id": "0x176",
    "raw_data": [
      0,
      0,
      1,
      0,
      0,
      0,
      5,
      0
    ],
    "id": "e1f2b14b-e2cb-4d5f-ac0c-01225eee7247"
  },
  {
    "timestamp": 858.61964,
    "can_id": "0x176",
    "raw_data": [
      0,
      0,
      1,
      0,
      0,
      0,
      5,
      0
    ],
    "id": "5b4f13db-40bd-4a4d-a3fa-6c17cb6059bb"
  },
  {
    "timestamp": 858.62263,
    "can_id": "0x176",
    "raw_data": [
      0,
      0,
      0,
      0,
      0,
      0,
      16,
      0
    ],
    "id": "719d098f-8d8e-408f-9fe6-0d59c598f2c1"
  },
  {
    "timestamp": 858.62374,
    "can_id": "0x192",
    "raw_data": [
      0,
      0,
      0,
      0,
      1,
      0,
      0,
      0
    ],
    "id": "d6cdf465-4288-493f-a2be-2bd961209b00"
  },
  {
    "timestamp": 858.62417,
    "can_id": "0x1",
    "raw_data": [
      0,
      0,
      0,
      0,
      147,
      5,
      0,
      0
    ],
    "id": "e84fff07-0552-445a-befe-5433cb67cb9c"
  },
  {
    "timestamp": 858.62553,
    "can_id": "0x176",
    "raw_data": [
      0,
      0,
      0,
      0,
      0,
      0,
      8,
      0
    ],
    "id": "6fcad7eb-aefb-4688-a613-01746d29be0a"
  },
  {
    "timestamp": 858.62579,
    "can_id": "0x172",
    "raw_data": [
      0,
      0,
      0,
      0,
      311,
      584,
      0,
      0
    ],
    "id": "5bfe3199-e45a-4d8d-ac93-a40d889c7316"
  },
  {
    "timestamp": 858.62604,
    "can_id": "0x171",
    "raw_data": [
      0,
      0,
      0,
      0,
      0,
      0,
      0,
      0
    ],
    "id": "1d4f21bf-6605-4a49-b233-e7919c1be874"
  },
  {
    "timestamp": 858.6263,
    "can_id": "0x170",
    "raw_data": [
      4,
      0,
      9,
      0,
      0,
      0,
      0,
      1
    ],
    "id": "9e96e175-3416-4567-942e-e8db74b4a57c"
  },
  {
    "timestamp": 858.62655,
    "can_id": "0x168",
    "raw_data": [
      52,
      0,
      311,
      593,
      596,
      597,
      0,
      0
    ],
    "id": "e300a217-330c-4b1d-8cf6-ac54c2cda437"
  },
  {
    "timestamp": 858.62681,
    "can_id": "0x167",
    "raw_data": [
      5,
      0,
      0,
      0,
      54,
      0,
      17,
      0
    ],
    "id": "a785758b-11ca-497a-a4a5-492cfc390dbb"
  },
  {
    "timestamp": 858.63253,
    "can_id": "0x176",
    "raw_data": [
      0,
      0,
      0,
      0,
      0,
      0,
      16,
      0
    ],
    "id": "8061c2c4-8210-4324-b647-e4e24a2cb817"
  },
  {
    "timestamp": 858.63458,
    "can_id": "0x176",
    "raw_data": [
      0,
      0,
      0,
      0,
      0,
      0,
      16,
      0
    ],
    "id": "5c7eceae-2de2-46b7-8534-d2ecde3573d6"
  },
  {
    "timestamp": 858.63765,
    "can_id": "0x176",
    "raw_data": [
      0,
      0,
      0,
      0,
      0,
      0,
      8,
      0
    ],
    "id": "965fefbf-0ddd-4803-905b-4579252ec52e"
  },
  {
    "timestamp": 858.64499,
    "can_id": "0x176",
    "raw_data": [
      0,
      0,
      0,
      0,
      0,
      0,
      8,
      0
    ],
    "id": "27617332-95ea-4564-adb9-fb0aa44dec8b"
  },
  {
    "timestamp": 858.64652,
    "can_id": "0x176",
    "raw_data": [
      0,
      0,
      597,
      597,
      0,
      0,
      18,
      0
    ],
    "id": "1d3b0deb-4d01-41d3-86a7-d7522c8d3ac9"
  },
  {
    "timestamp": 858.64959,
    "can_id": "0x176",
    "raw_data": [
      0,
      0,
      0,
      0,
      0,
      0,
      5,
      0
    ],
    "id": "d4806ecd-81d4-490c-bc69-b2c889c4d035"
  },
  {
    "timestamp": 858.65745,
    "can_id": "0x176",
    "raw_data": [
      0,
      0,
      0,
      0,
      0,
      0,
      16,
      0
    ],
    "id": "92eade73-004b-4c94-8179-7838a3b2d22f"
  },
  {
    "timestamp": 858.65855,
    "can_id": "0x176",
    "raw_data": [
      0,
      0,
      597,
      597,
      0,
      0,
      16,
      0
    ],
    "id": "bd56257d-3a59-43fc-9986-f88dbb28714b"
  },
  {
    "timestamp": 858.66171,
    "can_id": "0x176",
    "raw_data": [
      0,
      0,
      0,
      0,
      0,
      0,
      20,
      0
    ],
    "id": "376c972e-2fa1-43a7-88e9-d49e684d7134"
  },
  {
    "timestamp": 858.66453,
    "can_id": "0x176",
    "raw_data": [
      0,
      0,
      596,
      597,
      0,
      0,
      8,
      0
    ],
    "id": "4d9fe1d9-3d2b-45ee-ac13-c6dadc9bc54c"
  },
  {
    "timestamp": 858.67033,
    "can_id": "0x176",
    "raw_data": [
      0,
      0,
      1,
      0,
      0,
      0,
      20,
      0
    ],
    "id": "27155706-66c2-4eb1-9833-e3dd54076280"
  },
  {
    "timestamp": 858.67357,
    "can_id": "0x192",
    "raw_data": [
      0,
      0,
      0,
      0,
      1,
      0,
      0,
      0
    ],
    "id": "9aa97bc4-c5c3-485e-935c-318a8719c6e8"
  },
  {
    "timestamp": 858.67383,
    "can_id": "0x176",
    "raw_data": [
      0,
      0,
      595,
      597,
      0,
      0,
      5,
      0
    ],
    "id": "9cfe3245-9154-48df-90a6-82c24d658e1e"
  },
  {
    "timestamp": 858.67409,
    "can_id": "0x1",
    "raw_data": [
      0,
      0,
      0,
      0,
      147,
      5,
      0,
      0
    ],
    "id": "9f4526c0-c1bc-4471-a3f8-de46342bc973"
  },
  {
    "timestamp": 858.67656,
    "can_id": "0x176",
    "raw_data": [
      0,
      0,
      597,
      597,
      0,
      0,
      5,
      0
    ],
    "id": "dd1c6e5e-af2f-4a57-8280-cbb0c95a76d5"
  },
  {
    "timestamp": 858.6833,
    "can_id": "0x176",
    "raw_data": [
      0,
      0,
      0,
      0,
      0,
      0,
      5,
      0
    ],
    "id": "04079cf0-6375-4f4e-b67a-4082b0aff3bc"
  },
  {
    "timestamp": 858.68561,
    "can_id": "0x176",
    "raw_data": [
      0,
      0,
      0,
      0,
      0,
      0,
      5,
      0
    ],
    "id": "6a8e2a73-bd54-4d5f-b5af-c2ed0fe94285"
  },
  {
    "timestamp": 858.68859,
    "can_id": "0x176",
    "raw_data": [
      0,
      0,
      0,
      0,
      0,
      0,
      20,
      0
    ],
    "id": "87d1e9d3-e04c-4fe6-b458-9364717834b6"
  },
  {
    "timestamp": 858.69585,
    "can_id": "0x176",
    "raw_data": [
      0,
      0,
      0,
      0,
      0,
      0,
      16,
      0
    ],
    "id": "2b7ab2af-9b1a-4b68-8274-9a1d33b2c6cd"
  },
  {
    "timestamp": 858.69772,
    "can_id": "0x176",
    "raw_data": [
      0,
      0,
      0,
      0,
      0,
      0,
      3,
      0
    ],
    "id": "da9ae89c-c7b6-4013-ac2e-a12b6051e928"
  },
  {
    "timestamp": 858.70071,
    "can_id": "0x176",
    "raw_data": [
      0,
      0,
      0,
      0,
      0,
      0,
      18,
      0
    ],
    "id": "5abc492e-529a-461c-8301-917541e68c3c"
  },
  {
    "timestamp": 858.7083,
    "can_id": "0x176",
    "raw_data": [
      0,
      0,
      0,
      0,
      0,
      0,
      8,
      0
    ],
    "id": "9b9c01d4-0bff-4176-8f3f-077a323d71a4"
  },
  {
    "timestamp": 858.70967,
    "can_id": "0x176",
    "raw_data": [
      0,
      0,
      0,
      0,
      0,
      0,
      1,
      0
    ],
    "id": "eb557c58-75d4-4520-a09a-3afcc37315fb"
  },
  {
    "timestamp": 858.71249,
    "can_id": "0x176",
    "raw_data": [
      0,
      0,
      597,
      597,
      0,
      0,
      18,
      0
    ],
    "id": "8579437d-6f29-4769-a354-0e88fdc3a49e"
  },
  {
    "timestamp": 858.72076,
    "can_id": "0x176",
    "raw_data": [
      0,
      0,
      0,
      0,
      0,
      0,
      5,
      0
    ],
    "id": "eec861c8-4170-43ea-8451-31d3e0ffc0df"
  },
  {
    "timestamp": 858.7217,
    "can_id": "0x176",
    "raw_data": [
      0,
      0,
      1,
      0,
      0,
      0,
      16,
      0
    ],
    "id": "44442948-7836-4e31-8113-f25eb16400fe"
  },
  {
    "timestamp": 858.72409,
    "can_id": "0x192",
    "raw_data": [
      0,
      0,
      0,
      0,
      1,
      0,
      0,
      0
    ],
    "id": "d6978292-8850-45d9-9f4e-6e0a37dbb2c8"
  },
  {
    "timestamp": 858.72452,
    "can_id": "0x1",
    "raw_data": [
      0,
      0,
      0,
      0,
      147,
      5,
      0,
      0
    ],
    "id": "c45875c6-621b-4cf5-843d-389ad77e793f"
  },
  {
    "timestamp": 858.72767,
    "can_id": "0x176",
    "raw_data": [
      0,
      0,
      1,
      0,
      0,
      0,
      18,
      0
    ],
    "id": "875c8b8b-1fcc-4294-87da-f2e1f4294e3c"
  },
  {
    "timestamp": 858.73373,
    "can_id": "0x176",
    "raw_data": [
      0,
      0,
      0,
      0,
      0,
      0,
      8,
      0
    ],
    "id": "528fc00a-11ba-4dc3-83a6-1765989bb450"
  },
  {
    "timestamp": 858.73655,
    "can_id": "0x176",
    "raw_data": [
      0,
      0,
      0,
      0,
      0,
      0,
      3,
      0
    ],
    "id": "a779e213-9380-4b27-adb8-8c888318c036"
  },
  {
    "timestamp": 858.73971,
    "can_id": "0x176",
    "raw_data": [
      0,
      0,
      0,
      0,
      0,
      0,
      23,
      0
    ],
    "id": "a203b101-fa5f-4791-8960-23f1de35f695"
  },
  {
    "timestamp": 858.74739,
    "can_id": "0x176",
    "raw_data": [
      0,
      0,
      1,
      0,
      0,
      0,
      5,
      0
    ],
    "id": "1d92051d-79e3-4a17-ac9e-8c4468b54325"
  },
  {
    "timestamp": 858.74867,
    "can_id": "0x176",
    "raw_data": [
      0,
      0,
      0,
      0,
      0,
      0,
      20,
      0
    ],
    "id": "1f6f34ef-7528-4da7-a913-3ca1c73f0141"
  },
  {
    "timestamp": 858.75165,
    "can_id": "0x176",
    "raw_data": [
      0,
      0,
      1,
      0,
      0,
      0,
      8,
      0
    ],
    "id": "c0c512c4-8188-4a25-9202-321f29fba7cf"
  },
  {
    "timestamp": 858.75464,
    "can_id": "0x176",
    "raw_data": [
      0,
      0,
      0,
      0,
      0,
      0,
      5,
      0
    ],
    "id": "fa4fc1c6-aca9-4bb8-98e7-88e59995ad4c"
  },
  {
    "timestamp": 858.76147,
    "can_id": "0x176",
    "raw_data": [
      0,
      0,
      1,
      0,
      0,
      0,
      18,
      0
    ],
    "id": "5adc4ce1-9659-4e22-a541-3ec9702818d2"
  },
  {
    "timestamp": 858.76369,
    "can_id": "0x176",
    "raw_data": [
      0,
      0,
      0,
      0,
      0,
      0,
      8,
      0
    ],
    "id": "949611bb-951d-4105-be6c-d5f3836b3f9f"
  },
  {
    "timestamp": 858.76667,
    "can_id": "0x176",
    "raw_data": [
      0,
      0,
      0,
      0,
      0,
      0,
      5,
      0
    ],
    "id": "f9be0d66-89ce-4652-8e24-c9a864e320e9"
  },
  {
    "timestamp": 858.77358,
    "can_id": "0x192",
    "raw_data": [
      0,
      0,
      0,
      0,
      1,
      0,
      0,
      0
    ],
    "id": "d51cc1ef-8bcf-43b3-ba78-88d31f2086bd"
  },
  {
    "timestamp": 858.77606,
    "can_id": "0x176",
    "raw_data": [
      0,
      0,
      0,
      0,
      0,
      0,
      16,
      0
    ],
    "id": "f2d10319-7b56-4529-9a6b-d9aa01945a10"
  },
  {
    "timestamp": 858.77631,
    "can_id": "0x1",
    "raw_data": [
      0,
      0,
      0,
      0,
      147,
      5,
      0,
      0
    ],
    "id": "fe407f11-47cc-4956-bb5e-2de9e00bfccf"
  },
  {
    "timestamp": 858.7787,
    "can_id": "0x176",
    "raw_data": [
      0,
      0,
      597,
      597,
      0,
      0,
      16,
      0
    ],
    "id": "6310fbd5-b790-43cc-b8ef-6cc0280fa6e9"
  },
  {
    "timestamp": 858.78161,
    "can_id": "0x176",
    "raw_data": [
      0,
      0,
      0,
      0,
      0,
      0,
      5,
      0
    ],
    "id": "e9d93293-5bd4-416c-acf7-ad5eaa3e800d"
  },
  {
    "timestamp": 858.78997,
    "can_id": "0x176",
    "raw_data": [
      0,
      0,
      0,
      0,
      0,
      0,
      18,
      0
    ],
    "id": "7550edb4-26b9-4f38-b085-87773efbf26b"
  },
  {
    "timestamp": 858.79057,
    "can_id": "0x176",
    "raw_data": [
      0,
      0,
      1,
      0,
      0,
      0,
      16,
      0
    ],
    "id": "af62e9a9-8681-497e-986a-4d82a1234113"
  },
  {
    "timestamp": 858.79364,
    "can_id": "0x176",
    "raw_data": [
      0,
      0,
      1,
      0,
      0,
      0,
      8,
      0
    ],
    "id": "69e565a3-2758-47fd-a8e5-b4093542f401"
  },
  {
    "timestamp": 858.80396,
    "can_id": "0x176",
    "raw_data": [
      0,
      0,
      2,
      0,
      0,
      0,
      8,
      0
    ],
    "id": "aa94c840-10b7-4fe3-8529-1ab1ab8b22a9"
  },
  {
    "timestamp": 858.80575,
    "can_id": "0x176",
    "raw_data": [
      0,
      0,
      1,
      0,
      0,
      0,
      16,
      0
    ],
    "id": "d8896ad2-1738-46ea-a407-c1e856857fd3"
  },
  {
    "timestamp": 858.80874,
    "can_id": "0x176",
    "raw_data": [
      0,
      0,
      0,
      0,
      0,
      0,
      16,
      0
    ],
    "id": "f4479add-ee1b-4c02-9a0a-28d54dfc66d1"
  },
  {
    "timestamp": 858.81156,
    "can_id": "0x176",
    "raw_data": [
      0,
      0,
      1,
      0,
      0,
      0,
      20,
      0
    ],
    "id": "da427258-0008-473b-990d-539ec9a79567"
  },
  {
    "timestamp": 858.81796,
    "can_id": "0x176",
    "raw_data": [
      0,
      0,
      1,
      0,
      0,
      0,
      16,
      0
    ],
    "id": "f41019df-a9c5-4a89-8cca-69e919079968"
  },
  {
    "timestamp": 858.82069,
    "can_id": "0x176",
    "raw_data": [
      0,
      0,
      1,
      0,
      0,
      0,
      8,
      0
    ],
    "id": "a8ff7495-7d54-4182-8d5e-e0612fc07c01"
  },
  {
    "timestamp": 858.82367,
    "can_id": "0x192",
    "raw_data": [
      0,
      0,
      0,
      0,
      1,
      0,
      0,
      0
    ],
    "id": "38056c1c-7a10-41a5-a4ec-b01e313089e2"
  },
  {
    "timestamp": 858.82393,
    "can_id": "0x176",
    "raw_data": [
      0,
      0,
      0,
      0,
      0,
      0,
      1,
      0
    ],
    "id": "b727051d-2d99-413e-b3ab-f2d81776aafb"
  },
  {
    "timestamp": 858.82419,
    "can_id": "0x1",
    "raw_data": [
      0,
      0,
      0,
      0,
      145,
      5,
      0,
      0
    ],
    "id": "360a3014-bccb-4e4d-975e-b182aad38465"
  },
  {
    "timestamp": 858.82649,
    "can_id": "0x176",
    "raw_data": [
      0,
      0,
      0,
      0,
      0,
      0,
      16,
      0
    ],
    "id": "6264ac1d-81ef-4278-97fe-d8ec1484d89d"
  },
  {
    "timestamp": 858.83238,
    "can_id": "0x176",
    "raw_data": [
      0,
      0,
      0,
      0,
      0,
      0,
      8,
      0
    ],
    "id": "6b3f5925-8b8e-45d0-85d0-90dd2965b7e7"
  },
  {
    "timestamp": 858.83281,
    "can_id": "0x176",
    "raw_data": [
      0,
      0,
      0,
      0,
      0,
      0,
      8,
      0
    ],
    "id": "d7804766-cfff-4cb6-b79d-8f8b3c35d312"
  },
  {
    "timestamp": 858.83554,
    "can_id": "0x176",
    "raw_data": [
      0,
      0,
      597,
      597,
      0,
      0,
      8,
      0
    ],
    "id": "816f8993-e502-40d5-b815-0b72be6fc86e"
  },
  {
    "timestamp": 858.83878,
    "can_id": "0x176",
    "raw_data": [
      0,
      0,
      0,
      0,
      0,
      0,
      20,
      0
    ],
    "id": "37316136-ee2b-45ee-9587-a2899c590998"
  },
  {
    "timestamp": 858.8462,
    "can_id": "0x176",
    "raw_data": [
      0,
      0,
      1,
      0,
      0,
      0,
      16,
      0
    ],
    "id": "273afdac-501e-4676-8179-24a5a1fe3e1a"
  },
  {
    "timestamp": 858.84774,
    "can_id": "0x176",
    "raw_data": [
      0,
      0,
      0,
      0,
      0,
      0,
      16,
      0
    ],
    "id": "5916f0e6-e99a-4c98-97ff-d2b0951b9154"
  },
  {
    "timestamp": 858.85073,
    "can_id": "0x176",
    "raw_data": [
      0,
      0,
      1,
      0,
      0,
      0,
      3,
      0
    ],
    "id": "0d058e9c-4f3e-495d-8feb-cafc6009fed6"
  },
  {
    "timestamp": 858.8538,
    "can_id": "0x176",
    "raw_data": [
      0,
      0,
      0,
      0,
      0,
      0,
      3,
      0
    ],
    "id": "3c239365-6044-4451-83df-e01011e0aaba"
  },
  {
    "timestamp": 858.8602,
    "can_id": "0x176",
    "raw_data": [
      0,
      0,
      0,
      0,
      0,
      0,
      5,
      0
    ],
    "id": "77729792-d70c-4f2f-aab0-44d6072940a6"
  },
  {
    "timestamp": 858.8625,
    "can_id": "0x176",
    "raw_data": [
      0,
      0,
      0,
      0,
      0,
      0,
      16,
      0
    ],
    "id": "2639f3c7-7fec-44a9-85e4-600163994c7f"
  },
  {
    "timestamp": 858.86557,
    "can_id": "0x176",
    "raw_data": [
      0,
      0,
      0,
      0,
      0,
      0,
      18,
      0
    ],
    "id": "ab95aa72-9360-4df8-827b-431d96fb3255"
  },
  {
    "timestamp": 858.87359,
    "can_id": "0x192",
    "raw_data": [
      0,
      0,
      0,
      0,
      1,
      0,
      0,
      0
    ],
    "id": "8bf65679-b02c-44f5-995b-85300c294083"
  },
  {
    "timestamp": 858.87411,
    "can_id": "0x176",
    "raw_data": [
      0,
      0,
      1,
      0,
      0,
      0,
      8,
      0
    ],
    "id": "a4d9170f-c042-43b4-891d-b5af0bc29604"
  },
  {
    "timestamp": 858.87436,
    "can_id": "0x1",
    "raw_data": [
      0,
      0,
      0,
      0,
      147,
      5,
      0,
      0
    ],
    "id": "bed11a22-f677-4e48-8086-c8fd4e80f292"
  },
  {
    "timestamp": 858.87487,
    "can_id": "0x176",
    "raw_data": [
      0,
      0,
      1,
      0,
      0,
      0,
      16,
      0
    ],
    "id": "f07b33ec-1710-4db4-af32-3d8121e771a5"
  },
  {
    "timestamp": 858.87778,
    "can_id": "0x176",
    "raw_data": [
      0,
      0,
      0,
      0,
      0,
      0,
      16,
      0
    ],
    "id": "bebfbe0a-68f4-4c2c-961a-8ad3d65ebfe7"
  },
  {
    "timestamp": 858.88068,
    "can_id": "0x176",
    "raw_data": [
      0,
      0,
      0,
      0,
      0,
      0,
      8,
      0
    ],
    "id": "cba2ef7d-7681-4109-a6d5-891a12c21f24"
  },
  {
    "timestamp": 858.88836,
    "can_id": "0x176",
    "raw_data": [
      0,
      0,
      1,
      0,
      0,
      0,
      16,
      0
    ],
    "id": "bebae325-8bd0-49f8-8114-ce5f674c0665"
  },
  {
    "timestamp": 858.88972,
    "can_id": "0x176",
    "raw_data": [
      0,
      0,
      597,
      597,
      0,
      0,
      16,
      0
    ],
    "id": "ec90e3a7-f0f6-4b27-a427-5094f33a38c2"
  },
  {
    "timestamp": 858.89245,
    "can_id": "0x176",
    "raw_data": [
      0,
      0,
      597,
      597,
      0,
      0,
      8,
      0
    ],
    "id": "7b2b9933-29bf-40f1-bbe5-27de2858f67d"
  },
  {
    "timestamp": 858.89587,
    "can_id": "0x176",
    "raw_data": [
      0,
      0,
      0,
      0,
      0,
      0,
      18,
      0
    ],
    "id": "22f43b22-ae0a-4a4f-8d4e-2d6496e21c6a"
  },
  {
    "timestamp": 858.90252,
    "can_id": "0x176",
    "raw_data": [
      0,
      0,
      0,
      0,
      0,
      0,
      5,
      0
    ],
    "id": "280de862-8f71-4c6b-9df1-fba1004d03d2"
  },
  {
    "timestamp": 858.90466,
    "can_id": "0x176",
    "raw_data": [
      0,
      0,
      0,
      0,
      0,
      0,
      18,
      0
    ],
    "id": "4e3f347d-482a-473c-a6bd-c5f3a3dd821a"
  },
  {
    "timestamp": 858.90773,
    "can_id": "0x176",
    "raw_data": [
      0,
      0,
      597,
      597,
      0,
      0,
      8,
      0
    ],
    "id": "15d2695a-5acb-4f18-956b-a68b7bfde8de"
  },
  {
    "timestamp": 858.91054,
    "can_id": "0x176",
    "raw_data": [
      0,
      0,
      0,
      0,
      0,
      0,
      16,
      0
    ],
    "id": "d18df37a-3b12-4f5f-9142-6123a2bd6946"
  },
  {
    "timestamp": 858.91643,
    "can_id": "0x176",
    "raw_data": [
      0,
      0,
      1,
      0,
      0,
      0,
      5,
      0
    ],
    "id": "6c3c830a-55c5-4a4e-96f6-d8fb36226c2c"
  },
  {
    "timestamp": 858.91959,
    "can_id": "0x176",
    "raw_data": [
      0,
      0,
      0,
      0,
      0,
      0,
      18,
      0
    ],
    "id": "57d6b9c9-26db-4540-82fe-00580883f736"
  },
  {
    "timestamp": 858.92266,
    "can_id": "0x176",
    "raw_data": [
      0,
      0,
      1,
      0,
      0,
      0,
      18,
      0
    ],
    "id": "204db1bf-a8ed-482e-88c4-3851d5551430"
  },
  {
    "timestamp": 858.92369,
    "can_id": "0x192",
    "raw_data": [
      0,
      0,
      0,
      0,
      1,
      0,
      0,
      0
    ],
    "id": "2bc7f67c-506c-4c0e-986b-5dfd229a3fc8"
  },
  {
    "timestamp": 858.9242,
    "can_id": "0x1",
    "raw_data": [
      0,
      0,
      0,
      0,
      146,
      5,
      0,
      0
    ],
    "id": "79b8648e-7e50-447d-bb07-20d72e3b535b"
  },
  {
    "timestamp": 858.93051,
    "can_id": "0x176",
    "raw_data": [
      0,
      0,
      0,
      0,
      0,
      0,
      8,
      0
    ],
    "id": "01b1d4a8-089a-405a-b4b8-e71813151c4a"
  },
  {
    "timestamp": 858.93154,
    "can_id": "0x176",
    "raw_data": [
      0,
      0,
      597,
      597,
      0,
      0,
      8,
      0
    ],
    "id": "147941d1-ca82-4e9a-ac74-a2d44b094522"
  },
  {
    "timestamp": 858.93469,
    "can_id": "0x176",
    "raw_data": [
      0,
      0,
      0,
      0,
      0,
      0,
      18,
      0
    ],
    "id": "12c726e4-b32b-46a3-90b0-935cedd7e7af"
  },
  {
    "timestamp": 858.93777,
    "can_id": "0x176",
    "raw_data": [
      0,
      0,
      1,
      0,
      0,
      0,
      16,
      0
    ],
    "id": "e4191f48-95cb-4bbf-9476-46cc6f1e491f"
  },
  {
    "timestamp": 858.93811,
    "can_id": "0x172",
    "raw_data": [
      0,
      0,
      0,
      0,
      369,
      584,
      0,
      0
    ],
    "id": "5a292c3c-1901-4ea0-85b6-b62200a55943"
  },
  {
    "timestamp": 858.93836,
    "can_id": "0x171",
    "raw_data": [
      0,
      0,
      0,
      0,
      0,
      0,
      0,
      0
    ],
    "id": "16572236-b246-45d7-a917-7bf42b4156e2"
  },
  {
    "timestamp": 858.93862,
    "can_id": "0x170",
    "raw_data": [
      4,
      0,
      9,
      0,
      0,
      0,
      0,
      1
    ],
    "id": "30009772-3d6a-4058-a951-db48baefc91e"
  },
  {
    "timestamp": 858.93887,
    "can_id": "0x168",
    "raw_data": [
      52,
      0,
      311,
      593,
      583,
      597,
      0,
      0
    ],
    "id": "71a2e0cd-5336-447c-b9ae-36378ddb04a9"
  },
  {
    "timestamp": 858.93913,
    "can_id": "0x167",
    "raw_data": [
      16,
      0,
      0,
      0,
      39,
      0,
      7,
      0
    ],
    "id": "6fa5b603-79d0-462f-9bab-d3dcae630721"
  },
  {
    "timestamp": 858.94562,
    "can_id": "0x176",
    "raw_data": [
      0,
      0,
      0,
      0,
      0,
      0,
      8,
      0
    ],
    "id": "7dba4a92-d06d-4193-988e-f202be6824d1"
  },
  {
    "timestamp": 858.94655,
    "can_id": "0x176",
    "raw_data": [
      0,
      0,
      0,
      0,
      0,
      0,
      16,
      0
    ],
    "id": "a2687709-8bad-450d-954c-3f65e1552966"
  },
  {
    "timestamp": 858.94963,
    "can_id": "0x176",
    "raw_data": [
      0,
      0,
      0,
      0,
      0,
      0,
      20,
      0
    ],
    "id": "042c8e53-d08d-4eb2-9180-318175e0a19f"
  },
  {
    "timestamp": 858.95261,
    "can_id": "0x176",
    "raw_data": [
      0,
      0,
      0,
      0,
      0,
      0,
      8,
      0
    ],
    "id": "411a63cf-52d2-4866-bae4-6c48494b6e8a"
  },
  {
    "timestamp": 858.9585,
    "can_id": "0x176",
    "raw_data": [
      0,
      0,
      1,
      0,
      0,
      0,
      5,
      0
    ],
    "id": "dd54e096-f532-46d6-96fd-37077a51e6b7"
  },
  {
    "timestamp": 858.96157,
    "can_id": "0x176",
    "raw_data": [
      0,
      0,
      1,
      0,
      0,
      0,
      16,
      0
    ],
    "id": "ae2aa27f-e230-432a-9329-d0d4e9682633"
  },
  {
    "timestamp": 858.96456,
    "can_id": "0x176",
    "raw_data": [
      0,
      0,
      1,
      0,
      0,
      0,
      16,
      0
    ],
    "id": "6c9135d7-729c-4315-a0c0-d950678b7f3c"
  },
  {
    "timestamp": 858.96482,
    "can_id": "0x166",
    "raw_data": [
      596,
      597,
      597,
      597,
      0,
      0,
      0,
      0
    ],
    "id": "fdf3aa13-bec6-4bba-a68f-ef15e4d75b23"
  },
  {
    "timestamp": 858.96507,
    "can_id": "0x165",
    "raw_data": [
      265,
      19,
      0,
      0,
      0,
      0,
      354,
      0
    ],
    "id": "c2d9baab-967c-40e6-bd80-9726e66da7b4"
  },
  {
    "timestamp": 858.96746,
    "can_id": "0x176",
    "raw_data": [
      0,
      0,
      1,
      0,
      0,
      0,
      5,
      0
    ],
    "id": "8d62d1fd-b965-4911-9429-9d973e9966e8"
  },
  {
    "timestamp": 858.97045,
    "can_id": "0x176",
    "raw_data": [
      0,
      0,
      1,
      0,
      0,
      0,
      16,
      0
    ],
    "id": "9e6c0d5b-3655-4f66-9838-ef2be0caed59"
  },
  {
    "timestamp": 858.97907,
    "can_id": "0x176",
    "raw_data": [
      0,
      0,
      0,
      0,
      0,
      0,
      8,
      0
    ],
    "id": "e4528387-3621-454c-b21f-262449c14244"
  },
  {
    "timestamp": 858.97932,
    "can_id": "0x192",
    "raw_data": [
      0,
      0,
      0,
      0,
      1,
      0,
      0,
      0
    ],
    "id": "4c7f54d2-2da7-4637-8b90-b0181c45a8cd"
  },
  {
    "timestamp": 858.97958,
    "can_id": "0x176",
    "raw_data": [
      0,
      0,
      0,
      0,
      0,
      0,
      8,
      0
    ],
    "id": "9edd082b-bc20-4b40-a450-da55eb3a2d5e"
  },
  {
    "timestamp": 858.97983,
    "can_id": "0x1",
    "raw_data": [
      0,
      0,
      0,
      0,
      147,
      5,
      0,
      0
    ],
    "id": "979c501e-e412-414e-9642-bbf9cc0c794c"
  },
  {
    "timestamp": 858.98257,
    "can_id": "0x176",
    "raw_data": [
      0,
      0,
      0,
      0,
      0,
      0,
      16,
      0
    ],
    "id": "967ef7a9-bf38-4079-83ce-b2b2994496df"
  },
  {
    "timestamp": 858.98555,
    "can_id": "0x176",
    "raw_data": [
      0,
      0,
      0,
      0,
      0,
      0,
      20,
      0
    ],
    "id": "88f09485-9739-4f27-b796-4c82f05c71c9"
  },
  {
    "timestamp": 858.98854,
    "can_id": "0x176",
    "raw_data": [
      0,
      0,
      1,
      0,
      0,
      0,
      8,
      0
    ],
    "id": "dd977085-d4f7-4d48-9884-b7ad800afd1d"
  },
  {
    "timestamp": 858.99153,
    "can_id": "0x176",
    "raw_data": [
      0,
      0,
      0,
      0,
      0,
      0,
      5,
      0
    ],
    "id": "bc717a9e-6dc9-4de5-b4ce-a2c5744fdd9f"
  },
  {
    "timestamp": 858.99451,
    "can_id": "0x176",
    "raw_data": [
      0,
      0,
      0,
      0,
      0,
      0,
      8,
      0
    ],
    "id": "cfb16dd4-df83-4c88-b60d-53f54a8f085f"
  },
  {
    "timestamp": 858.9975,
    "can_id": "0x176",
    "raw_data": [
      0,
      0,
      1,
      0,
      0,
      0,
      8,
      0
    ],
    "id": "7101b6e9-7891-4b6e-85e8-71f510052233"
  }
]